Workbook

Sheet Табло
A2: BDS напредък и следващи действия
A4: Към | B4: =Допускания!D7 -> 46282 | F4: =HYPERLINK("BDS_Plan.docx","Отвори BDS Plan") -> Отвори BDS Plan
A6: Всеки ден | B6: Отмятай задачите в Word. Помощникът обновява това табло автоматично.
A7: В петък | B7: Попълни числата в Седмици. Пълнотата се проверява автоматично.
A8: Месечно | B8: Попълни Месеци и приключи отчетения период.
A10: Период | B10: Изпълнение | C10: Готови | D10: Общо | F10: Период | G10: Готови | H10: Остават
A11: 14 дни | B11: =C11/D11 -> 0 | C11: =SUMIFS(Задачи!$I$7:$I$38,Задачи!$B$7:$B$38,A11) -> 0 | D11: =COUNTIFS(Задачи!$B$7:$B$38,A11) -> 17 | F11: =A11 -> 14 дни | G11: =C11 -> 0 | H11: =D11-C11 -> 17
A12: 30 дни | B12: =C12/D12 -> 0 | C12: =SUMIFS(Задачи!$I$7:$I$38,Задачи!$B$7:$B$38,A12) -> 0 | D12: =COUNTIFS(Задачи!$B$7:$B$38,A12) -> 6 | F12: =A12 -> 30 дни | G12: =C12 -> 0 | H12: =D12-C12 -> 6
A13: 90 дни | B13: =C13/D13 -> 0 | C13: =SUMIFS(Задачи!$I$7:$I$38,Задачи!$B$7:$B$38,A13) -> 0 | D13: =COUNTIFS(Задачи!$B$7:$B$38,A13) -> 6 | F13: =A13 -> 90 дни | G13: =C13 -> 0 | H13: =D13-C13 -> 6
A14: След условия | B14: =C14/D14 -> 0 | C14: =SUMIFS(Задачи!$I$7:$I$38,Задачи!$B$7:$B$38,A14) -> 0 | D14: =COUNTIFS(Задачи!$B$7:$B$38,A14) -> 3 | F14: =A14 -> След условия | G14: =C14 -> 0 | H14: =D14-C14 -> 3
A16: Заявено изпълнение | B16: =SUM(Задачи!I7:I38)/32 -> 0
A17: Просрочени | B17: =COUNTIFS(Задачи!$I$7:$I$38,0,Задачи!$F$7:$F$38,"<"&Допускания!$D$7,Задачи!$E$7:$E$38,"<>Отложено") -> 0
A18: Блокирани | B18: =COUNTIFS(Задачи!$E$7:$E$38,"Блокирано") -> 0
A19: Провери условията | B19: =COUNTIFS(Задачи!$I$7:$I$38,1,Задачи!$R$7:$R$38,0) -> 0
A21: Текущ етап | B21: =IF(B11<1,"Основи и първи платени сделки",IF(B12<1,"Повторяем delivery и recurring пилоти",IF(B13<1,"Делегиране и доказване на модела","Провери финансовата устойчивост"))) -> Основи и първи платени сделки
A29: Ред | B29: Следваща задача | C29: ID | D29: Срок
A30: 1 | B30: =IF(COUNTIFS(Задачи!$S$7:$S$38,A30)=0,"Няма готова за старт задача",INDEX(Задачи!$C$7:$C$38,MATCH(A30,Задачи!$S$7:$S$38,0))) -> Реши видимостта на repository | C30: =IF(COUNTIFS(Задачи!$S$7:$S$38,A30)=0,"",INDEX(Задачи!$A$7:$A$38,MATCH(A30,Задачи!$S$7:$S$38,0))) -> T02 | D30: =IF(C30="","",INDEX(Задачи!$F$7:$F$38,MATCH(A30,Задачи!$S$7:$S$38,0))) -> 46286 | F30: Започни от | H30: =HYPERLINK("#'Задачи'!A6","Задачи") -> Задачи
A31: 2 | B31: =IF(COUNTIFS(Задачи!$S$7:$S$38,A31)=0,"Няма готова за старт задача",INDEX(Задачи!$C$7:$C$38,MATCH(A31,Задачи!$S$7:$S$38,0))) -> Започни отчитане на часове и разход | C31: =IF(COUNTIFS(Задачи!$S$7:$S$38,A31)=0,"",INDEX(Задачи!$A$7:$A$38,MATCH(A31,Задачи!$S$7:$S$38,0))) -> T04 | D31: =IF(C31="","",INDEX(Задачи!$F$7:$F$38,MATCH(A31,Задачи!$S$7:$S$38,0))) -> 46287 | F31: Промени старт | H31: =HYPERLINK("#'Допускания'!C5","Допускания") -> Допускания
A32: 3 | B32: =IF(COUNTIFS(Задачи!$S$7:$S$38,A32)=0,"Няма готова за старт задача",INDEX(Задачи!$C$7:$C$38,MATCH(A32,Задачи!$S$7:$S$38,0))) -> Въведи реалното начално състояние | C32: =IF(COUNTIFS(Задачи!$S$7:$S$38,A32)=0,"",INDEX(Задачи!$A$7:$A$38,MATCH(A32,Задачи!$S$7:$S$38,0))) -> T01 | D32: =IF(C32="","",INDEX(Задачи!$F$7:$F$38,MATCH(A32,Задачи!$S$7:$S$38,0))) -> 46286 | F32: Кого да търся | H32: =HYPERLINK("#'Лийдове'!A6","Лийдове") -> Лийдове
A35: Показател | B35: Реално | C35: Цел | D35: Прогрес | F35: Последен затворен месец | J35: =IF(COUNTIFS(Месеци!$Q$7:$Q$42,"Да",Месеци!$A$7:$A$42,"<"&DATE(YEAR(Допускания!$D$7),MONTH(Допускания!$D$7),1))=0,"",SUMPRODUCT((Месеци!$Q$7:$Q$42="Да")*(Месеци!$A$7:$A$42<DATE(YEAR(Допускания!$D$7),MONTH(Допускания!$D$7),1))*(Месеци!$A$7:$A$42=_xlfn.MAXIFS(Месеци!$A$7:$A$42,Месеци!$Q$7:$Q$42,"Да",Месеци!$A$7:$A$42,"<"&DATE(YEAR(Допускания!$D$7),MONTH(Допускания!$D$7),1)))*(ROW(Месеци!$A$7:$A$42)-6)))
A36: Приход | B36: =IF($J$35="","Няма данни",IF(NOT(ISNUMBER(INDEX(Месеци!$D$7:$D$42,$J$35))),"Няма данни",INDEX(Месеци!$D$7:$D$42,$J$35))) -> Няма данни | C36: =Допускания!D8 -> 30000 | D36: =IF(ISNUMBER(B36),B36/C36,"") | J36: =IF(J35="","Няма данни",INDEX(Месеци!$A$7:$A$42,J35)) -> Няма данни
A37: MRR | B37: =IF($J$35="","Няма данни",IF(NOT(ISNUMBER(INDEX(Месеци!$E$7:$E$42,$J$35))),"Няма данни",INDEX(Месеци!$E$7:$E$42,$J$35))) -> Няма данни | C37: =Допускания!D9 -> 15000 | D37: =IF(ISNUMBER(B37),B37/C37,"")
A38: Опер. марж | B38: =IF($J$35="","Няма данни",IF(NOT(ISNUMBER(INDEX(Месеци!$I$7:$I$42,$J$35))),"Няма данни",INDEX(Месеци!$I$7:$I$42,$J$35))) -> Няма данни | C38: =Допускания!D10 -> 0.25 | D38: =IF(ISNUMBER(B38),B38/C38,"") | F38: Устойчиви 30k | J38: =IF(ISNUMBER(B39),IF(B39>=Допускания!D12,"Потвърдено","Още не"),B39) -> Няма данни
A39: Месеци 30k | B39: =IF($J$35="","Няма данни",IF(NOT(ISNUMBER(INDEX(Месеци!$R$7:$R$42,$J$35))),"Непълни данни",INDEX(Месеци!$S$7:$S$42,$J$35))) -> Няма данни | C39: =Допускания!D12 -> 3 | D39: =IF(ISNUMBER(B39),B39/C39,"") | F39: Устойчиви 50k | J39: =IF(ISNUMBER(B40),IF(B40>=Допускания!D12,"Потвърдено","Още не"),B40) -> Няма данни
A40: Месеци 50k | B40: =IF($J$35="","Няма данни",IF(NOT(ISNUMBER(INDEX(Месеци!$T$7:$T$42,$J$35))),"Непълни данни",INDEX(Месеци!$U$7:$U$42,$J$35))) -> Няма данни | C40: =Допускания!D12 -> 3 | D40: =IF(ISNUMBER(B40),B40/C40,"")
F41: Задачите и приходът са отделни показатели.
A43: Метрика | B43: Последни 4 седмици | C43: План на седмица
A44: Prospects | B44: =IF(COUNTIFS(Седмици!$N$7:$N$162,"Да",Седмици!$A$7:$A$162,">="&Допускания!$D$7-28,Седмици!$A$7:$A$162,"<="&Допускания!$D$7)=0,"Няма данни",SUMIFS(Седмици!$B$7:$B$162,Седмици!$N$7:$N$162,"Да",Седмици!$A$7:$A$162,">="&Допускания!$D$7-28,Седмици!$A$7:$A$162,"<="&Допускания!$D$7)) -> Няма данни | C44: =ROUNDUP(INDEX(Модел!$D$66:$H$66,1,MATCH(Допускания!$D$8,Модел!$D$7:$H$7,0))/Допускания!$D$50,0) -> 157 | F44: Избран прогнозен модел | J44: =Допускания!F5 -> PLANNED Growth
A45: Call attempts | B45: =IF(COUNTIFS(Седмици!$N$7:$N$162,"Да",Седмици!$A$7:$A$162,">="&Допускания!$D$7-28,Седмици!$A$7:$A$162,"<="&Допускания!$D$7)=0,"Няма данни",SUMIFS(Седмици!$C$7:$C$162,Седмици!$N$7:$N$162,"Да",Седмици!$A$7:$A$162,">="&Допускания!$D$7-28,Седмици!$A$7:$A$162,"<="&Допускания!$D$7)) -> Няма данни | C45: =ROUNDUP(INDEX(Модел!$D$67:$H$67,1,MATCH(Допускания!$D$8,Модел!$D$7:$H$7,0))/Допускания!$D$50,0) -> 314
A46: Held meetings | B46: =IF(COUNTIFS(Седмици!$N$7:$N$162,"Да",Седмици!$A$7:$A$162,">="&Допускания!$D$7-28,Седмици!$A$7:$A$162,"<="&Допускания!$D$7)=0,"Няма данни",SUMIFS(Седмици!$F$7:$F$162,Седмици!$N$7:$N$162,"Да",Седмици!$A$7:$A$162,">="&Допускания!$D$7-28,Седмици!$A$7:$A$162,"<="&Допускания!$D$7)) -> Няма данни | C46: =ROUNDUP(INDEX(Модел!$D$63:$H$63,1,MATCH(Допускания!$D$8,Модел!$D$7:$H$7,0))/Допускания!$D$50,0) -> 13 | F46: =HYPERLINK("#'Модел'!C7","Виж финансовите сценарии") -> Виж финансовите сценарии
A47: Proposals | B47: =IF(COUNTIFS(Седмици!$N$7:$N$162,"Да",Седмици!$A$7:$A$162,">="&Допускания!$D$7-28,Седмици!$A$7:$A$162,"<="&Допускания!$D$7)=0,"Няма данни",SUMIFS(Седмици!$G$7:$G$162,Седмици!$N$7:$N$162,"Да",Седмици!$A$7:$A$162,">="&Допускания!$D$7-28,Седмици!$A$7:$A$162,"<="&Допускания!$D$7)) -> Няма данни | C47: =ROUNDUP(INDEX(Модел!$D$62:$H$62,1,MATCH(Допускания!$D$8,Модел!$D$7:$H$7,0))/Допускания!$D$50,0) -> 10
A50: Процентът отчита отметките ти. Реалните приходи, MRR и устойчивост се доказват отделно.
A51: Автоматично обновяване след 1_SETUP.cmd. Дръж двата файла и помощника в тази папка.
A53: Последна връзка | B53: Още не е активирана. Стартирай 1_SETUP.cmd.

Sheet Задачи
A2: План за изпълнение и доказателства
A4: Word управлява Готово и Дата готово. Отметката е самооценка; бележките са по избор. Не преименувай ID.
A6: ID | B6: Период | C6: Задача | D6: Отговорник | E6: Статус | F6: Срок | G6: Дата готово | H6: Бележка или доказателство | I6: Отметнато | J6: Какво остава | K6: Приоритет | L6: Зависи от 1 | M6: Зависи от 2 | N6: Impact | O6: Urgency | P6: Effort | Q6: Dependency | R6: Готови условия | S6: Ред за действие | T6: Word | U6: Критерий за готово
A7: T01 | B7: 14 дни | C7: Въведи реалното начално състояние | D7: Преслав | E7: Не е започнато | F7: =Допускания!$D$6+0 -> 46286 | I7: =IF(E7="Готово",1,0) -> 0 | J7: =IF(I7=1,IF(R7=1,"Готово по отметка","Отметнато; провери условията"),IF(E7="Отложено","Отложено",IF(R7=0,"Чака зависимост",IF(E7="Блокирано","Премахни блокирането",IF(F7<Допускания!$D$7,"Просрочено","За изпълнение"))))) -> За изпълнение | K7: =N7*O7*Q7/P7 -> 25 | N7: 5 | O7: 5 | P7: 2 | Q7: =IF(COUNTIFS($L$7:$L$38,A7)+COUNTIFS($M$7:$M$38,A7)>0,2,1) -> 2 | R7: =IF(AND(OR(L7="",COUNTIFS($A$7:$A$38,L7,$I$7:$I$38,1)=1),OR(M7="",COUNTIFS($A$7:$A$38,M7,$I$7:$I$38,1)=1)),1,0) -> 1 | S7: =IF(AND(I7=0,R7=1,E7<>"Блокирано",E7<>"Отложено"),COUNTIFS($R$7:$R$38,1,$I$7:$I$38,0,$E$7:$E$38,"<>Блокирано",$E$7:$E$38,"<>Отложено",$K$7:$K$38,">"&K7)+COUNTIFS($R$7:R7,1,$I$7:I7,0,$E$7:E7,"<>Блокирано",$E$7:E7,"<>Отложено",$K$7:K7,K7),"") -> 3 | T7: =HYPERLINK("BDS_Plan.docx#T01","T01 в Word") -> T01 в Word | U7: Последният приключен месец има приходи, MRR, разходи, плащания и активни клиенти; списък с платения backlog.
A8: T02 | B8: 14 дни | C8: Реши видимостта на repository | D8: Преслав | E8: Не е започнато | F8: =Допускания!$D$6+0 -> 46286 | I8: =IF(E8="Готово",1,0) -> 0 | J8: =IF(I8=1,IF(R8=1,"Готово по отметка","Отметнато; провери условията"),IF(E8="Отложено","Отложено",IF(R8=0,"Чака зависимост",IF(E8="Блокирано","Премахни блокирането",IF(F8<Допускания!$D$7,"Просрочено","За изпълнение"))))) -> За изпълнение | K8: =N8*O8*Q8/P8 -> 50 | N8: 5 | O8: 5 | P8: 1 | Q8: =IF(COUNTIFS($L$7:$L$38,A8)+COUNTIFS($M$7:$M$38,A8)>0,2,1) -> 2 | R8: =IF(AND(OR(L8="",COUNTIFS($A$7:$A$38,L8,$I$7:$I$38,1)=1),OR(M8="",COUNTIFS($A$7:$A$38,M8,$I$7:$I$38,1)=1)),1,0) -> 1 | S8: =IF(AND(I8=0,R8=1,E8<>"Блокирано",E8<>"Отложено"),COUNTIFS($R$7:$R$38,1,$I$7:$I$38,0,$E$7:$E$38,"<>Блокирано",$E$7:$E$38,"<>Отложено",$K$7:$K$38,">"&K8)+COUNTIFS($R$7:R8,1,$I$7:I8,0,$E$7:E8,"<>Блокирано",$E$7:E8,"<>Отложено",$K$7:K8,K8),"") -> 1 | T8: =HYPERLINK("BDS_Plan.docx#T02","T02 в Word") -> T02 в Word | U8: Документирано решение за public/private; прегледани вътрешни данни и публичният build.
A9: T03 | B9: 14 дни | C9: Подреди съществуващите възможности | D9: Преслав | E9: Не е започнато | F9: =Допускания!$D$6+1 -> 46287 | I9: =IF(E9="Готово",1,0) -> 0 | J9: =IF(I9=1,IF(R9=1,"Готово по отметка","Отметнато; провери условията"),IF(E9="Отложено","Отложено",IF(R9=0,"Чака зависимост",IF(E9="Блокирано","Премахни блокирането",IF(F9<Допускания!$D$7,"Просрочено","За изпълнение"))))) -> Чака зависимост | K9: =N9*O9*Q9/P9 -> 50 | L9: T01 | N9: 5 | O9: 5 | P9: 1 | Q9: =IF(COUNTIFS($L$7:$L$38,A9)+COUNTIFS($M$7:$M$38,A9)>0,2,1) -> 2 | R9: =IF(AND(OR(L9="",COUNTIFS($A$7:$A$38,L9,$I$7:$I$38,1)=1),OR(M9="",COUNTIFS($A$7:$A$38,M9,$I$7:$I$38,1)=1)),1,0) -> 0 | S9: =IF(AND(I9=0,R9=1,E9<>"Блокирано",E9<>"Отложено"),COUNTIFS($R$7:$R$38,1,$I$7:$I$38,0,$E$7:$E$38,"<>Блокирано",$E$7:$E$38,"<>Отложено",$K$7:$K$38,">"&K9)+COUNTIFS($R$7:R9,1,$I$7:I9,0,$E$7:E9,"<>Блокирано",$E$7:E9,"<>Отложено",$K$7:K9,K9),"") | T9: =HYPERLINK("BDS_Plan.docx#T03","T03 в Word") -> T03 в Word | U9: Всяка активна сделка има собственик, следващо действие и дата.
A10: T04 | B10: 14 дни | C10: Започни отчитане на часове и разход | D10: Преслав | E10: Не е започнато | F10: =Допускания!$D$6+1 -> 46287 | I10: =IF(E10="Готово",1,0) -> 0 | J10: =IF(I10=1,IF(R10=1,"Готово по отметка","Отметнато; провери условията"),IF(E10="Отложено","Отложено",IF(R10=0,"Чака зависимост",IF(E10="Блокирано","Премахни блокирането",IF(F10<Допускания!$D$7,"Просрочено","За изпълнение"))))) -> За изпълнение | K10: =N10*O10*Q10/P10 -> 40 | N10: 5 | O10: 4 | P10: 1 | Q10: =IF(COUNTIFS($L$7:$L$38,A10)+COUNTIFS($M$7:$M$38,A10)>0,2,1) -> 2 | R10: =IF(AND(OR(L10="",COUNTIFS($A$7:$A$38,L10,$I$7:$I$38,1)=1),OR(M10="",COUNTIFS($A$7:$A$38,M10,$I$7:$I$38,1)=1)),1,0) -> 1 | S10: =IF(AND(I10=0,R10=1,E10<>"Блокирано",E10<>"Отложено"),COUNTIFS($R$7:$R$38,1,$I$7:$I$38,0,$E$7:$E$38,"<>Блокирано",$E$7:$E$38,"<>Отложено",$K$7:$K$38,">"&K10)+COUNTIFS($R$7:R10,1,$I$7:I10,0,$E$7:E10,"<>Блокирано",$E$7:E10,"<>Отложено",$K$7:K10,K10),"") -> 2 | T10: =HYPERLINK("BDS_Plan.docx#T04","T04 в Word") -> T04 в Word | U10: Всеки активен проект и абонамент има estimate, actual hours и отговорник.
A11: T05 | B11: 14 дни | C11: Избери един ICP и водещ продукт | D11: Преслав | E11: Не е започнато | F11: =Допускания!$D$6+2 -> 46288 | I11: =IF(E11="Готово",1,0) -> 0 | J11: =IF(I11=1,IF(R11=1,"Готово по отметка","Отметнато; провери условията"),IF(E11="Отложено","Отложено",IF(R11=0,"Чака зависимост",IF(E11="Блокирано","Премахни блокирането",IF(F11<Допускания!$D$7,"Просрочено","За изпълнение"))))) -> Чака зависимост | K11: =N11*O11*Q11/P11 -> 25 | L11: T01 | M11: T03 | N11: 5 | O11: 5 | P11: 2 | Q11: =IF(COUNTIFS($L$7:$L$38,A11)+COUNTIFS($M$7:$M$38,A11)>0,2,1) -> 2 | R11: =IF(AND(OR(L11="",COUNTIFS($A$7:$A$38,L11,$I$7:$I$38,1)=1),OR(M11="",COUNTIFS($A$7:$A$38,M11,$I$7:$I$38,1)=1)),1,0) -> 0 | S11: =IF(AND(I11=0,R11=1,E11<>"Блокирано",E11<>"Отложено"),COUNTIFS($R$7:$R$38,1,$I$7:$I$38,0,$E$7:$E$38,"<>Блокирано",$E$7:$E$38,"<>Отложено",$K$7:$K$38,">"&K11)+COUNTIFS($R$7:R11,1,$I$7:I11,0,$E$7:E11,"<>Блокирано",$E$7:E11,"<>Отложено",$K$7:K11,K11),"") | T11: =HYPERLINK("BDS_Plan.docx#T05","T05 в Word") -> T05 в Word | U11: Една целева група, един измерим проблем и една повторяема оферта; изборът е подкрепен с разговори.
A12: T06 | B12: 14 дни | C12: Фиксирай обхват и минимален марж | D12: Преслав | E12: Не е започнато | F12: =Допускания!$D$6+3 -> 46289 | I12: =IF(E12="Готово",1,0) -> 0 | J12: =IF(I12=1,IF(R12=1,"Готово по отметка","Отметнато; провери условията"),IF(E12="Отложено","Отложено",IF(R12=0,"Чака зависимост",IF(E12="Блокирано","Премахни блокирането",IF(F12<Допускания!$D$7,"Просрочено","За изпълнение"))))) -> Чака зависимост | K12: =N12*O12*Q12/P12 -> 25 | L12: T04 | M12: T05 | N12: 5 | O12: 5 | P12: 2 | Q12: =IF(COUNTIFS($L$7:$L$38,A12)+COUNTIFS($M$7:$M$38,A12)>0,2,1) -> 2 | R12: =IF(AND(OR(L12="",COUNTIFS($A$7:$A$38,L12,$I$7:$I$38,1)=1),OR(M12="",COUNTIFS($A$7:$A$38,M12,$I$7:$I$38,1)=1)),1,0) -> 0 | S12: =IF(AND(I12=0,R12=1,E12<>"Блокирано",E12<>"Отложено"),COUNTIFS($R$7:$R$38,1,$I$7:$I$38,0,$E$7:$E$38,"<>Блокирано",$E$7:$E$38,"<>Отложено",$K$7:$K$38,">"&K12)+COUNTIFS($R$7:R12,1,$I$7:I12,0,$E$7:E12,"<>Блокирано",$E$7:E12,"<>Отложено",$K$7:K12,K12),"") | T12: =HYPERLINK("BDS_Plan.docx#T06","T06 в Word") -> T06 в Word | U12: Офертата има включено/изключено, лимити, приемане, срок след материали и калкулация.
A13: T07 | B13: 14 дни | C13: Обедини входящите лийдове | D13: Технически отговорник | E13: Не е започнато | F13: =Допускания!$D$6+4 -> 46290 | I13: =IF(E13="Готово",1,0) -> 0 | J13: =IF(I13=1,IF(R13=1,"Готово по отметка","Отметнато; провери условията"),IF(E13="Отложено","Отложено",IF(R13=0,"Чака зависимост",IF(E13="Блокирано","Премахни блокирането",IF(F13<Допускания!$D$7,"Просрочено","За изпълнение"))))) -> Чака зависимост | K13: =N13*O13*Q13/P13 -> 16.666667 | L13: T02 | N13: 5 | O13: 5 | P13: 3 | Q13: =IF(COUNTIFS($L$7:$L$38,A13)+COUNTIFS($M$7:$M$38,A13)>0,2,1) -> 2 | R13: =IF(AND(OR(L13="",COUNTIFS($A$7:$A$38,L13,$I$7:$I$38,1)=1),OR(M13="",COUNTIFS($A$7:$A$38,M13,$I$7:$I$38,1)=1)),1,0) -> 0 | S13: =IF(AND(I13=0,R13=1,E13<>"Блокирано",E13<>"Отложено"),COUNTIFS($R$7:$R$38,1,$I$7:$I$38,0,$E$7:$E$38,"<>Блокирано",$E$7:$E$38,"<>Отложено",$K$7:$K$38,">"&K13)+COUNTIFS($R$7:R13,1,$I$7:I13,0,$E$7:E13,"<>Блокирано",$E$7:E13,"<>Отложено",$K$7:K13,K13),"") | T13: =HYPERLINK("BDS_Plan.docx#T07","T07 в Word") -> T07 в Word | U13: Двете форми създават един проследим LeadID; има лог на неуспехите и проверка за дублиране.
A14: T08 | B14: 14 дни | C14: Провери tracking и Ads акаунтите | D14: Преслав | E14: Не е започнато | F14: =Допускания!$D$6+5 -> 46291 | I14: =IF(E14="Готово",1,0) -> 0 | J14: =IF(I14=1,IF(R14=1,"Готово по отметка","Отметнато; провери условията"),IF(E14="Отложено","Отложено",IF(R14=0,"Чака зависимост",IF(E14="Блокирано","Премахни блокирането",IF(F14<Допускания!$D$7,"Просрочено","За изпълнение"))))) -> Чака зависимост | K14: =N14*O14*Q14/P14 -> 10 | L14: T07 | N14: 4 | O14: 5 | P14: 2 | Q14: =IF(COUNTIFS($L$7:$L$38,A14)+COUNTIFS($M$7:$M$38,A14)>0,2,1) -> 1 | R14: =IF(AND(OR(L14="",COUNTIFS($A$7:$A$38,L14,$I$7:$I$38,1)=1),OR(M14="",COUNTIFS($A$7:$A$38,M14,$I$7:$I$38,1)=1)),1,0) -> 0 | S14: =IF(AND(I14=0,R14=1,E14<>"Блокирано",E14<>"Отложено"),COUNTIFS($R$7:$R$38,1,$I$7:$I$38,0,$E$7:$E$38,"<>Блокирано",$E$7:$E$38,"<>Отложено",$K$7:$K$38,">"&K14)+COUNTIFS($R$7:R14,1,$I$7:I14,0,$E$7:E14,"<>Блокирано",$E$7:E14,"<>Отложено",$K$7:K14,K14),"") | T14: =HYPERLINK("BDS_Plan.docx#T08","T08 в Word") -> T08 в Word | U14: Тестов lead се вижда еднократно в CRM и analytics; потвърдени правилни Ads IDs и consent.
A15: T09 | B15: 14 дни | C15: Добави задължителни CRM действия | D15: Sales Ops | E15: Не е започнато | F15: =Допускания!$D$6+4 -> 46290 | I15: =IF(E15="Готово",1,0) -> 0 | J15: =IF(I15=1,IF(R15=1,"Готово по отметка","Отметнато; провери условията"),IF(E15="Отложено","Отложено",IF(R15=0,"Чака зависимост",IF(E15="Блокирано","Премахни блокирането",IF(F15<Допускания!$D$7,"Просрочено","За изпълнение"))))) -> Чака зависимост | K15: =N15*O15*Q15/P15 -> 25 | L15: T03 | N15: 5 | O15: 5 | P15: 2 | Q15: =IF(COUNTIFS($L$7:$L$38,A15)+COUNTIFS($M$7:$M$38,A15)>0,2,1) -> 2 | R15: =IF(AND(OR(L15="",COUNTIFS($A$7:$A$38,L15,$I$7:$I$38,1)=1),OR(M15="",COUNTIFS($A$7:$A$38,M15,$I$7:$I$38,1)=1)),1,0) -> 0 | S15: =IF(AND(I15=0,R15=1,E15<>"Блокирано",E15<>"Отложено"),COUNTIFS($R$7:$R$38,1,$I$7:$I$38,0,$E$7:$E$38,"<>Блокирано",$E$7:$E$38,"<>Отложено",$K$7:$K$38,">"&K15)+COUNTIFS($R$7:R15,1,$I$7:I15,0,$E$7:E15,"<>Блокирано",$E$7:E15,"<>Отложено",$K$7:K15,K15),"") | T15: =HYPERLINK("BDS_Plan.docx#T09","T09 в Word") -> T09 в Word | U15: Всички активни сделки имат NextActionAt, StageEnteredAt, Owner и доказателство за етап.
A16: T10 | B16: 14 дни | C16: Въведи scoring и списък за звънене | D16: Sales Ops | E16: Не е започнато | F16: =Допускания!$D$6+5 -> 46291 | I16: =IF(E16="Готово",1,0) -> 0 | J16: =IF(I16=1,IF(R16=1,"Готово по отметка","Отметнато; провери условията"),IF(E16="Отложено","Отложено",IF(R16=0,"Чака зависимост",IF(E16="Блокирано","Премахни блокирането",IF(F16<Допускания!$D$7,"Просрочено","За изпълнение"))))) -> Чака зависимост | K16: =N16*O16*Q16/P16 -> 32 | L16: T05 | M16: T09 | N16: 4 | O16: 4 | P16: 1 | Q16: =IF(COUNTIFS($L$7:$L$38,A16)+COUNTIFS($M$7:$M$38,A16)>0,2,1) -> 2 | R16: =IF(AND(OR(L16="",COUNTIFS($A$7:$A$38,L16,$I$7:$I$38,1)=1),OR(M16="",COUNTIFS($A$7:$A$38,M16,$I$7:$I$38,1)=1)),1,0) -> 0 | S16: =IF(AND(I16=0,R16=1,E16<>"Блокирано",E16<>"Отложено"),COUNTIFS($R$7:$R$38,1,$I$7:$I$38,0,$E$7:$E$38,"<>Блокирано",$E$7:$E$38,"<>Отложено",$K$7:$K$38,">"&K16)+COUNTIFS($R$7:R16,1,$I$7:I16,0,$E$7:E16,"<>Блокирано",$E$7:E16,"<>Отложено",$K$7:K16,K16),"") | T16: =HYPERLINK("BDS_Plan.docx#T10","T10 в Word") -> T10 в Word | U16: 20 проверени лийда са оценени по 7 критерия; DNC и дубликати са изключени.
A17: T11 | B17: 14 дни | C17: Подготви 150 проверени prospects | D17: Sales Ops | E17: Не е започнато | F17: =Допускания!$D$6+8 -> 46294 | I17: =IF(E17="Готово",1,0) -> 0 | J17: =IF(I17=1,IF(R17=1,"Готово по отметка","Отметнато; провери условията"),IF(E17="Отложено","Отложено",IF(R17=0,"Чака зависимост",IF(E17="Блокирано","Премахни блокирането",IF(F17<Допускания!$D$7,"Просрочено","За изпълнение"))))) -> Чака зависимост | K17: =N17*O17*Q17/P17 -> 12.5 | L17: T10 | N17: 5 | O17: 5 | P17: 2 | Q17: =IF(COUNTIFS($L$7:$L$38,A17)+COUNTIFS($M$7:$M$38,A17)>0,2,1) -> 1 | R17: =IF(AND(OR(L17="",COUNTIFS($A$7:$A$38,L17,$I$7:$I$38,1)=1),OR(M17="",COUNTIFS($A$7:$A$38,M17,$I$7:$I$38,1)=1)),1,0) -> 0 | S17: =IF(AND(I17=0,R17=1,E17<>"Блокирано",E17<>"Отложено"),COUNTIFS($R$7:$R$38,1,$I$7:$I$38,0,$E$7:$E$38,"<>Блокирано",$E$7:$E$38,"<>Отложено",$K$7:$K$38,">"&K17)+COUNTIFS($R$7:R17,1,$I$7:I17,0,$E$7:E17,"<>Блокирано",$E$7:E17,"<>Отложено",$K$7:K17,K17),"") | T17: =HYPERLINK("BDS_Plan.docx#T11","T11 в Word") -> T11 в Word | U17: 150 уникални подходящи бизнеса със source, дата, контакт и конкретен проблем.
A18: T12 | B18: 14 дни | C18: Изпълни 300 опита за разговор | D18: Преслав | E18: Не е започнато | F18: =Допускания!$D$6+11 -> 46297 | I18: =IF(E18="Готово",1,0) -> 0 | J18: =IF(I18=1,IF(R18=1,"Готово по отметка","Отметнато; провери условията"),IF(E18="Отложено","Отложено",IF(R18=0,"Чака зависимост",IF(E18="Блокирано","Премахни блокирането",IF(F18<Допускания!$D$7,"Просрочено","За изпълнение"))))) -> Чака зависимост | K18: =N18*O18*Q18/P18 -> 16.666667 | L18: T10 | N18: 5 | O18: 5 | P18: 3 | Q18: =IF(COUNTIFS($L$7:$L$38,A18)+COUNTIFS($M$7:$M$38,A18)>0,2,1) -> 2 | R18: =IF(AND(OR(L18="",COUNTIFS($A$7:$A$38,L18,$I$7:$I$38,1)=1),OR(M18="",COUNTIFS($A$7:$A$38,M18,$I$7:$I$38,1)=1)),1,0) -> 0 | S18: =IF(AND(I18=0,R18=1,E18<>"Блокирано",E18<>"Отложено"),COUNTIFS($R$7:$R$38,1,$I$7:$I$38,0,$E$7:$E$38,"<>Блокирано",$E$7:$E$38,"<>Отложено",$K$7:$K$38,">"&K18)+COUNTIFS($R$7:R18,1,$I$7:I18,0,$E$7:E18,"<>Блокирано",$E$7:E18,"<>Отложено",$K$7:K18,K18),"") | T18: =HYPERLINK("BDS_Plan.docx#T12","T12 в Word") -> T12 в Word | U18: 300 реални опита са записани с outcome и следващо действие; DNC е спазен.
A19: T13 | B19: 14 дни | C19: Проведи 12 discovery срещи | D19: Преслав | E19: Не е започнато | F19: =Допускания!$D$6+12 -> 46298 | I19: =IF(E19="Готово",1,0) -> 0 | J19: =IF(I19=1,IF(R19=1,"Готово по отметка","Отметнато; провери условията"),IF(E19="Отложено","Отложено",IF(R19=0,"Чака зависимост",IF(E19="Блокирано","Премахни блокирането",IF(F19<Допускания!$D$7,"Просрочено","За изпълнение"))))) -> Чака зависимост | K19: =N19*O19*Q19/P19 -> 8.3333333 | L19: T05 | M19: T09 | N19: 5 | O19: 5 | P19: 3 | Q19: =IF(COUNTIFS($L$7:$L$38,A19)+COUNTIFS($M$7:$M$38,A19)>0,2,1) -> 1 | R19: =IF(AND(OR(L19="",COUNTIFS($A$7:$A$38,L19,$I$7:$I$38,1)=1),OR(M19="",COUNTIFS($A$7:$A$38,M19,$I$7:$I$38,1)=1)),1,0) -> 0 | S19: =IF(AND(I19=0,R19=1,E19<>"Блокирано",E19<>"Отложено"),COUNTIFS($R$7:$R$38,1,$I$7:$I$38,0,$E$7:$E$38,"<>Блокирано",$E$7:$E$38,"<>Отложено",$K$7:$K$38,">"&K19)+COUNTIFS($R$7:R19,1,$I$7:I19,0,$E$7:E19,"<>Блокирано",$E$7:E19,"<>Отложено",$K$7:K19,K19),"") | T19: =HYPERLINK("BDS_Plan.docx#T13","T13 в Word") -> T13 в Word | U19: 12 проведени срещи с проблем, стойност, бюджет, срок и decision maker.
A20: T14 | B20: 14 дни | C20: Изпрати 9 квалифицирани оферти | D20: Преслав | E20: Не е започнато | F20: =Допускания!$D$6+12 -> 46298 | I20: =IF(E20="Готово",1,0) -> 0 | J20: =IF(I20=1,IF(R20=1,"Готово по отметка","Отметнато; провери условията"),IF(E20="Отложено","Отложено",IF(R20=0,"Чака зависимост",IF(E20="Блокирано","Премахни блокирането",IF(F20<Допускания!$D$7,"Просрочено","За изпълнение"))))) -> Чака зависимост | K20: =N20*O20*Q20/P20 -> 12.5 | L20: T06 | M20: T09 | N20: 5 | O20: 5 | P20: 2 | Q20: =IF(COUNTIFS($L$7:$L$38,A20)+COUNTIFS($M$7:$M$38,A20)>0,2,1) -> 1 | R20: =IF(AND(OR(L20="",COUNTIFS($A$7:$A$38,L20,$I$7:$I$38,1)=1),OR(M20="",COUNTIFS($A$7:$A$38,M20,$I$7:$I$38,1)=1)),1,0) -> 0 | S20: =IF(AND(I20=0,R20=1,E20<>"Блокирано",E20<>"Отложено"),COUNTIFS($R$7:$R$38,1,$I$7:$I$38,0,$E$7:$E$38,"<>Блокирано",$E$7:$E$38,"<>Отложено",$K$7:$K$38,">"&K20)+COUNTIFS($R$7:R20,1,$I$7:I20,0,$E$7:E20,"<>Блокирано",$E$7:E20,"<>Отложено",$K$7:K20,K20),"") | T20: =HYPERLINK("BDS_Plan.docx#T14","T14 в Word") -> T14 в Word | U20: 9 прегледани оферти с точен scope, цена, MRR опция и next step.
A21: T15 | B21: 14 дни | C21: Потвърди първите 2 платени сделки | D21: Преслав | E21: Не е започнато | F21: =Допускания!$D$6+13 -> 46299 | I21: =IF(E21="Готово",1,0) -> 0 | J21: =IF(I21=1,IF(R21=1,"Готово по отметка","Отметнато; провери условията"),IF(E21="Отложено","Отложено",IF(R21=0,"Чака зависимост",IF(E21="Блокирано","Премахни блокирането",IF(F21<Допускания!$D$7,"Просрочено","За изпълнение"))))) -> Чака зависимост | K21: =N21*O21*Q21/P21 -> 25 | L21: T06 | M21: T09 | N21: 5 | O21: 5 | P21: 2 | Q21: =IF(COUNTIFS($L$7:$L$38,A21)+COUNTIFS($M$7:$M$38,A21)>0,2,1) -> 2 | R21: =IF(AND(OR(L21="",COUNTIFS($A$7:$A$38,L21,$I$7:$I$38,1)=1),OR(M21="",COUNTIFS($A$7:$A$38,M21,$I$7:$I$38,1)=1)),1,0) -> 0 | S21: =IF(AND(I21=0,R21=1,E21<>"Блокирано",E21<>"Отложено"),COUNTIFS($R$7:$R$38,1,$I$7:$I$38,0,$E$7:$E$38,"<>Блокирано",$E$7:$E$38,"<>Отложено",$K$7:$K$38,">"&K21)+COUNTIFS($R$7:R21,1,$I$7:I21,0,$E$7:E21,"<>Блокирано",$E$7:E21,"<>Отложено",$K$7:K21,K21),"") | T21: =HYPERLINK("BDS_Plan.docx#T15","T15 в Word") -> T15 в Word | U21: 2 приети оферти и получени аванси; сумите са сверени с плащания.
A22: T16 | B22: 14 дни | C22: Въведи onboarding checklist | D22: Operations | E22: Не е започнато | F22: =Допускания!$D$6+9 -> 46295 | I22: =IF(E22="Готово",1,0) -> 0 | J22: =IF(I22=1,IF(R22=1,"Готово по отметка","Отметнато; провери условията"),IF(E22="Отложено","Отложено",IF(R22=0,"Чака зависимост",IF(E22="Блокирано","Премахни блокирането",IF(F22<Допускания!$D$7,"Просрочено","За изпълнение"))))) -> Чака зависимост | K22: =N22*O22*Q22/P22 -> 16 | L22: T06 | M22: T09 | N22: 4 | O22: 4 | P22: 2 | Q22: =IF(COUNTIFS($L$7:$L$38,A22)+COUNTIFS($M$7:$M$38,A22)>0,2,1) -> 2 | R22: =IF(AND(OR(L22="",COUNTIFS($A$7:$A$38,L22,$I$7:$I$38,1)=1),OR(M22="",COUNTIFS($A$7:$A$38,M22,$I$7:$I$38,1)=1)),1,0) -> 0 | S22: =IF(AND(I22=0,R22=1,E22<>"Блокирано",E22<>"Отложено"),COUNTIFS($R$7:$R$38,1,$I$7:$I$38,0,$E$7:$E$38,"<>Блокирано",$E$7:$E$38,"<>Отложено",$K$7:$K$38,">"&K22)+COUNTIFS($R$7:R22,1,$I$7:I22,0,$E$7:E22,"<>Блокирано",$E$7:E22,"<>Отложено",$K$7:K22,K22),"") | T22: =HYPERLINK("BDS_Plan.docx#T16","T16 в Word") -> T16 в Word | U22: Един checklist изисква плащане, brief, материали, достъпи, owner и acceptance.
A23: T17 | B23: 14 дни | C23: Направи преглед на ден 14 | D23: Преслав | E23: Не е започнато | F23: =Допускания!$D$6+13 -> 46299 | I23: =IF(E23="Готово",1,0) -> 0 | J23: =IF(I23=1,IF(R23=1,"Готово по отметка","Отметнато; провери условията"),IF(E23="Отложено","Отложено",IF(R23=0,"Чака зависимост",IF(E23="Блокирано","Премахни блокирането",IF(F23<Допускания!$D$7,"Просрочено","За изпълнение"))))) -> Чака зависимост | K23: =N23*O23*Q23/P23 -> 25 | L23: T04 | M23: T12 | N23: 5 | O23: 5 | P23: 1 | Q23: =IF(COUNTIFS($L$7:$L$38,A23)+COUNTIFS($M$7:$M$38,A23)>0,2,1) -> 1 | R23: =IF(AND(OR(L23="",COUNTIFS($A$7:$A$38,L23,$I$7:$I$38,1)=1),OR(M23="",COUNTIFS($A$7:$A$38,M23,$I$7:$I$38,1)=1)),1,0) -> 0 | S23: =IF(AND(I23=0,R23=1,E23<>"Блокирано",E23<>"Отложено"),COUNTIFS($R$7:$R$38,1,$I$7:$I$38,0,$E$7:$E$38,"<>Блокирано",$E$7:$E$38,"<>Отложено",$K$7:$K$38,">"&K23)+COUNTIFS($R$7:R23,1,$I$7:I23,0,$E$7:E23,"<>Блокирано",$E$7:E23,"<>Отложено",$K$7:K23,K23),"") | T23: =HYPERLINK("BDS_Plan.docx#T17","T17 в Word") -> T17 в Word | U23: Има сравнение план/факт, основна загуба във funnel и един следващ експеримент.
A24: T18 | B24: 30 дни | C24: Изпълни и измери един пълен проект | D24: Delivery lead | E24: Не е започнато | F24: =Допускания!$D$6+20 -> 46306 | I24: =IF(E24="Готово",1,0) -> 0 | J24: =IF(I24=1,IF(R24=1,"Готово по отметка","Отметнато; провери условията"),IF(E24="Отложено","Отложено",IF(R24=0,"Чака зависимост",IF(E24="Блокирано","Премахни блокирането",IF(F24<Допускания!$D$7,"Просрочено","За изпълнение"))))) -> Чака зависимост | K24: =N24*O24*Q24/P24 -> 13.333333 | L24: T06 | M24: T16 | N24: 5 | O24: 4 | P24: 3 | Q24: =IF(COUNTIFS($L$7:$L$38,A24)+COUNTIFS($M$7:$M$38,A24)>0,2,1) -> 2 | R24: =IF(AND(OR(L24="",COUNTIFS($A$7:$A$38,L24,$I$7:$I$38,1)=1),OR(M24="",COUNTIFS($A$7:$A$38,M24,$I$7:$I$38,1)=1)),1,0) -> 0 | S24: =IF(AND(I24=0,R24=1,E24<>"Блокирано",E24<>"Отложено"),COUNTIFS($R$7:$R$38,1,$I$7:$I$38,0,$E$7:$E$38,"<>Блокирано",$E$7:$E$38,"<>Отложено",$K$7:$K$38,">"&K24)+COUNTIFS($R$7:R24,1,$I$7:I24,0,$E$7:E24,"<>Блокирано",$E$7:E24,"<>Отложено",$K$7:K24,K24),"") | T24: =HYPERLINK("BDS_Plan.docx#T18","T18 в Word") -> T18 в Word | U24: Приет проект, QA checklist, actual hours, gross margin и customer feedback.
A25: T19 | B25: 30 дни | C25: Продай 3 платени recurring пилота | D25: Преслав | E25: Не е започнато | F25: =Допускания!$D$6+29 -> 46315 | I25: =IF(E25="Готово",1,0) -> 0 | J25: =IF(I25=1,IF(R25=1,"Готово по отметка","Отметнато; провери условията"),IF(E25="Отложено","Отложено",IF(R25=0,"Чака зависимост",IF(E25="Блокирано","Премахни блокирането",IF(F25<Допускания!$D$7,"Просрочено","За изпълнение"))))) -> Чака зависимост | K25: =N25*O25*Q25/P25 -> 13.333333 | L25: T06 | M25: T15 | N25: 5 | O25: 4 | P25: 3 | Q25: =IF(COUNTIFS($L$7:$L$38,A25)+COUNTIFS($M$7:$M$38,A25)>0,2,1) -> 2 | R25: =IF(AND(OR(L25="",COUNTIFS($A$7:$A$38,L25,$I$7:$I$38,1)=1),OR(M25="",COUNTIFS($A$7:$A$38,M25,$I$7:$I$38,1)=1)),1,0) -> 0 | S25: =IF(AND(I25=0,R25=1,E25<>"Блокирано",E25<>"Отложено"),COUNTIFS($R$7:$R$38,1,$I$7:$I$38,0,$E$7:$E$38,"<>Блокирано",$E$7:$E$38,"<>Отложено",$K$7:$K$38,">"&K25)+COUNTIFS($R$7:R25,1,$I$7:I25,0,$E$7:E25,"<>Блокирано",$E$7:E25,"<>Отложено",$K$7:K25,K25),"") | T25: =HYPERLINK("BDS_Plan.docx#T19","T19 в Word") -> T19 в Word | U25: 3 клиента плащат за ясно ограничен Growth пакет; baseline и отчет са уговорени.
A26: T20 | B26: 30 дни | C26: Въведи седмичен operating review | D26: Operations | E26: Не е започнато | F26: =Допускания!$D$6+20 -> 46306 | I26: =IF(E26="Готово",1,0) -> 0 | J26: =IF(I26=1,IF(R26=1,"Готово по отметка","Отметнато; провери условията"),IF(E26="Отложено","Отложено",IF(R26=0,"Чака зависимост",IF(E26="Блокирано","Премахни блокирането",IF(F26<Допускания!$D$7,"Просрочено","За изпълнение"))))) -> Чака зависимост | K26: =N26*O26*Q26/P26 -> 32 | L26: T01 | M26: T09 | N26: 4 | O26: 4 | P26: 1 | Q26: =IF(COUNTIFS($L$7:$L$38,A26)+COUNTIFS($M$7:$M$38,A26)>0,2,1) -> 2 | R26: =IF(AND(OR(L26="",COUNTIFS($A$7:$A$38,L26,$I$7:$I$38,1)=1),OR(M26="",COUNTIFS($A$7:$A$38,M26,$I$7:$I$38,1)=1)),1,0) -> 0 | S26: =IF(AND(I26=0,R26=1,E26<>"Блокирано",E26<>"Отложено"),COUNTIFS($R$7:$R$38,1,$I$7:$I$38,0,$E$7:$E$38,"<>Блокирано",$E$7:$E$38,"<>Отложено",$K$7:$K$38,">"&K26)+COUNTIFS($R$7:R26,1,$I$7:I26,0,$E$7:E26,"<>Блокирано",$E$7:E26,"<>Отложено",$K$7:K26,K26),"") | T26: =HYPERLINK("BDS_Plan.docx#T20","T20 в Word") -> T20 в Word | U26: Попълнени седмични показатели и месечен P&L; 13-седмичен cash outlook се преглежда.
A27: T21 | B27: 30 дни | C27: Документирай и предай първия процес | D27: Преслав | E27: Не е започнато | F27: =Допускания!$D$6+29 -> 46315 | I27: =IF(E27="Готово",1,0) -> 0 | J27: =IF(I27=1,IF(R27=1,"Готово по отметка","Отметнато; провери условията"),IF(E27="Отложено","Отложено",IF(R27=0,"Чака зависимост",IF(E27="Блокирано","Премахни блокирането",IF(F27<Допускания!$D$7,"Просрочено","За изпълнение"))))) -> Чака зависимост | K27: =N27*O27*Q27/P27 -> 20 | L27: T18 | N27: 5 | O27: 4 | P27: 2 | Q27: =IF(COUNTIFS($L$7:$L$38,A27)+COUNTIFS($M$7:$M$38,A27)>0,2,1) -> 2 | R27: =IF(AND(OR(L27="",COUNTIFS($A$7:$A$38,L27,$I$7:$I$38,1)=1),OR(M27="",COUNTIFS($A$7:$A$38,M27,$I$7:$I$38,1)=1)),1,0) -> 0 | S27: =IF(AND(I27=0,R27=1,E27<>"Блокирано",E27<>"Отложено"),COUNTIFS($R$7:$R$38,1,$I$7:$I$38,0,$E$7:$E$38,"<>Блокирано",$E$7:$E$38,"<>Отложено",$K$7:$K$38,">"&K27)+COUNTIFS($R$7:R27,1,$I$7:I27,0,$E$7:E27,"<>Блокирано",$E$7:E27,"<>Отложено",$K$7:K27,K27),"") | T27: =HYPERLINK("BDS_Plan.docx#T21","T21 в Word") -> T21 в Word | U27: Друг човек изпълнява процеса по SOP; Преслав проверява изхода, а не всяка стъпка.
A28: T22 | B28: 30 дни | C28: Провери trigger за Sales Ops | D28: Преслав | E28: Не е започнато | F28: =Допускания!$D$6+29 -> 46315 | I28: =IF(E28="Готово",1,0) -> 0 | J28: =IF(I28=1,IF(R28=1,"Готово по отметка","Отметнато; провери условията"),IF(E28="Отложено","Отложено",IF(R28=0,"Чака зависимост",IF(E28="Блокирано","Премахни блокирането",IF(F28<Допускания!$D$7,"Просрочено","За изпълнение"))))) -> Чака зависимост | K28: =N28*O28*Q28/P28 -> 6 | L28: T20 | M28: T21 | N28: 4 | O28: 3 | P28: 2 | Q28: =IF(COUNTIFS($L$7:$L$38,A28)+COUNTIFS($M$7:$M$38,A28)>0,2,1) -> 1 | R28: =IF(AND(OR(L28="",COUNTIFS($A$7:$A$38,L28,$I$7:$I$38,1)=1),OR(M28="",COUNTIFS($A$7:$A$38,M28,$I$7:$I$38,1)=1)),1,0) -> 0 | S28: =IF(AND(I28=0,R28=1,E28<>"Блокирано",E28<>"Отложено"),COUNTIFS($R$7:$R$38,1,$I$7:$I$38,0,$E$7:$E$38,"<>Блокирано",$E$7:$E$38,"<>Отложено",$K$7:$K$38,">"&K28)+COUNTIFS($R$7:R28,1,$I$7:I28,0,$E$7:E28,"<>Блокирано",$E$7:E28,"<>Отложено",$K$7:K28,K28),"") | T28: =HYPERLINK("BDS_Plan.docx#T22","T22 в Word") -> T22 в Word | U28: Измерени admin часове, SOP, KPI и бюджет; записано решение дали hiring trigger е изпълнен.
A29: T23 | B29: 30 дни | C29: Провери delivery капацитета | D29: Delivery lead | E29: Не е започнато | F29: =Допускания!$D$6+29 -> 46315 | I29: =IF(E29="Готово",1,0) -> 0 | J29: =IF(I29=1,IF(R29=1,"Готово по отметка","Отметнато; провери условията"),IF(E29="Отложено","Отложено",IF(R29=0,"Чака зависимост",IF(E29="Блокирано","Премахни блокирането",IF(F29<Допускания!$D$7,"Просрочено","За изпълнение"))))) -> Чака зависимост | K29: =N29*O29*Q29/P29 -> 20 | L29: T18 | M29: T20 | N29: 5 | O29: 4 | P29: 2 | Q29: =IF(COUNTIFS($L$7:$L$38,A29)+COUNTIFS($M$7:$M$38,A29)>0,2,1) -> 2 | R29: =IF(AND(OR(L29="",COUNTIFS($A$7:$A$38,L29,$I$7:$I$38,1)=1),OR(M29="",COUNTIFS($A$7:$A$38,M29,$I$7:$I$38,1)=1)),1,0) -> 0 | S29: =IF(AND(I29=0,R29=1,E29<>"Блокирано",E29<>"Отложено"),COUNTIFS($R$7:$R$38,1,$I$7:$I$38,0,$E$7:$E$38,"<>Блокирано",$E$7:$E$38,"<>Отложено",$K$7:$K$38,">"&K29)+COUNTIFS($R$7:R29,1,$I$7:I29,0,$E$7:E29,"<>Блокирано",$E$7:E29,"<>Отложено",$K$7:K29,K29),"") | T29: =HYPERLINK("BDS_Plan.docx#T23","T23 в Word") -> T23 в Word | U29: Платеният backlog, наличните часове и сроковете са видими; contractor има бюджет и QA.
A30: T24 | B30: 90 дни | C30: Измери 2 renewal цикъла | D30: Customer Success | E30: Не е започнато | F30: =Допускания!$D$6+74 -> 46360 | I30: =IF(E30="Готово",1,0) -> 0 | J30: =IF(I30=1,IF(R30=1,"Готово по отметка","Отметнато; провери условията"),IF(E30="Отложено","Отложено",IF(R30=0,"Чака зависимост",IF(E30="Блокирано","Премахни блокирането",IF(F30<Допускания!$D$7,"Просрочено","За изпълнение"))))) -> Чака зависимост | K30: =N30*O30*Q30/P30 -> 13.333333 | L30: T19 | M30: T20 | N30: 5 | O30: 4 | P30: 3 | Q30: =IF(COUNTIFS($L$7:$L$38,A30)+COUNTIFS($M$7:$M$38,A30)>0,2,1) -> 2 | R30: =IF(AND(OR(L30="",COUNTIFS($A$7:$A$38,L30,$I$7:$I$38,1)=1),OR(M30="",COUNTIFS($A$7:$A$38,M30,$I$7:$I$38,1)=1)),1,0) -> 0 | S30: =IF(AND(I30=0,R30=1,E30<>"Блокирано",E30<>"Отложено"),COUNTIFS($R$7:$R$38,1,$I$7:$I$38,0,$E$7:$E$38,"<>Блокирано",$E$7:$E$38,"<>Отложено",$K$7:$K$38,">"&K30)+COUNTIFS($R$7:R30,1,$I$7:I30,0,$E$7:E30,"<>Блокирано",$E$7:E30,"<>Отложено",$K$7:K30,K30),"") | T30: =HYPERLINK("BDS_Plan.docx#T24","T24 в Word") -> T24 в Word | U30: 3 пилота са минали два цикъла; известни са retention, часове и gross margin.
A31: T25 | B31: 90 дни | C31: Въведи subscription и retention регистър | D31: Customer Success | E31: Не е започнато | F31: =Допускания!$D$6+44 -> 46330 | I31: =IF(E31="Готово",1,0) -> 0 | J31: =IF(I31=1,IF(R31=1,"Готово по отметка","Отметнато; провери условията"),IF(E31="Отложено","Отложено",IF(R31=0,"Чака зависимост",IF(E31="Блокирано","Премахни блокирането",IF(F31<Допускания!$D$7,"Просрочено","За изпълнение"))))) -> Чака зависимост | K31: =N31*O31*Q31/P31 -> 20 | L31: T19 | M31: T21 | N31: 5 | O31: 4 | P31: 2 | Q31: =IF(COUNTIFS($L$7:$L$38,A31)+COUNTIFS($M$7:$M$38,A31)>0,2,1) -> 2 | R31: =IF(AND(OR(L31="",COUNTIFS($A$7:$A$38,L31,$I$7:$I$38,1)=1),OR(M31="",COUNTIFS($A$7:$A$38,M31,$I$7:$I$38,1)=1)),1,0) -> 0 | S31: =IF(AND(I31=0,R31=1,E31<>"Блокирано",E31<>"Отложено"),COUNTIFS($R$7:$R$38,1,$I$7:$I$38,0,$E$7:$E$38,"<>Блокирано",$E$7:$E$38,"<>Отложено",$K$7:$K$38,">"&K31)+COUNTIFS($R$7:R31,1,$I$7:I31,0,$E$7:E31,"<>Блокирано",$E$7:E31,"<>Отложено",$K$7:K31,K31),"") | T31: =HYPERLINK("BDS_Plan.docx#T25","T25 в Word") -> T25 в Word | U31: Всеки абонамент има owner, цена, дата за плащане, scope, последен резултат и риск.
A32: T26 | B32: 90 дни | C32: Делегирай delivery и customer success | D32: Operations | E32: Не е започнато | F32: =Допускания!$D$6+59 -> 46345 | I32: =IF(E32="Готово",1,0) -> 0 | J32: =IF(I32=1,IF(R32=1,"Готово по отметка","Отметнато; провери условията"),IF(E32="Отложено","Отложено",IF(R32=0,"Чака зависимост",IF(E32="Блокирано","Премахни блокирането",IF(F32<Допускания!$D$7,"Просрочено","За изпълнение"))))) -> Чака зависимост | K32: =N32*O32*Q32/P32 -> 10 | L32: T21 | M32: T23 | N32: 5 | O32: 3 | P32: 3 | Q32: =IF(COUNTIFS($L$7:$L$38,A32)+COUNTIFS($M$7:$M$38,A32)>0,2,1) -> 2 | R32: =IF(AND(OR(L32="",COUNTIFS($A$7:$A$38,L32,$I$7:$I$38,1)=1),OR(M32="",COUNTIFS($A$7:$A$38,M32,$I$7:$I$38,1)=1)),1,0) -> 0 | S32: =IF(AND(I32=0,R32=1,E32<>"Блокирано",E32<>"Отложено"),COUNTIFS($R$7:$R$38,1,$I$7:$I$38,0,$E$7:$E$38,"<>Блокирано",$E$7:$E$38,"<>Отложено",$K$7:$K$38,">"&K32)+COUNTIFS($R$7:R32,1,$I$7:I32,0,$E$7:E32,"<>Блокирано",$E$7:E32,"<>Отложено",$K$7:K32,K32),"") | T32: =HYPERLINK("BDS_Plan.docx#T26","T26 в Word") -> T26 в Word | U32: Има owner и заместник за QA, onboarding, support и renewal; ескалациите са описани.
A33: T27 | B33: 90 дни | C33: Докажи повторяемост на продукта | D33: Преслав | E33: Не е започнато | F33: =Допускания!$D$6+74 -> 46360 | I33: =IF(E33="Готово",1,0) -> 0 | J33: =IF(I33=1,IF(R33=1,"Готово по отметка","Отметнато; провери условията"),IF(E33="Отложено","Отложено",IF(R33=0,"Чака зависимост",IF(E33="Блокирано","Премахни блокирането",IF(F33<Допускания!$D$7,"Просрочено","За изпълнение"))))) -> Чака зависимост | K33: =N33*O33*Q33/P33 -> 20 | L33: T18 | M33: T24 | N33: 5 | O33: 4 | P33: 2 | Q33: =IF(COUNTIFS($L$7:$L$38,A33)+COUNTIFS($M$7:$M$38,A33)>0,2,1) -> 2 | R33: =IF(AND(OR(L33="",COUNTIFS($A$7:$A$38,L33,$I$7:$I$38,1)=1),OR(M33="",COUNTIFS($A$7:$A$38,M33,$I$7:$I$38,1)=1)),1,0) -> 0 | S33: =IF(AND(I33=0,R33=1,E33<>"Блокирано",E33<>"Отложено"),COUNTIFS($R$7:$R$38,1,$I$7:$I$38,0,$E$7:$E$38,"<>Блокирано",$E$7:$E$38,"<>Отложено",$K$7:$K$38,">"&K33)+COUNTIFS($R$7:R33,1,$I$7:I33,0,$E$7:E33,"<>Блокирано",$E$7:E33,"<>Отложено",$K$7:K33,K33),"") | T33: =HYPERLINK("BDS_Plan.docx#T27","T27 в Word") -> T27 в Word | U33: Поне два delivery цикъла и два renewal цикъла са измерени; офертата покрива маржа.
A34: T28 | B34: 90 дни | C34: Тествай следващ пазар | D34: Sales lead | E34: Не е започнато | F34: =Допускания!$D$6+89 -> 46375 | I34: =IF(E34="Готово",1,0) -> 0 | J34: =IF(I34=1,IF(R34=1,"Готово по отметка","Отметнато; провери условията"),IF(E34="Отложено","Отложено",IF(R34=0,"Чака зависимост",IF(E34="Блокирано","Премахни блокирането",IF(F34<Допускания!$D$7,"Просрочено","За изпълнение"))))) -> Чака зависимост | K34: =N34*O34*Q34/P34 -> 8 | L34: T27 | M34: T23 | N34: 4 | O34: 3 | P34: 3 | Q34: =IF(COUNTIFS($L$7:$L$38,A34)+COUNTIFS($M$7:$M$38,A34)>0,2,1) -> 2 | R34: =IF(AND(OR(L34="",COUNTIFS($A$7:$A$38,L34,$I$7:$I$38,1)=1),OR(M34="",COUNTIFS($A$7:$A$38,M34,$I$7:$I$38,1)=1)),1,0) -> 0 | S34: =IF(AND(I34=0,R34=1,E34<>"Блокирано",E34<>"Отложено"),COUNTIFS($R$7:$R$38,1,$I$7:$I$38,0,$E$7:$E$38,"<>Блокирано",$E$7:$E$38,"<>Отложено",$K$7:$K$38,">"&K34)+COUNTIFS($R$7:R34,1,$I$7:I34,0,$E$7:E34,"<>Блокирано",$E$7:E34,"<>Отложено",$K$7:K34,K34),"") | T34: =HYPERLINK("BDS_Plan.docx#T28","T28 в Word") -> T28 в Word | U34: Нов регион или партньорски канал е тестван с ограничен бюджет и измерен CAC.
A35: T29 | B35: 90 дни | C35: Направи 10 дневен тест без основателя | D35: Operations | E35: Не е започнато | F35: =Допускания!$D$6+89 -> 46375 | I35: =IF(E35="Готово",1,0) -> 0 | J35: =IF(I35=1,IF(R35=1,"Готово по отметка","Отметнато; провери условията"),IF(E35="Отложено","Отложено",IF(R35=0,"Чака зависимост",IF(E35="Блокирано","Премахни блокирането",IF(F35<Допускания!$D$7,"Просрочено","За изпълнение"))))) -> Чака зависимост | K35: =N35*O35*Q35/P35 -> 13.333333 | L35: T25 | M35: T26 | N35: 5 | O35: 4 | P35: 3 | Q35: =IF(COUNTIFS($L$7:$L$38,A35)+COUNTIFS($M$7:$M$38,A35)>0,2,1) -> 2 | R35: =IF(AND(OR(L35="",COUNTIFS($A$7:$A$38,L35,$I$7:$I$38,1)=1),OR(M35="",COUNTIFS($A$7:$A$38,M35,$I$7:$I$38,1)=1)),1,0) -> 0 | S35: =IF(AND(I35=0,R35=1,E35<>"Блокирано",E35<>"Отложено"),COUNTIFS($R$7:$R$38,1,$I$7:$I$38,0,$E$7:$E$38,"<>Блокирано",$E$7:$E$38,"<>Отложено",$K$7:$K$38,">"&K35)+COUNTIFS($R$7:R35,1,$I$7:I35,0,$E$7:E35,"<>Блокирано",$E$7:E35,"<>Отложено",$K$7:K35,K35),"") | T35: =HYPERLINK("BDS_Plan.docx#T29","T29 в Word") -> T29 в Word | U35: 10 работни дни без задължително участие на Преслав във всяка продажба, доставка и инцидент.
A36: T30 | B36: След условия | C36: Потвърди устойчиви 30 000 евро | D36: Преслав | E36: Не е започнато | F36: =Допускания!$D$6+179 -> 46465 | I36: =IF(E36="Готово",1,0) -> 0 | J36: =IF(I36=1,IF(R36=1,"Готово по отметка","Отметнато; провери условията"),IF(E36="Отложено","Отложено",IF(R36=0,"Чака зависимост",IF(E36="Блокирано","Премахни блокирането",IF(F36<Допускания!$D$7,"Просрочено","За изпълнение"))))) -> Чака зависимост | K36: =N36*O36*Q36/P36 -> 25 | L36: T27 | M36: T29 | N36: 5 | O36: 5 | P36: 2 | Q36: =IF(COUNTIFS($L$7:$L$38,A36)+COUNTIFS($M$7:$M$38,A36)>0,2,1) -> 2 | R36: =IF(AND(OR(L36="",COUNTIFS($A$7:$A$38,L36,$I$7:$I$38,1)=1),OR(M36="",COUNTIFS($A$7:$A$38,M36,$I$7:$I$38,1)=1)),1,0) -> 0 | S36: =IF(AND(I36=0,R36=1,E36<>"Блокирано",E36<>"Отложено"),COUNTIFS($R$7:$R$38,1,$I$7:$I$38,0,$E$7:$E$38,"<>Блокирано",$E$7:$E$38,"<>Отложено",$K$7:$K$38,">"&K36)+COUNTIFS($R$7:R36,1,$I$7:I36,0,$E$7:E36,"<>Блокирано",$E$7:E36,"<>Отложено",$K$7:K36,K36),"") | T36: =HYPERLINK("BDS_Plan.docx#T30","T30 в Word") -> T30 в Word | U36: 3 последователни приключени месеца: приход ≥30k, MRR ≥15k, марж ≥25%, навреме ≥90%, 0 SLA backlog и автономна операция.
A37: T31 | B37: След условия | C37: Подготви капацитет за 50 000 евро | D37: Преслав | E37: Не е започнато | F37: =Допускания!$D$6+269 -> 46555 | I37: =IF(E37="Готово",1,0) -> 0 | J37: =IF(I37=1,IF(R37=1,"Готово по отметка","Отметнато; провери условията"),IF(E37="Отложено","Отложено",IF(R37=0,"Чака зависимост",IF(E37="Блокирано","Премахни блокирането",IF(F37<Допускания!$D$7,"Просрочено","За изпълнение"))))) -> Чака зависимост | K37: =N37*O37*Q37/P37 -> 8 | L37: T30 | M37: T28 | N37: 4 | O37: 3 | P37: 3 | Q37: =IF(COUNTIFS($L$7:$L$38,A37)+COUNTIFS($M$7:$M$38,A37)>0,2,1) -> 2 | R37: =IF(AND(OR(L37="",COUNTIFS($A$7:$A$38,L37,$I$7:$I$38,1)=1),OR(M37="",COUNTIFS($A$7:$A$38,M37,$I$7:$I$38,1)=1)),1,0) -> 0 | S37: =IF(AND(I37=0,R37=1,E37<>"Блокирано",E37<>"Отложено"),COUNTIFS($R$7:$R$38,1,$I$7:$I$38,0,$E$7:$E$38,"<>Блокирано",$E$7:$E$38,"<>Отложено",$K$7:$K$38,">"&K37)+COUNTIFS($R$7:R37,1,$I$7:I37,0,$E$7:E37,"<>Блокирано",$E$7:E37,"<>Отложено",$K$7:K37,K37),"") | T37: =HYPERLINK("BDS_Plan.docx#T31","T31 в Word") -> T31 в Word | U37: Планът покрива около 582 productive hours и 111 уникални recurring клиента при валидиран Growth модел.
A38: T32 | B38: След условия | C38: Потвърди устойчиви 50 000 евро | D38: Преслав | E38: Не е започнато | F38: =Допускания!$D$6+359 -> 46645 | I38: =IF(E38="Готово",1,0) -> 0 | J38: =IF(I38=1,IF(R38=1,"Готово по отметка","Отметнато; провери условията"),IF(E38="Отложено","Отложено",IF(R38=0,"Чака зависимост",IF(E38="Блокирано","Премахни блокирането",IF(F38<Допускания!$D$7,"Просрочено","За изпълнение"))))) -> Чака зависимост | K38: =N38*O38*Q38/P38 -> 10 | L38: T31 | N38: 5 | O38: 4 | P38: 2 | Q38: =IF(COUNTIFS($L$7:$L$38,A38)+COUNTIFS($M$7:$M$38,A38)>0,2,1) -> 1 | R38: =IF(AND(OR(L38="",COUNTIFS($A$7:$A$38,L38,$I$7:$I$38,1)=1),OR(M38="",COUNTIFS($A$7:$A$38,M38,$I$7:$I$38,1)=1)),1,0) -> 0 | S38: =IF(AND(I38=0,R38=1,E38<>"Блокирано",E38<>"Отложено"),COUNTIFS($R$7:$R$38,1,$I$7:$I$38,0,$E$7:$E$38,"<>Блокирано",$E$7:$E$38,"<>Отложено",$K$7:$K$38,">"&K38)+COUNTIFS($R$7:R38,1,$I$7:I38,0,$E$7:E38,"<>Блокирано",$E$7:E38,"<>Отложено",$K$7:K38,K38),"") | T38: =HYPERLINK("BDS_Plan.docx#T32","T32 в Word") -> T32 в Word | U38: 3 последователни месеца ≥50k, MRR ≥30k и същите условия за марж, качество и автономност.

Sheet Седмици
A2: Седмичен отчет
A4: Попълвай в петък. Празно = липсва данни. Въведи 0, ако стойността наистина е нула.
A6: Седмица от | B6: Verified prospects | C6: Опити за разговор | D6: Контакти | E6: SQL | F6: Проведени срещи | G6: Изпратени оферти | H6: Приети сделки | I6: Получени аванси € | J6: Delivery часа | K6: Founder часа | L6: Просрочени действия | M6: Бележка | N6: Отчетът е пълен
A7: =Допускания!$D$6-WEEKDAY(Допускания!$D$6,2)+1+0 -> 46286 | N7: =IF(COUNT(B7:L7)=11,"Да","Не") -> Не
A8: =Допускания!$D$6-WEEKDAY(Допускания!$D$6,2)+1+7 -> 46293 | N8: =IF(COUNT(B8:L8)=11,"Да","Не") -> Не
A9: =Допускания!$D$6-WEEKDAY(Допускания!$D$6,2)+1+14 -> 46300 | N9: =IF(COUNT(B9:L9)=11,"Да","Не") -> Не
A10: =Допускания!$D$6-WEEKDAY(Допускания!$D$6,2)+1+21 -> 46307 | N10: =IF(COUNT(B10:L10)=11,"Да","Не") -> Не
A11: =Допускания!$D$6-WEEKDAY(Допускания!$D$6,2)+1+28 -> 46314 | N11: =IF(COUNT(B11:L11)=11,"Да","Не") -> Не
A12: =Допускания!$D$6-WEEKDAY(Допускания!$D$6,2)+1+35 -> 46321 | N12: =IF(COUNT(B12:L12)=11,"Да","Не") -> Не
A13: =Допускания!$D$6-WEEKDAY(Допускания!$D$6,2)+1+42 -> 46328 | N13: =IF(COUNT(B13:L13)=11,"Да","Не") -> Не
A14: =Допускания!$D$6-WEEKDAY(Допускания!$D$6,2)+1+49 -> 46335 | N14: =IF(COUNT(B14:L14)=11,"Да","Не") -> Не
A15: =Допускания!$D$6-WEEKDAY(Допускания!$D$6,2)+1+56 -> 46342 | N15: =IF(COUNT(B15:L15)=11,"Да","Не") -> Не
A16: =Допускания!$D$6-WEEKDAY(Допускания!$D$6,2)+1+63 -> 46349 | N16: =IF(COUNT(B16:L16)=11,"Да","Не") -> Не
A17: =Допускания!$D$6-WEEKDAY(Допускания!$D$6,2)+1+70 -> 46356 | N17: =IF(COUNT(B17:L17)=11,"Да","Не") -> Не
A18: =Допускания!$D$6-WEEKDAY(Допускания!$D$6,2)+1+77 -> 46363 | N18: =IF(COUNT(B18:L18)=11,"Да","Не") -> Не
A19: =Допускания!$D$6-WEEKDAY(Допускания!$D$6,2)+1+84 -> 46370 | N19: =IF(COUNT(B19:L19)=11,"Да","Не") -> Не
A20: =Допускания!$D$6-WEEKDAY(Допускания!$D$6,2)+1+91 -> 46377 | N20: =IF(COUNT(B20:L20)=11,"Да","Не") -> Не
A21: =Допускания!$D$6-WEEKDAY(Допускания!$D$6,2)+1+98 -> 46384 | N21: =IF(COUNT(B21:L21)=11,"Да","Не") -> Не
A22: =Допускания!$D$6-WEEKDAY(Допускания!$D$6,2)+1+105 -> 46391 | N22: =IF(COUNT(B22:L22)=11,"Да","Не") -> Не
A23: =Допускания!$D$6-WEEKDAY(Допускания!$D$6,2)+1+112 -> 46398 | N23: =IF(COUNT(B23:L23)=11,"Да","Не") -> Не
A24: =Допускания!$D$6-WEEKDAY(Допускания!$D$6,2)+1+119 -> 46405 | N24: =IF(COUNT(B24:L24)=11,"Да","Не") -> Не
A25: =Допускания!$D$6-WEEKDAY(Допускания!$D$6,2)+1+126 -> 46412 | N25: =IF(COUNT(B25:L25)=11,"Да","Не") -> Не
A26: =Допускания!$D$6-WEEKDAY(Допускания!$D$6,2)+1+133 -> 46419 | N26: =IF(COUNT(B26:L26)=11,"Да","Не") -> Не
A27: =Допускания!$D$6-WEEKDAY(Допускания!$D$6,2)+1+140 -> 46426 | N27: =IF(COUNT(B27:L27)=11,"Да","Не") -> Не
A28: =Допускания!$D$6-WEEKDAY(Допускания!$D$6,2)+1+147 -> 46433 | N28: =IF(COUNT(B28:L28)=11,"Да","Не") -> Не
A29: =Допускания!$D$6-WEEKDAY(Допускания!$D$6,2)+1+154 -> 46440 | N29: =IF(COUNT(B29:L29)=11,"Да","Не") -> Не
A30: =Допускания!$D$6-WEEKDAY(Допускания!$D$6,2)+1+161 -> 46447 | N30: =IF(COUNT(B30:L30)=11,"Да","Не") -> Не
A31: =Допускания!$D$6-WEEKDAY(Допускания!$D$6,2)+1+168 -> 46454 | N31: =IF(COUNT(B31:L31)=11,"Да","Не") -> Не
A32: =Допускания!$D$6-WEEKDAY(Допускания!$D$6,2)+1+175 -> 46461 | N32: =IF(COUNT(B32:L32)=11,"Да","Не") -> Не
A33: =Допускания!$D$6-WEEKDAY(Допускания!$D$6,2)+1+182 -> 46468 | N33: =IF(COUNT(B33:L33)=11,"Да","Не") -> Не
A34: =Допускания!$D$6-WEEKDAY(Допускания!$D$6,2)+1+189 -> 46475 | N34: =IF(COUNT(B34:L34)=11,"Да","Не") -> Не
A35: =Допускания!$D$6-WEEKDAY(Допускания!$D$6,2)+1+196 -> 46482 | N35: =IF(COUNT(B35:L35)=11,"Да","Не") -> Не
A36: =Допускания!$D$6-WEEKDAY(Допускания!$D$6,2)+1+203 -> 46489 | N36: =IF(COUNT(B36:L36)=11,"Да","Не") -> Не
A37: =Допускания!$D$6-WEEKDAY(Допускания!$D$6,2)+1+210 -> 46496 | N37: =IF(COUNT(B37:L37)=11,"Да","Не") -> Не
A38: =Допускания!$D$6-WEEKDAY(Допускания!$D$6,2)+1+217 -> 46503 | N38: =IF(COUNT(B38:L38)=11,"Да","Не") -> Не
A39: =Допускания!$D$6-WEEKDAY(Допускания!$D$6,2)+1+224 -> 46510 | N39: =IF(COUNT(B39:L39)=11,"Да","Не") -> Не
A40: =Допускания!$D$6-WEEKDAY(Допускания!$D$6,2)+1+231 -> 46517 | N40: =IF(COUNT(B40:L40)=11,"Да","Не") -> Не
A41: =Допускания!$D$6-WEEKDAY(Допускания!$D$6,2)+1+238 -> 46524 | N41: =IF(COUNT(B41:L41)=11,"Да","Не") -> Не
A42: =Допускания!$D$6-WEEKDAY(Допускания!$D$6,2)+1+245 -> 46531 | N42: =IF(COUNT(B42:L42)=11,"Да","Не") -> Не
A43: =Допускания!$D$6-WEEKDAY(Допускания!$D$6,2)+1+252 -> 46538 | N43: =IF(COUNT(B43:L43)=11,"Да","Не") -> Не
A44: =Допускания!$D$6-WEEKDAY(Допускания!$D$6,2)+1+259 -> 46545 | N44: =IF(COUNT(B44:L44)=11,"Да","Не") -> Не
A45: =Допускания!$D$6-WEEKDAY(Допускания!$D$6,2)+1+266 -> 46552 | N45: =IF(COUNT(B45:L45)=11,"Да","Не") -> Не
A46: =Допускания!$D$6-WEEKDAY(Допускания!$D$6,2)+1+273 -> 46559 | N46: =IF(COUNT(B46:L46)=11,"Да","Не") -> Не
A47: =Допускания!$D$6-WEEKDAY(Допускания!$D$6,2)+1+280 -> 46566 | N47: =IF(COUNT(B47:L47)=11,"Да","Не") -> Не
A48: =Допускания!$D$6-WEEKDAY(Допускания!$D$6,2)+1+287 -> 46573 | N48: =IF(COUNT(B48:L48)=11,"Да","Не") -> Не
A49: =Допускания!$D$6-WEEKDAY(Допускания!$D$6,2)+1+294 -> 46580 | N49: =IF(COUNT(B49:L49)=11,"Да","Не") -> Не
A50: =Допускания!$D$6-WEEKDAY(Допускания!$D$6,2)+1+301 -> 46587 | N50: =IF(COUNT(B50:L50)=11,"Да","Не") -> Не
A51: =Допускания!$D$6-WEEKDAY(Допускания!$D$6,2)+1+308 -> 46594 | N51: =IF(COUNT(B51:L51)=11,"Да","Не") -> Не
A52: =Допускания!$D$6-WEEKDAY(Допускания!$D$6,2)+1+315 -> 46601 | N52: =IF(COUNT(B52:L52)=11,"Да","Не") -> Не
A53: =Допускания!$D$6-WEEKDAY(Допускания!$D$6,2)+1+322 -> 46608 | N53: =IF(COUNT(B53:L53)=11,"Да","Не") -> Не
A54: =Допускания!$D$6-WEEKDAY(Допускания!$D$6,2)+1+329 -> 46615 | N54: =IF(COUNT(B54:L54)=11,"Да","Не") -> Не
A55: =Допускания!$D$6-WEEKDAY(Допускания!$D$6,2)+1+336 -> 46622 | N55: =IF(COUNT(B55:L55)=11,"Да","Не") -> Не
A56: =Допускания!$D$6-WEEKDAY(Допускания!$D$6,2)+1+343 -> 46629 | N56: =IF(COUNT(B56:L56)=11,"Да","Не") -> Не
A57: =Допускания!$D$6-WEEKDAY(Допускания!$D$6,2)+1+350 -> 46636 | N57: =IF(COUNT(B57:L57)=11,"Да","Не") -> Не
A58: =Допускания!$D$6-WEEKDAY(Допускания!$D$6,2)+1+357 -> 46643 | N58: =IF(COUNT(B58:L58)=11,"Да","Не") -> Не
A59: =Допускания!$D$6-WEEKDAY(Допускания!$D$6,2)+1+364 -> 46650 | N59: =IF(COUNT(B59:L59)=11,"Да","Не") -> Не
A60: =Допускания!$D$6-WEEKDAY(Допускания!$D$6,2)+1+371 -> 46657 | N60: =IF(COUNT(B60:L60)=11,"Да","Не") -> Не
A61: =Допускания!$D$6-WEEKDAY(Допускания!$D$6,2)+1+378 -> 46664 | N61: =IF(COUNT(B61:L61)=11,"Да","Не") -> Не
A62: =Допускания!$D$6-WEEKDAY(Допускания!$D$6,2)+1+385 -> 46671 | N62: =IF(COUNT(B62:L62)=11,"Да","Не") -> Не
A63: =Допускания!$D$6-WEEKDAY(Допускания!$D$6,2)+1+392 -> 46678 | N63: =IF(COUNT(B63:L63)=11,"Да","Не") -> Не
A64: =Допускания!$D$6-WEEKDAY(Допускания!$D$6,2)+1+399 -> 46685 | N64: =IF(COUNT(B64:L64)=11,"Да","Не") -> Не
A65: =Допускания!$D$6-WEEKDAY(Допускания!$D$6,2)+1+406 -> 46692 | N65: =IF(COUNT(B65:L65)=11,"Да","Не") -> Не
A66: =Допускания!$D$6-WEEKDAY(Допускания!$D$6,2)+1+413 -> 46699 | N66: =IF(COUNT(B66:L66)=11,"Да","Не") -> Не
A67: =Допускания!$D$6-WEEKDAY(Допускания!$D$6,2)+1+420 -> 46706 | N67: =IF(COUNT(B67:L67)=11,"Да","Не") -> Не
A68: =Допускания!$D$6-WEEKDAY(Допускания!$D$6,2)+1+427 -> 46713 | N68: =IF(COUNT(B68:L68)=11,"Да","Не") -> Не
A69: =Допускания!$D$6-WEEKDAY(Допускания!$D$6,2)+1+434 -> 46720 | N69: =IF(COUNT(B69:L69)=11,"Да","Не") -> Не
A70: =Допускания!$D$6-WEEKDAY(Допускания!$D$6,2)+1+441 -> 46727 | N70: =IF(COUNT(B70:L70)=11,"Да","Не") -> Не
A71: =Допускания!$D$6-WEEKDAY(Допускания!$D$6,2)+1+448 -> 46734 | N71: =IF(COUNT(B71:L71)=11,"Да","Не") -> Не
A72: =Допускания!$D$6-WEEKDAY(Допускания!$D$6,2)+1+455 -> 46741 | N72: =IF(COUNT(B72:L72)=11,"Да","Не") -> Не
A73: =Допускания!$D$6-WEEKDAY(Допускания!$D$6,2)+1+462 -> 46748 | N73: =IF(COUNT(B73:L73)=11,"Да","Не") -> Не
A74: =Допускания!$D$6-WEEKDAY(Допускания!$D$6,2)+1+469 -> 46755 | N74: =IF(COUNT(B74:L74)=11,"Да","Не") -> Не
A75: =Допускания!$D$6-WEEKDAY(Допускания!$D$6,2)+1+476 -> 46762 | N75: =IF(COUNT(B75:L75)=11,"Да","Не") -> Не
A76: =Допускания!$D$6-WEEKDAY(Допускания!$D$6,2)+1+483 -> 46769 | N76: =IF(COUNT(B76:L76)=11,"Да","Не") -> Не
A77: =Допускания!$D$6-WEEKDAY(Допускания!$D$6,2)+1+490 -> 46776 | N77: =IF(COUNT(B77:L77)=11,"Да","Не") -> Не
A78: =Допускания!$D$6-WEEKDAY(Допускания!$D$6,2)+1+497 -> 46783 | N78: =IF(COUNT(B78:L78)=11,"Да","Не") -> Не
A79: =Допускания!$D$6-WEEKDAY(Допускания!$D$6,2)+1+504 -> 46790 | N79: =IF(COUNT(B79:L79)=11,"Да","Не") -> Не
A80: =Допускания!$D$6-WEEKDAY(Допускания!$D$6,2)+1+511 -> 46797 | N80: =IF(COUNT(B80:L80)=11,"Да","Не") -> Не
A81: =Допускания!$D$6-WEEKDAY(Допускания!$D$6,2)+1+518 -> 46804 | N81: =IF(COUNT(B81:L81)=11,"Да","Не") -> Не
A82: =Допускания!$D$6-WEEKDAY(Допускания!$D$6,2)+1+525 -> 46811 | N82: =IF(COUNT(B82:L82)=11,"Да","Не") -> Не
A83: =Допускания!$D$6-WEEKDAY(Допускания!$D$6,2)+1+532 -> 46818 | N83: =IF(COUNT(B83:L83)=11,"Да","Не") -> Не
A84: =Допускания!$D$6-WEEKDAY(Допускания!$D$6,2)+1+539 -> 46825 | N84: =IF(COUNT(B84:L84)=11,"Да","Не") -> Не
A85: =Допускания!$D$6-WEEKDAY(Допускания!$D$6,2)+1+546 -> 46832 | N85: =IF(COUNT(B85:L85)=11,"Да","Не") -> Не
A86: =Допускания!$D$6-WEEKDAY(Допускания!$D$6,2)+1+553 -> 46839 | N86: =IF(COUNT(B86:L86)=11,"Да","Не") -> Не
A87: =Допускания!$D$6-WEEKDAY(Допускания!$D$6,2)+1+560 -> 46846 | N87: =IF(COUNT(B87:L87)=11,"Да","Не") -> Не
A88: =Допускания!$D$6-WEEKDAY(Допускания!$D$6,2)+1+567 -> 46853 | N88: =IF(COUNT(B88:L88)=11,"Да","Не") -> Не
A89: =Допускания!$D$6-WEEKDAY(Допускания!$D$6,2)+1+574 -> 46860 | N89: =IF(COUNT(B89:L89)=11,"Да","Не") -> Не
A90: =Допускания!$D$6-WEEKDAY(Допускания!$D$6,2)+1+581 -> 46867 | N90: =IF(COUNT(B90:L90)=11,"Да","Не") -> Не
A91: =Допускания!$D$6-WEEKDAY(Допускания!$D$6,2)+1+588 -> 46874 | N91: =IF(COUNT(B91:L91)=11,"Да","Не") -> Не
A92: =Допускания!$D$6-WEEKDAY(Допускания!$D$6,2)+1+595 -> 46881 | N92: =IF(COUNT(B92:L92)=11,"Да","Не") -> Не
A93: =Допускания!$D$6-WEEKDAY(Допускания!$D$6,2)+1+602 -> 46888 | N93: =IF(COUNT(B93:L93)=11,"Да","Не") -> Не
A94: =Допускания!$D$6-WEEKDAY(Допускания!$D$6,2)+1+609 -> 46895 | N94: =IF(COUNT(B94:L94)=11,"Да","Не") -> Не
A95: =Допускания!$D$6-WEEKDAY(Допускания!$D$6,2)+1+616 -> 46902 | N95: =IF(COUNT(B95:L95)=11,"Да","Не") -> Не
A96: =Допускания!$D$6-WEEKDAY(Допускания!$D$6,2)+1+623 -> 46909 | N96: =IF(COUNT(B96:L96)=11,"Да","Не") -> Не
A97: =Допускания!$D$6-WEEKDAY(Допускания!$D$6,2)+1+630 -> 46916 | N97: =IF(COUNT(B97:L97)=11,"Да","Не") -> Не
A98: =Допускания!$D$6-WEEKDAY(Допускания!$D$6,2)+1+637 -> 46923 | N98: =IF(COUNT(B98:L98)=11,"Да","Не") -> Не
A99: =Допускания!$D$6-WEEKDAY(Допускания!$D$6,2)+1+644 -> 46930 | N99: =IF(COUNT(B99:L99)=11,"Да","Не") -> Не
A100: =Допускания!$D$6-WEEKDAY(Допускания!$D$6,2)+1+651 -> 46937 | N100: =IF(COUNT(B100:L100)=11,"Да","Не") -> Не
A101: =Допускания!$D$6-WEEKDAY(Допускания!$D$6,2)+1+658 -> 46944 | N101: =IF(COUNT(B101:L101)=11,"Да","Не") -> Не
A102: =Допускания!$D$6-WEEKDAY(Допускания!$D$6,2)+1+665 -> 46951 | N102: =IF(COUNT(B102:L102)=11,"Да","Не") -> Не
A103: =Допускания!$D$6-WEEKDAY(Допускания!$D$6,2)+1+672 -> 46958 | N103: =IF(COUNT(B103:L103)=11,"Да","Не") -> Не
...

Sheet Месеци
A2: Реални месечни резултати
A4: Приход = признат за периода. MRR = договорен месечен run rate. Получените плащания са отделно.
A6: Месец | B6: Еднократен приход | C6: Абонаментен приход | D6: Общ приход | E6: MRR край | F6: Преки разходи | G6: Оpex с founder pay | H6: Опер. печалба | I6: Опер. марж | J6: Плащания получени | K6: Активни recurring клиенти | L6: Доставени проекти | M6: Навреме проекти | N6: Навреме % | O6: SLA просрочени | P6: Работи без основателя | Q6: Месец приключен | R6: Покрива 30k | S6: Поредни 30k | T6: Покрива 50k | U6: Поредни 50k
A7: =EDATE(DATE(YEAR(Допускания!$D$6),MONTH(Допускания!$D$6),1),-1) -> 46235 | D7: =IF(COUNT(B7:C7)<2,"",SUM(B7:C7)) | H7: =IF(OR(NOT(ISNUMBER(D7)),COUNT(F7:G7)<2),"",D7-SUM(F7:G7)) | I7: =IF(OR(NOT(ISNUMBER(H7)),D7=0),"",H7/D7) | N7: =IF(COUNT(L7:M7)<2,"",IF(L7=0,IF(M7=0,1,""),M7/L7)) | P7: Не | Q7: Не | R7: =IF(AND(Q7="Да",EOMONTH(A7,0)<Допускания!$D$7,COUNT(B7:C7)=2,COUNT(E7:G7)=3,COUNT(L7:M7)=2,ISNUMBER(O7),L7>=M7,ISNUMBER(I7),ISNUMBER(N7)),IF(AND(D7>=30000,E7>=15000,I7>=Допускания!$D$10,N7>=Допускания!$D$11,O7=0,P7="Да"),1,0),"") | S7: =IF(NOT(ISNUMBER(R7)),"",IF(R7=1,1,0)) | T7: =IF(AND(Q7="Да",EOMONTH(A7,0)<Допускания!$D$7,COUNT(B7:C7)=2,COUNT(E7:G7)=3,COUNT(L7:M7)=2,ISNUMBER(O7),L7>=M7,ISNUMBER(I7),ISNUMBER(N7)),IF(AND(D7>=50000,E7>=30000,I7>=Допускания!$D$10,N7>=Допускания!$D$11,O7=0,P7="Да"),1,0),"") | U7: =IF(NOT(ISNUMBER(T7)),"",IF(T7=1,1,0))
A8: =EDATE(DATE(YEAR(Допускания!$D$6),MONTH(Допускания!$D$6),1),0) -> 46266 | D8: =IF(COUNT(B8:C8)<2,"",SUM(B8:C8)) | H8: =IF(OR(NOT(ISNUMBER(D8)),COUNT(F8:G8)<2),"",D8-SUM(F8:G8)) | I8: =IF(OR(NOT(ISNUMBER(H8)),D8=0),"",H8/D8) | N8: =IF(COUNT(L8:M8)<2,"",IF(L8=0,IF(M8=0,1,""),M8/L8)) | P8: Не | Q8: Не | R8: =IF(AND(Q8="Да",EOMONTH(A8,0)<Допускания!$D$7,COUNT(B8:C8)=2,COUNT(E8:G8)=3,COUNT(L8:M8)=2,ISNUMBER(O8),L8>=M8,ISNUMBER(I8),ISNUMBER(N8)),IF(AND(D8>=30000,E8>=15000,I8>=Допускания!$D$10,N8>=Допускания!$D$11,O8=0,P8="Да"),1,0),"") | S8: =IF(NOT(ISNUMBER(R8)),"",IF(R8=1,IF(ISNUMBER(S7),S7+1,1),0)) | T8: =IF(AND(Q8="Да",EOMONTH(A8,0)<Допускания!$D$7,COUNT(B8:C8)=2,COUNT(E8:G8)=3,COUNT(L8:M8)=2,ISNUMBER(O8),L8>=M8,ISNUMBER(I8),ISNUMBER(N8)),IF(AND(D8>=50000,E8>=30000,I8>=Допускания!$D$10,N8>=Допускания!$D$11,O8=0,P8="Да"),1,0),"") | U8: =IF(NOT(ISNUMBER(T8)),"",IF(T8=1,IF(ISNUMBER(U7),U7+1,1),0))
A9: =EDATE(DATE(YEAR(Допускания!$D$6),MONTH(Допускания!$D$6),1),1) -> 46296 | D9: =IF(COUNT(B9:C9)<2,"",SUM(B9:C9)) | H9: =IF(OR(NOT(ISNUMBER(D9)),COUNT(F9:G9)<2),"",D9-SUM(F9:G9)) | I9: =IF(OR(NOT(ISNUMBER(H9)),D9=0),"",H9/D9) | N9: =IF(COUNT(L9:M9)<2,"",IF(L9=0,IF(M9=0,1,""),M9/L9)) | P9: Не | Q9: Не | R9: =IF(AND(Q9="Да",EOMONTH(A9,0)<Допускания!$D$7,COUNT(B9:C9)=2,COUNT(E9:G9)=3,COUNT(L9:M9)=2,ISNUMBER(O9),L9>=M9,ISNUMBER(I9),ISNUMBER(N9)),IF(AND(D9>=30000,E9>=15000,I9>=Допускания!$D$10,N9>=Допускания!$D$11,O9=0,P9="Да"),1,0),"") | S9: =IF(NOT(ISNUMBER(R9)),"",IF(R9=1,IF(ISNUMBER(S8),S8+1,1),0)) | T9: =IF(AND(Q9="Да",EOMONTH(A9,0)<Допускания!$D$7,COUNT(B9:C9)=2,COUNT(E9:G9)=3,COUNT(L9:M9)=2,ISNUMBER(O9),L9>=M9,ISNUMBER(I9),ISNUMBER(N9)),IF(AND(D9>=50000,E9>=30000,I9>=Допускания!$D$10,N9>=Допускания!$D$11,O9=0,P9="Да"),1,0),"") | U9: =IF(NOT(ISNUMBER(T9)),"",IF(T9=1,IF(ISNUMBER(U8),U8+1,1),0))
A10: =EDATE(DATE(YEAR(Допускания!$D$6),MONTH(Допускания!$D$6),1),2) -> 46327 | D10: =IF(COUNT(B10:C10)<2,"",SUM(B10:C10)) | H10: =IF(OR(NOT(ISNUMBER(D10)),COUNT(F10:G10)<2),"",D10-SUM(F10:G10)) | I10: =IF(OR(NOT(ISNUMBER(H10)),D10=0),"",H10/D10) | N10: =IF(COUNT(L10:M10)<2,"",IF(L10=0,IF(M10=0,1,""),M10/L10)) | P10: Не | Q10: Не | R10: =IF(AND(Q10="Да",EOMONTH(A10,0)<Допускания!$D$7,COUNT(B10:C10)=2,COUNT(E10:G10)=3,COUNT(L10:M10)=2,ISNUMBER(O10),L10>=M10,ISNUMBER(I10),ISNUMBER(N10)),IF(AND(D10>=30000,E10>=15000,I10>=Допускания!$D$10,N10>=Допускания!$D$11,O10=0,P10="Да"),1,0),"") | S10: =IF(NOT(ISNUMBER(R10)),"",IF(R10=1,IF(ISNUMBER(S9),S9+1,1),0)) | T10: =IF(AND(Q10="Да",EOMONTH(A10,0)<Допускания!$D$7,COUNT(B10:C10)=2,COUNT(E10:G10)=3,COUNT(L10:M10)=2,ISNUMBER(O10),L10>=M10,ISNUMBER(I10),ISNUMBER(N10)),IF(AND(D10>=50000,E10>=30000,I10>=Допускания!$D$10,N10>=Допускания!$D$11,O10=0,P10="Да"),1,0),"") | U10: =IF(NOT(ISNUMBER(T10)),"",IF(T10=1,IF(ISNUMBER(U9),U9+1,1),0))
A11: =EDATE(DATE(YEAR(Допускания!$D$6),MONTH(Допускания!$D$6),1),3) -> 46357 | D11: =IF(COUNT(B11:C11)<2,"",SUM(B11:C11)) | H11: =IF(OR(NOT(ISNUMBER(D11)),COUNT(F11:G11)<2),"",D11-SUM(F11:G11)) | I11: =IF(OR(NOT(ISNUMBER(H11)),D11=0),"",H11/D11) | N11: =IF(COUNT(L11:M11)<2,"",IF(L11=0,IF(M11=0,1,""),M11/L11)) | P11: Не | Q11: Не | R11: =IF(AND(Q11="Да",EOMONTH(A11,0)<Допускания!$D$7,COUNT(B11:C11)=2,COUNT(E11:G11)=3,COUNT(L11:M11)=2,ISNUMBER(O11),L11>=M11,ISNUMBER(I11),ISNUMBER(N11)),IF(AND(D11>=30000,E11>=15000,I11>=Допускания!$D$10,N11>=Допускания!$D$11,O11=0,P11="Да"),1,0),"") | S11: =IF(NOT(ISNUMBER(R11)),"",IF(R11=1,IF(ISNUMBER(S10),S10+1,1),0)) | T11: =IF(AND(Q11="Да",EOMONTH(A11,0)<Допускания!$D$7,COUNT(B11:C11)=2,COUNT(E11:G11)=3,COUNT(L11:M11)=2,ISNUMBER(O11),L11>=M11,ISNUMBER(I11),ISNUMBER(N11)),IF(AND(D11>=50000,E11>=30000,I11>=Допускания!$D$10,N11>=Допускания!$D$11,O11=0,P11="Да"),1,0),"") | U11: =IF(NOT(ISNUMBER(T11)),"",IF(T11=1,IF(ISNUMBER(U10),U10+1,1),0))
A12: =EDATE(DATE(YEAR(Допускания!$D$6),MONTH(Допускания!$D$6),1),4) -> 46388 | D12: =IF(COUNT(B12:C12)<2,"",SUM(B12:C12)) | H12: =IF(OR(NOT(ISNUMBER(D12)),COUNT(F12:G12)<2),"",D12-SUM(F12:G12)) | I12: =IF(OR(NOT(ISNUMBER(H12)),D12=0),"",H12/D12) | N12: =IF(COUNT(L12:M12)<2,"",IF(L12=0,IF(M12=0,1,""),M12/L12)) | P12: Не | Q12: Не | R12: =IF(AND(Q12="Да",EOMONTH(A12,0)<Допускания!$D$7,COUNT(B12:C12)=2,COUNT(E12:G12)=3,COUNT(L12:M12)=2,ISNUMBER(O12),L12>=M12,ISNUMBER(I12),ISNUMBER(N12)),IF(AND(D12>=30000,E12>=15000,I12>=Допускания!$D$10,N12>=Допускания!$D$11,O12=0,P12="Да"),1,0),"") | S12: =IF(NOT(ISNUMBER(R12)),"",IF(R12=1,IF(ISNUMBER(S11),S11+1,1),0)) | T12: =IF(AND(Q12="Да",EOMONTH(A12,0)<Допускания!$D$7,COUNT(B12:C12)=2,COUNT(E12:G12)=3,COUNT(L12:M12)=2,ISNUMBER(O12),L12>=M12,ISNUMBER(I12),ISNUMBER(N12)),IF(AND(D12>=50000,E12>=30000,I12>=Допускания!$D$10,N12>=Допускания!$D$11,O12=0,P12="Да"),1,0),"") | U12: =IF(NOT(ISNUMBER(T12)),"",IF(T12=1,IF(ISNUMBER(U11),U11+1,1),0))
A13: =EDATE(DATE(YEAR(Допускания!$D$6),MONTH(Допускания!$D$6),1),5) -> 46419 | D13: =IF(COUNT(B13:C13)<2,"",SUM(B13:C13)) | H13: =IF(OR(NOT(ISNUMBER(D13)),COUNT(F13:G13)<2),"",D13-SUM(F13:G13)) | I13: =IF(OR(NOT(ISNUMBER(H13)),D13=0),"",H13/D13) | N13: =IF(COUNT(L13:M13)<2,"",IF(L13=0,IF(M13=0,1,""),M13/L13)) | P13: Не | Q13: Не | R13: =IF(AND(Q13="Да",EOMONTH(A13,0)<Допускания!$D$7,COUNT(B13:C13)=2,COUNT(E13:G13)=3,COUNT(L13:M13)=2,ISNUMBER(O13),L13>=M13,ISNUMBER(I13),ISNUMBER(N13)),IF(AND(D13>=30000,E13>=15000,I13>=Допускания!$D$10,N13>=Допускания!$D$11,O13=0,P13="Да"),1,0),"") | S13: =IF(NOT(ISNUMBER(R13)),"",IF(R13=1,IF(ISNUMBER(S12),S12+1,1),0)) | T13: =IF(AND(Q13="Да",EOMONTH(A13,0)<Допускания!$D$7,COUNT(B13:C13)=2,COUNT(E13:G13)=3,COUNT(L13:M13)=2,ISNUMBER(O13),L13>=M13,ISNUMBER(I13),ISNUMBER(N13)),IF(AND(D13>=50000,E13>=30000,I13>=Допускания!$D$10,N13>=Допускания!$D$11,O13=0,P13="Да"),1,0),"") | U13: =IF(NOT(ISNUMBER(T13)),"",IF(T13=1,IF(ISNUMBER(U12),U12+1,1),0))
A14: =EDATE(DATE(YEAR(Допускания!$D$6),MONTH(Допускания!$D$6),1),6) -> 46447 | D14: =IF(COUNT(B14:C14)<2,"",SUM(B14:C14)) | H14: =IF(OR(NOT(ISNUMBER(D14)),COUNT(F14:G14)<2),"",D14-SUM(F14:G14)) | I14: =IF(OR(NOT(ISNUMBER(H14)),D14=0),"",H14/D14) | N14: =IF(COUNT(L14:M14)<2,"",IF(L14=0,IF(M14=0,1,""),M14/L14)) | P14: Не | Q14: Не | R14: =IF(AND(Q14="Да",EOMONTH(A14,0)<Допускания!$D$7,COUNT(B14:C14)=2,COUNT(E14:G14)=3,COUNT(L14:M14)=2,ISNUMBER(O14),L14>=M14,ISNUMBER(I14),ISNUMBER(N14)),IF(AND(D14>=30000,E14>=15000,I14>=Допускания!$D$10,N14>=Допускания!$D$11,O14=0,P14="Да"),1,0),"") | S14: =IF(NOT(ISNUMBER(R14)),"",IF(R14=1,IF(ISNUMBER(S13),S13+1,1),0)) | T14: =IF(AND(Q14="Да",EOMONTH(A14,0)<Допускания!$D$7,COUNT(B14:C14)=2,COUNT(E14:G14)=3,COUNT(L14:M14)=2,ISNUMBER(O14),L14>=M14,ISNUMBER(I14),ISNUMBER(N14)),IF(AND(D14>=50000,E14>=30000,I14>=Допускания!$D$10,N14>=Допускания!$D$11,O14=0,P14="Да"),1,0),"") | U14: =IF(NOT(ISNUMBER(T14)),"",IF(T14=1,IF(ISNUMBER(U13),U13+1,1),0))
A15: =EDATE(DATE(YEAR(Допускания!$D$6),MONTH(Допускания!$D$6),1),7) -> 46478 | D15: =IF(COUNT(B15:C15)<2,"",SUM(B15:C15)) | H15: =IF(OR(NOT(ISNUMBER(D15)),COUNT(F15:G15)<2),"",D15-SUM(F15:G15)) | I15: =IF(OR(NOT(ISNUMBER(H15)),D15=0),"",H15/D15) | N15: =IF(COUNT(L15:M15)<2,"",IF(L15=0,IF(M15=0,1,""),M15/L15)) | P15: Не | Q15: Не | R15: =IF(AND(Q15="Да",EOMONTH(A15,0)<Допускания!$D$7,COUNT(B15:C15)=2,COUNT(E15:G15)=3,COUNT(L15:M15)=2,ISNUMBER(O15),L15>=M15,ISNUMBER(I15),ISNUMBER(N15)),IF(AND(D15>=30000,E15>=15000,I15>=Допускания!$D$10,N15>=Допускания!$D$11,O15=0,P15="Да"),1,0),"") | S15: =IF(NOT(ISNUMBER(R15)),"",IF(R15=1,IF(ISNUMBER(S14),S14+1,1),0)) | T15: =IF(AND(Q15="Да",EOMONTH(A15,0)<Допускания!$D$7,COUNT(B15:C15)=2,COUNT(E15:G15)=3,COUNT(L15:M15)=2,ISNUMBER(O15),L15>=M15,ISNUMBER(I15),ISNUMBER(N15)),IF(AND(D15>=50000,E15>=30000,I15>=Допускания!$D$10,N15>=Допускания!$D$11,O15=0,P15="Да"),1,0),"") | U15: =IF(NOT(ISNUMBER(T15)),"",IF(T15=1,IF(ISNUMBER(U14),U14+1,1),0))
A16: =EDATE(DATE(YEAR(Допускания!$D$6),MONTH(Допускания!$D$6),1),8) -> 46508 | D16: =IF(COUNT(B16:C16)<2,"",SUM(B16:C16)) | H16: =IF(OR(NOT(ISNUMBER(D16)),COUNT(F16:G16)<2),"",D16-SUM(F16:G16)) | I16: =IF(OR(NOT(ISNUMBER(H16)),D16=0),"",H16/D16) | N16: =IF(COUNT(L16:M16)<2,"",IF(L16=0,IF(M16=0,1,""),M16/L16)) | P16: Не | Q16: Не | R16: =IF(AND(Q16="Да",EOMONTH(A16,0)<Допускания!$D$7,COUNT(B16:C16)=2,COUNT(E16:G16)=3,COUNT(L16:M16)=2,ISNUMBER(O16),L16>=M16,ISNUMBER(I16),ISNUMBER(N16)),IF(AND(D16>=30000,E16>=15000,I16>=Допускания!$D$10,N16>=Допускания!$D$11,O16=0,P16="Да"),1,0),"") | S16: =IF(NOT(ISNUMBER(R16)),"",IF(R16=1,IF(ISNUMBER(S15),S15+1,1),0)) | T16: =IF(AND(Q16="Да",EOMONTH(A16,0)<Допускания!$D$7,COUNT(B16:C16)=2,COUNT(E16:G16)=3,COUNT(L16:M16)=2,ISNUMBER(O16),L16>=M16,ISNUMBER(I16),ISNUMBER(N16)),IF(AND(D16>=50000,E16>=30000,I16>=Допускания!$D$10,N16>=Допускания!$D$11,O16=0,P16="Да"),1,0),"") | U16: =IF(NOT(ISNUMBER(T16)),"",IF(T16=1,IF(ISNUMBER(U15),U15+1,1),0))
A17: =EDATE(DATE(YEAR(Допускания!$D$6),MONTH(Допускания!$D$6),1),9) -> 46539 | D17: =IF(COUNT(B17:C17)<2,"",SUM(B17:C17)) | H17: =IF(OR(NOT(ISNUMBER(D17)),COUNT(F17:G17)<2),"",D17-SUM(F17:G17)) | I17: =IF(OR(NOT(ISNUMBER(H17)),D17=0),"",H17/D17) | N17: =IF(COUNT(L17:M17)<2,"",IF(L17=0,IF(M17=0,1,""),M17/L17)) | P17: Не | Q17: Не | R17: =IF(AND(Q17="Да",EOMONTH(A17,0)<Допускания!$D$7,COUNT(B17:C17)=2,COUNT(E17:G17)=3,COUNT(L17:M17)=2,ISNUMBER(O17),L17>=M17,ISNUMBER(I17),ISNUMBER(N17)),IF(AND(D17>=30000,E17>=15000,I17>=Допускания!$D$10,N17>=Допускания!$D$11,O17=0,P17="Да"),1,0),"") | S17: =IF(NOT(ISNUMBER(R17)),"",IF(R17=1,IF(ISNUMBER(S16),S16+1,1),0)) | T17: =IF(AND(Q17="Да",EOMONTH(A17,0)<Допускания!$D$7,COUNT(B17:C17)=2,COUNT(E17:G17)=3,COUNT(L17:M17)=2,ISNUMBER(O17),L17>=M17,ISNUMBER(I17),ISNUMBER(N17)),IF(AND(D17>=50000,E17>=30000,I17>=Допускания!$D$10,N17>=Допускания!$D$11,O17=0,P17="Да"),1,0),"") | U17: =IF(NOT(ISNUMBER(T17)),"",IF(T17=1,IF(ISNUMBER(U16),U16+1,1),0))
A18: =EDATE(DATE(YEAR(Допускания!$D$6),MONTH(Допускания!$D$6),1),10) -> 46569 | D18: =IF(COUNT(B18:C18)<2,"",SUM(B18:C18)) | H18: =IF(OR(NOT(ISNUMBER(D18)),COUNT(F18:G18)<2),"",D18-SUM(F18:G18)) | I18: =IF(OR(NOT(ISNUMBER(H18)),D18=0),"",H18/D18) | N18: =IF(COUNT(L18:M18)<2,"",IF(L18=0,IF(M18=0,1,""),M18/L18)) | P18: Не | Q18: Не | R18: =IF(AND(Q18="Да",EOMONTH(A18,0)<Допускания!$D$7,COUNT(B18:C18)=2,COUNT(E18:G18)=3,COUNT(L18:M18)=2,ISNUMBER(O18),L18>=M18,ISNUMBER(I18),ISNUMBER(N18)),IF(AND(D18>=30000,E18>=15000,I18>=Допускания!$D$10,N18>=Допускания!$D$11,O18=0,P18="Да"),1,0),"") | S18: =IF(NOT(ISNUMBER(R18)),"",IF(R18=1,IF(ISNUMBER(S17),S17+1,1),0)) | T18: =IF(AND(Q18="Да",EOMONTH(A18,0)<Допускания!$D$7,COUNT(B18:C18)=2,COUNT(E18:G18)=3,COUNT(L18:M18)=2,ISNUMBER(O18),L18>=M18,ISNUMBER(I18),ISNUMBER(N18)),IF(AND(D18>=50000,E18>=30000,I18>=Допускания!$D$10,N18>=Допускания!$D$11,O18=0,P18="Да"),1,0),"") | U18: =IF(NOT(ISNUMBER(T18)),"",IF(T18=1,IF(ISNUMBER(U17),U17+1,1),0))
A19: =EDATE(DATE(YEAR(Допускания!$D$6),MONTH(Допускания!$D$6),1),11) -> 46600 | D19: =IF(COUNT(B19:C19)<2,"",SUM(B19:C19)) | H19: =IF(OR(NOT(ISNUMBER(D19)),COUNT(F19:G19)<2),"",D19-SUM(F19:G19)) | I19: =IF(OR(NOT(ISNUMBER(H19)),D19=0),"",H19/D19) | N19: =IF(COUNT(L19:M19)<2,"",IF(L19=0,IF(M19=0,1,""),M19/L19)) | P19: Не | Q19: Не | R19: =IF(AND(Q19="Да",EOMONTH(A19,0)<Допускания!$D$7,COUNT(B19:C19)=2,COUNT(E19:G19)=3,COUNT(L19:M19)=2,ISNUMBER(O19),L19>=M19,ISNUMBER(I19),ISNUMBER(N19)),IF(AND(D19>=30000,E19>=15000,I19>=Допускания!$D$10,N19>=Допускания!$D$11,O19=0,P19="Да"),1,0),"") | S19: =IF(NOT(ISNUMBER(R19)),"",IF(R19=1,IF(ISNUMBER(S18),S18+1,1),0)) | T19: =IF(AND(Q19="Да",EOMONTH(A19,0)<Допускания!$D$7,COUNT(B19:C19)=2,COUNT(E19:G19)=3,COUNT(L19:M19)=2,ISNUMBER(O19),L19>=M19,ISNUMBER(I19),ISNUMBER(N19)),IF(AND(D19>=50000,E19>=30000,I19>=Допускания!$D$10,N19>=Допускания!$D$11,O19=0,P19="Да"),1,0),"") | U19: =IF(NOT(ISNUMBER(T19)),"",IF(T19=1,IF(ISNUMBER(U18),U18+1,1),0))
A20: =EDATE(DATE(YEAR(Допускания!$D$6),MONTH(Допускания!$D$6),1),12) -> 46631 | D20: =IF(COUNT(B20:C20)<2,"",SUM(B20:C20)) | H20: =IF(OR(NOT(ISNUMBER(D20)),COUNT(F20:G20)<2),"",D20-SUM(F20:G20)) | I20: =IF(OR(NOT(ISNUMBER(H20)),D20=0),"",H20/D20) | N20: =IF(COUNT(L20:M20)<2,"",IF(L20=0,IF(M20=0,1,""),M20/L20)) | P20: Не | Q20: Не | R20: =IF(AND(Q20="Да",EOMONTH(A20,0)<Допускания!$D$7,COUNT(B20:C20)=2,COUNT(E20:G20)=3,COUNT(L20:M20)=2,ISNUMBER(O20),L20>=M20,ISNUMBER(I20),ISNUMBER(N20)),IF(AND(D20>=30000,E20>=15000,I20>=Допускания!$D$10,N20>=Допускания!$D$11,O20=0,P20="Да"),1,0),"") | S20: =IF(NOT(ISNUMBER(R20)),"",IF(R20=1,IF(ISNUMBER(S19),S19+1,1),0)) | T20: =IF(AND(Q20="Да",EOMONTH(A20,0)<Допускания!$D$7,COUNT(B20:C20)=2,COUNT(E20:G20)=3,COUNT(L20:M20)=2,ISNUMBER(O20),L20>=M20,ISNUMBER(I20),ISNUMBER(N20)),IF(AND(D20>=50000,E20>=30000,I20>=Допускания!$D$10,N20>=Допускания!$D$11,O20=0,P20="Да"),1,0),"") | U20: =IF(NOT(ISNUMBER(T20)),"",IF(T20=1,IF(ISNUMBER(U19),U19+1,1),0))
A21: =EDATE(DATE(YEAR(Допускания!$D$6),MONTH(Допускания!$D$6),1),13) -> 46661 | D21: =IF(COUNT(B21:C21)<2,"",SUM(B21:C21)) | H21: =IF(OR(NOT(ISNUMBER(D21)),COUNT(F21:G21)<2),"",D21-SUM(F21:G21)) | I21: =IF(OR(NOT(ISNUMBER(H21)),D21=0),"",H21/D21) | N21: =IF(COUNT(L21:M21)<2,"",IF(L21=0,IF(M21=0,1,""),M21/L21)) | P21: Не | Q21: Не | R21: =IF(AND(Q21="Да",EOMONTH(A21,0)<Допускания!$D$7,COUNT(B21:C21)=2,COUNT(E21:G21)=3,COUNT(L21:M21)=2,ISNUMBER(O21),L21>=M21,ISNUMBER(I21),ISNUMBER(N21)),IF(AND(D21>=30000,E21>=15000,I21>=Допускания!$D$10,N21>=Допускания!$D$11,O21=0,P21="Да"),1,0),"") | S21: =IF(NOT(ISNUMBER(R21)),"",IF(R21=1,IF(ISNUMBER(S20),S20+1,1),0)) | T21: =IF(AND(Q21="Да",EOMONTH(A21,0)<Допускания!$D$7,COUNT(B21:C21)=2,COUNT(E21:G21)=3,COUNT(L21:M21)=2,ISNUMBER(O21),L21>=M21,ISNUMBER(I21),ISNUMBER(N21)),IF(AND(D21>=50000,E21>=30000,I21>=Допускания!$D$10,N21>=Допускания!$D$11,O21=0,P21="Да"),1,0),"") | U21: =IF(NOT(ISNUMBER(T21)),"",IF(T21=1,IF(ISNUMBER(U20),U20+1,1),0))
A22: =EDATE(DATE(YEAR(Допускания!$D$6),MONTH(Допускания!$D$6),1),14) -> 46692 | D22: =IF(COUNT(B22:C22)<2,"",SUM(B22:C22)) | H22: =IF(OR(NOT(ISNUMBER(D22)),COUNT(F22:G22)<2),"",D22-SUM(F22:G22)) | I22: =IF(OR(NOT(ISNUMBER(H22)),D22=0),"",H22/D22) | N22: =IF(COUNT(L22:M22)<2,"",IF(L22=0,IF(M22=0,1,""),M22/L22)) | P22: Не | Q22: Не | R22: =IF(AND(Q22="Да",EOMONTH(A22,0)<Допускания!$D$7,COUNT(B22:C22)=2,COUNT(E22:G22)=3,COUNT(L22:M22)=2,ISNUMBER(O22),L22>=M22,ISNUMBER(I22),ISNUMBER(N22)),IF(AND(D22>=30000,E22>=15000,I22>=Допускания!$D$10,N22>=Допускания!$D$11,O22=0,P22="Да"),1,0),"") | S22: =IF(NOT(ISNUMBER(R22)),"",IF(R22=1,IF(ISNUMBER(S21),S21+1,1),0)) | T22: =IF(AND(Q22="Да",EOMONTH(A22,0)<Допускания!$D$7,COUNT(B22:C22)=2,COUNT(E22:G22)=3,COUNT(L22:M22)=2,ISNUMBER(O22),L22>=M22,ISNUMBER(I22),ISNUMBER(N22)),IF(AND(D22>=50000,E22>=30000,I22>=Допускания!$D$10,N22>=Допускания!$D$11,O22=0,P22="Да"),1,0),"") | U22: =IF(NOT(ISNUMBER(T22)),"",IF(T22=1,IF(ISNUMBER(U21),U21+1,1),0))
A23: =EDATE(DATE(YEAR(Допускания!$D$6),MONTH(Допускания!$D$6),1),15) -> 46722 | D23: =IF(COUNT(B23:C23)<2,"",SUM(B23:C23)) | H23: =IF(OR(NOT(ISNUMBER(D23)),COUNT(F23:G23)<2),"",D23-SUM(F23:G23)) | I23: =IF(OR(NOT(ISNUMBER(H23)),D23=0),"",H23/D23) | N23: =IF(COUNT(L23:M23)<2,"",IF(L23=0,IF(M23=0,1,""),M23/L23)) | P23: Не | Q23: Не | R23: =IF(AND(Q23="Да",EOMONTH(A23,0)<Допускания!$D$7,COUNT(B23:C23)=2,COUNT(E23:G23)=3,COUNT(L23:M23)=2,ISNUMBER(O23),L23>=M23,ISNUMBER(I23),ISNUMBER(N23)),IF(AND(D23>=30000,E23>=15000,I23>=Допускания!$D$10,N23>=Допускания!$D$11,O23=0,P23="Да"),1,0),"") | S23: =IF(NOT(ISNUMBER(R23)),"",IF(R23=1,IF(ISNUMBER(S22),S22+1,1),0)) | T23: =IF(AND(Q23="Да",EOMONTH(A23,0)<Допускания!$D$7,COUNT(B23:C23)=2,COUNT(E23:G23)=3,COUNT(L23:M23)=2,ISNUMBER(O23),L23>=M23,ISNUMBER(I23),ISNUMBER(N23)),IF(AND(D23>=50000,E23>=30000,I23>=Допускания!$D$10,N23>=Допускания!$D$11,O23=0,P23="Да"),1,0),"") | U23: =IF(NOT(ISNUMBER(T23)),"",IF(T23=1,IF(ISNUMBER(U22),U22+1,1),0))
A24: =EDATE(DATE(YEAR(Допускания!$D$6),MONTH(Допускания!$D$6),1),16) -> 46753 | D24: =IF(COUNT(B24:C24)<2,"",SUM(B24:C24)) | H24: =IF(OR(NOT(ISNUMBER(D24)),COUNT(F24:G24)<2),"",D24-SUM(F24:G24)) | I24: =IF(OR(NOT(ISNUMBER(H24)),D24=0),"",H24/D24) | N24: =IF(COUNT(L24:M24)<2,"",IF(L24=0,IF(M24=0,1,""),M24/L24)) | P24: Не | Q24: Не | R24: =IF(AND(Q24="Да",EOMONTH(A24,0)<Допускания!$D$7,COUNT(B24:C24)=2,COUNT(E24:G24)=3,COUNT(L24:M24)=2,ISNUMBER(O24),L24>=M24,ISNUMBER(I24),ISNUMBER(N24)),IF(AND(D24>=30000,E24>=15000,I24>=Допускания!$D$10,N24>=Допускания!$D$11,O24=0,P24="Да"),1,0),"") | S24: =IF(NOT(ISNUMBER(R24)),"",IF(R24=1,IF(ISNUMBER(S23),S23+1,1),0)) | T24: =IF(AND(Q24="Да",EOMONTH(A24,0)<Допускания!$D$7,COUNT(B24:C24)=2,COUNT(E24:G24)=3,COUNT(L24:M24)=2,ISNUMBER(O24),L24>=M24,ISNUMBER(I24),ISNUMBER(N24)),IF(AND(D24>=50000,E24>=30000,I24>=Допускания!$D$10,N24>=Допускания!$D$11,O24=0,P24="Да"),1,0),"") | U24: =IF(NOT(ISNUMBER(T24)),"",IF(T24=1,IF(ISNUMBER(U23),U23+1,1),0))
A25: =EDATE(DATE(YEAR(Допускания!$D$6),MONTH(Допускания!$D$6),1),17) -> 46784 | D25: =IF(COUNT(B25:C25)<2,"",SUM(B25:C25)) | H25: =IF(OR(NOT(ISNUMBER(D25)),COUNT(F25:G25)<2),"",D25-SUM(F25:G25)) | I25: =IF(OR(NOT(ISNUMBER(H25)),D25=0),"",H25/D25) | N25: =IF(COUNT(L25:M25)<2,"",IF(L25=0,IF(M25=0,1,""),M25/L25)) | P25: Не | Q25: Не | R25: =IF(AND(Q25="Да",EOMONTH(A25,0)<Допускания!$D$7,COUNT(B25:C25)=2,COUNT(E25:G25)=3,COUNT(L25:M25)=2,ISNUMBER(O25),L25>=M25,ISNUMBER(I25),ISNUMBER(N25)),IF(AND(D25>=30000,E25>=15000,I25>=Допускания!$D$10,N25>=Допускания!$D$11,O25=0,P25="Да"),1,0),"") | S25: =IF(NOT(ISNUMBER(R25)),"",IF(R25=1,IF(ISNUMBER(S24),S24+1,1),0)) | T25: =IF(AND(Q25="Да",EOMONTH(A25,0)<Допускания!$D$7,COUNT(B25:C25)=2,COUNT(E25:G25)=3,COUNT(L25:M25)=2,ISNUMBER(O25),L25>=M25,ISNUMBER(I25),ISNUMBER(N25)),IF(AND(D25>=50000,E25>=30000,I25>=Допускания!$D$10,N25>=Допускания!$D$11,O25=0,P25="Да"),1,0),"") | U25: =IF(NOT(ISNUMBER(T25)),"",IF(T25=1,IF(ISNUMBER(U24),U24+1,1),0))
A26: =EDATE(DATE(YEAR(Допускания!$D$6),MONTH(Допускания!$D$6),1),18) -> 46813 | D26: =IF(COUNT(B26:C26)<2,"",SUM(B26:C26)) | H26: =IF(OR(NOT(ISNUMBER(D26)),COUNT(F26:G26)<2),"",D26-SUM(F26:G26)) | I26: =IF(OR(NOT(ISNUMBER(H26)),D26=0),"",H26/D26) | N26: =IF(COUNT(L26:M26)<2,"",IF(L26=0,IF(M26=0,1,""),M26/L26)) | P26: Не | Q26: Не | R26: =IF(AND(Q26="Да",EOMONTH(A26,0)<Допускания!$D$7,COUNT(B26:C26)=2,COUNT(E26:G26)=3,COUNT(L26:M26)=2,ISNUMBER(O26),L26>=M26,ISNUMBER(I26),ISNUMBER(N26)),IF(AND(D26>=30000,E26>=15000,I26>=Допускания!$D$10,N26>=Допускания!$D$11,O26=0,P26="Да"),1,0),"") | S26: =IF(NOT(ISNUMBER(R26)),"",IF(R26=1,IF(ISNUMBER(S25),S25+1,1),0)) | T26: =IF(AND(Q26="Да",EOMONTH(A26,0)<Допускания!$D$7,COUNT(B26:C26)=2,COUNT(E26:G26)=3,COUNT(L26:M26)=2,ISNUMBER(O26),L26>=M26,ISNUMBER(I26),ISNUMBER(N26)),IF(AND(D26>=50000,E26>=30000,I26>=Допускания!$D$10,N26>=Допускания!$D$11,O26=0,P26="Да"),1,0),"") | U26: =IF(NOT(ISNUMBER(T26)),"",IF(T26=1,IF(ISNUMBER(U25),U25+1,1),0))
A27: =EDATE(DATE(YEAR(Допускания!$D$6),MONTH(Допускания!$D$6),1),19) -> 46844 | D27: =IF(COUNT(B27:C27)<2,"",SUM(B27:C27)) | H27: =IF(OR(NOT(ISNUMBER(D27)),COUNT(F27:G27)<2),"",D27-SUM(F27:G27)) | I27: =IF(OR(NOT(ISNUMBER(H27)),D27=0),"",H27/D27) | N27: =IF(COUNT(L27:M27)<2,"",IF(L27=0,IF(M27=0,1,""),M27/L27)) | P27: Не | Q27: Не | R27: =IF(AND(Q27="Да",EOMONTH(A27,0)<Допускания!$D$7,COUNT(B27:C27)=2,COUNT(E27:G27)=3,COUNT(L27:M27)=2,ISNUMBER(O27),L27>=M27,ISNUMBER(I27),ISNUMBER(N27)),IF(AND(D27>=30000,E27>=15000,I27>=Допускания!$D$10,N27>=Допускания!$D$11,O27=0,P27="Да"),1,0),"") | S27: =IF(NOT(ISNUMBER(R27)),"",IF(R27=1,IF(ISNUMBER(S26),S26+1,1),0)) | T27: =IF(AND(Q27="Да",EOMONTH(A27,0)<Допускания!$D$7,COUNT(B27:C27)=2,COUNT(E27:G27)=3,COUNT(L27:M27)=2,ISNUMBER(O27),L27>=M27,ISNUMBER(I27),ISNUMBER(N27)),IF(AND(D27>=50000,E27>=30000,I27>=Допускания!$D$10,N27>=Допускания!$D$11,O27=0,P27="Да"),1,0),"") | U27: =IF(NOT(ISNUMBER(T27)),"",IF(T27=1,IF(ISNUMBER(U26),U26+1,1),0))
A28: =EDATE(DATE(YEAR(Допускания!$D$6),MONTH(Допускания!$D$6),1),20) -> 46874 | D28: =IF(COUNT(B28:C28)<2,"",SUM(B28:C28)) | H28: =IF(OR(NOT(ISNUMBER(D28)),COUNT(F28:G28)<2),"",D28-SUM(F28:G28)) | I28: =IF(OR(NOT(ISNUMBER(H28)),D28=0),"",H28/D28) | N28: =IF(COUNT(L28:M28)<2,"",IF(L28=0,IF(M28=0,1,""),M28/L28)) | P28: Не | Q28: Не | R28: =IF(AND(Q28="Да",EOMONTH(A28,0)<Допускания!$D$7,COUNT(B28:C28)=2,COUNT(E28:G28)=3,COUNT(L28:M28)=2,ISNUMBER(O28),L28>=M28,ISNUMBER(I28),ISNUMBER(N28)),IF(AND(D28>=30000,E28>=15000,I28>=Допускания!$D$10,N28>=Допускания!$D$11,O28=0,P28="Да"),1,0),"") | S28: =IF(NOT(ISNUMBER(R28)),"",IF(R28=1,IF(ISNUMBER(S27),S27+1,1),0)) | T28: =IF(AND(Q28="Да",EOMONTH(A28,0)<Допускания!$D$7,COUNT(B28:C28)=2,COUNT(E28:G28)=3,COUNT(L28:M28)=2,ISNUMBER(O28),L28>=M28,ISNUMBER(I28),ISNUMBER(N28)),IF(AND(D28>=50000,E28>=30000,I28>=Допускания!$D$10,N28>=Допускания!$D$11,O28=0,P28="Да"),1,0),"") | U28: =IF(NOT(ISNUMBER(T28)),"",IF(T28=1,IF(ISNUMBER(U27),U27+1,1),0))
A29: =EDATE(DATE(YEAR(Допускания!$D$6),MONTH(Допускания!$D$6),1),21) -> 46905 | D29: =IF(COUNT(B29:C29)<2,"",SUM(B29:C29)) | H29: =IF(OR(NOT(ISNUMBER(D29)),COUNT(F29:G29)<2),"",D29-SUM(F29:G29)) | I29: =IF(OR(NOT(ISNUMBER(H29)),D29=0),"",H29/D29) | N29: =IF(COUNT(L29:M29)<2,"",IF(L29=0,IF(M29=0,1,""),M29/L29)) | P29: Не | Q29: Не | R29: =IF(AND(Q29="Да",EOMONTH(A29,0)<Допускания!$D$7,COUNT(B29:C29)=2,COUNT(E29:G29)=3,COUNT(L29:M29)=2,ISNUMBER(O29),L29>=M29,ISNUMBER(I29),ISNUMBER(N29)),IF(AND(D29>=30000,E29>=15000,I29>=Допускания!$D$10,N29>=Допускания!$D$11,O29=0,P29="Да"),1,0),"") | S29: =IF(NOT(ISNUMBER(R29)),"",IF(R29=1,IF(ISNUMBER(S28),S28+1,1),0)) | T29: =IF(AND(Q29="Да",EOMONTH(A29,0)<Допускания!$D$7,COUNT(B29:C29)=2,COUNT(E29:G29)=3,COUNT(L29:M29)=2,ISNUMBER(O29),L29>=M29,ISNUMBER(I29),ISNUMBER(N29)),IF(AND(D29>=50000,E29>=30000,I29>=Допускания!$D$10,N29>=Допускания!$D$11,O29=0,P29="Да"),1,0),"") | U29: =IF(NOT(ISNUMBER(T29)),"",IF(T29=1,IF(ISNUMBER(U28),U28+1,1),0))
A30: =EDATE(DATE(YEAR(Допускания!$D$6),MONTH(Допускания!$D$6),1),22) -> 46935 | D30: =IF(COUNT(B30:C30)<2,"",SUM(B30:C30)) | H30: =IF(OR(NOT(ISNUMBER(D30)),COUNT(F30:G30)<2),"",D30-SUM(F30:G30)) | I30: =IF(OR(NOT(ISNUMBER(H30)),D30=0),"",H30/D30) | N30: =IF(COUNT(L30:M30)<2,"",IF(L30=0,IF(M30=0,1,""),M30/L30)) | P30: Не | Q30: Не | R30: =IF(AND(Q30="Да",EOMONTH(A30,0)<Допускания!$D$7,COUNT(B30:C30)=2,COUNT(E30:G30)=3,COUNT(L30:M30)=2,ISNUMBER(O30),L30>=M30,ISNUMBER(I30),ISNUMBER(N30)),IF(AND(D30>=30000,E30>=15000,I30>=Допускания!$D$10,N30>=Допускания!$D$11,O30=0,P30="Да"),1,0),"") | S30: =IF(NOT(ISNUMBER(R30)),"",IF(R30=1,IF(ISNUMBER(S29),S29+1,1),0)) | T30: =IF(AND(Q30="Да",EOMONTH(A30,0)<Допускания!$D$7,COUNT(B30:C30)=2,COUNT(E30:G30)=3,COUNT(L30:M30)=2,ISNUMBER(O30),L30>=M30,ISNUMBER(I30),ISNUMBER(N30)),IF(AND(D30>=50000,E30>=30000,I30>=Допускания!$D$10,N30>=Допускания!$D$11,O30=0,P30="Да"),1,0),"") | U30: =IF(NOT(ISNUMBER(T30)),"",IF(T30=1,IF(ISNUMBER(U29),U29+1,1),0))
A31: =EDATE(DATE(YEAR(Допускания!$D$6),MONTH(Допускания!$D$6),1),23) -> 46966 | D31: =IF(COUNT(B31:C31)<2,"",SUM(B31:C31)) | H31: =IF(OR(NOT(ISNUMBER(D31)),COUNT(F31:G31)<2),"",D31-SUM(F31:G31)) | I31: =IF(OR(NOT(ISNUMBER(H31)),D31=0),"",H31/D31) | N31: =IF(COUNT(L31:M31)<2,"",IF(L31=0,IF(M31=0,1,""),M31/L31)) | P31: Не | Q31: Не | R31: =IF(AND(Q31="Да",EOMONTH(A31,0)<Допускания!$D$7,COUNT(B31:C31)=2,COUNT(E31:G31)=3,COUNT(L31:M31)=2,ISNUMBER(O31),L31>=M31,ISNUMBER(I31),ISNUMBER(N31)),IF(AND(D31>=30000,E31>=15000,I31>=Допускания!$D$10,N31>=Допускания!$D$11,O31=0,P31="Да"),1,0),"") | S31: =IF(NOT(ISNUMBER(R31)),"",IF(R31=1,IF(ISNUMBER(S30),S30+1,1),0)) | T31: =IF(AND(Q31="Да",EOMONTH(A31,0)<Допускания!$D$7,COUNT(B31:C31)=2,COUNT(E31:G31)=3,COUNT(L31:M31)=2,ISNUMBER(O31),L31>=M31,ISNUMBER(I31),ISNUMBER(N31)),IF(AND(D31>=50000,E31>=30000,I31>=Допускания!$D$10,N31>=Допускания!$D$11,O31=0,P31="Да"),1,0),"") | U31: =IF(NOT(ISNUMBER(T31)),"",IF(T31=1,IF(ISNUMBER(U30),U30+1,1),0))
A32: =EDATE(DATE(YEAR(Допускания!$D$6),MONTH(Допускания!$D$6),1),24) -> 46997 | D32: =IF(COUNT(B32:C32)<2,"",SUM(B32:C32)) | H32: =IF(OR(NOT(ISNUMBER(D32)),COUNT(F32:G32)<2),"",D32-SUM(F32:G32)) | I32: =IF(OR(NOT(ISNUMBER(H32)),D32=0),"",H32/D32) | N32: =IF(COUNT(L32:M32)<2,"",IF(L32=0,IF(M32=0,1,""),M32/L32)) | P32: Не | Q32: Не | R32: =IF(AND(Q32="Да",EOMONTH(A32,0)<Допускания!$D$7,COUNT(B32:C32)=2,COUNT(E32:G32)=3,COUNT(L32:M32)=2,ISNUMBER(O32),L32>=M32,ISNUMBER(I32),ISNUMBER(N32)),IF(AND(D32>=30000,E32>=15000,I32>=Допускания!$D$10,N32>=Допускания!$D$11,O32=0,P32="Да"),1,0),"") | S32: =IF(NOT(ISNUMBER(R32)),"",IF(R32=1,IF(ISNUMBER(S31),S31+1,1),0)) | T32: =IF(AND(Q32="Да",EOMONTH(A32,0)<Допускания!$D$7,COUNT(B32:C32)=2,COUNT(E32:G32)=3,COUNT(L32:M32)=2,ISNUMBER(O32),L32>=M32,ISNUMBER(I32),ISNUMBER(N32)),IF(AND(D32>=50000,E32>=30000,I32>=Допускания!$D$10,N32>=Допускания!$D$11,O32=0,P32="Да"),1,0),"") | U32: =IF(NOT(ISNUMBER(T32)),"",IF(T32=1,IF(ISNUMBER(U31),U31+1,1),0))
A33: =EDATE(DATE(YEAR(Допускания!$D$6),MONTH(Допускания!$D$6),1),25) -> 47027 | D33: =IF(COUNT(B33:C33)<2,"",SUM(B33:C33)) | H33: =IF(OR(NOT(ISNUMBER(D33)),COUNT(F33:G33)<2),"",D33-SUM(F33:G33)) | I33: =IF(OR(NOT(ISNUMBER(H33)),D33=0),"",H33/D33) | N33: =IF(COUNT(L33:M33)<2,"",IF(L33=0,IF(M33=0,1,""),M33/L33)) | P33: Не | Q33: Не | R33: =IF(AND(Q33="Да",EOMONTH(A33,0)<Допускания!$D$7,COUNT(B33:C33)=2,COUNT(E33:G33)=3,COUNT(L33:M33)=2,ISNUMBER(O33),L33>=M33,ISNUMBER(I33),ISNUMBER(N33)),IF(AND(D33>=30000,E33>=15000,I33>=Допускания!$D$10,N33>=Допускания!$D$11,O33=0,P33="Да"),1,0),"") | S33: =IF(NOT(ISNUMBER(R33)),"",IF(R33=1,IF(ISNUMBER(S32),S32+1,1),0)) | T33: =IF(AND(Q33="Да",EOMONTH(A33,0)<Допускания!$D$7,COUNT(B33:C33)=2,COUNT(E33:G33)=3,COUNT(L33:M33)=2,ISNUMBER(O33),L33>=M33,ISNUMBER(I33),ISNUMBER(N33)),IF(AND(D33>=50000,E33>=30000,I33>=Допускания!$D$10,N33>=Допускания!$D$11,O33=0,P33="Да"),1,0),"") | U33: =IF(NOT(ISNUMBER(T33)),"",IF(T33=1,IF(ISNUMBER(U32),U32+1,1),0))
A34: =EDATE(DATE(YEAR(Допускания!$D$6),MONTH(Допускания!$D$6),1),26) -> 47058 | D34: =IF(COUNT(B34:C34)<2,"",SUM(B34:C34)) | H34: =IF(OR(NOT(ISNUMBER(D34)),COUNT(F34:G34)<2),"",D34-SUM(F34:G34)) | I34: =IF(OR(NOT(ISNUMBER(H34)),D34=0),"",H34/D34) | N34: =IF(COUNT(L34:M34)<2,"",IF(L34=0,IF(M34=0,1,""),M34/L34)) | P34: Не | Q34: Не | R34: =IF(AND(Q34="Да",EOMONTH(A34,0)<Допускания!$D$7,COUNT(B34:C34)=2,COUNT(E34:G34)=3,COUNT(L34:M34)=2,ISNUMBER(O34),L34>=M34,ISNUMBER(I34),ISNUMBER(N34)),IF(AND(D34>=30000,E34>=15000,I34>=Допускания!$D$10,N34>=Допускания!$D$11,O34=0,P34="Да"),1,0),"") | S34: =IF(NOT(ISNUMBER(R34)),"",IF(R34=1,IF(ISNUMBER(S33),S33+1,1),0)) | T34: =IF(AND(Q34="Да",EOMONTH(A34,0)<Допускания!$D$7,COUNT(B34:C34)=2,COUNT(E34:G34)=3,COUNT(L34:M34)=2,ISNUMBER(O34),L34>=M34,ISNUMBER(I34),ISNUMBER(N34)),IF(AND(D34>=50000,E34>=30000,I34>=Допускания!$D$10,N34>=Допускания!$D$11,O34=0,P34="Да"),1,0),"") | U34: =IF(NOT(ISNUMBER(T34)),"",IF(T34=1,IF(ISNUMBER(U33),U33+1,1),0))
A35: =EDATE(DATE(YEAR(Допускания!$D$6),MONTH(Допускания!$D$6),1),27) -> 47088 | D35: =IF(COUNT(B35:C35)<2,"",SUM(B35:C35)) | H35: =IF(OR(NOT(ISNUMBER(D35)),COUNT(F35:G35)<2),"",D35-SUM(F35:G35)) | I35: =IF(OR(NOT(ISNUMBER(H35)),D35=0),"",H35/D35) | N35: =IF(COUNT(L35:M35)<2,"",IF(L35=0,IF(M35=0,1,""),M35/L35)) | P35: Не | Q35: Не | R35: =IF(AND(Q35="Да",EOMONTH(A35,0)<Допускания!$D$7,COUNT(B35:C35)=2,COUNT(E35:G35)=3,COUNT(L35:M35)=2,ISNUMBER(O35),L35>=M35,ISNUMBER(I35),ISNUMBER(N35)),IF(AND(D35>=30000,E35>=15000,I35>=Допускания!$D$10,N35>=Допускания!$D$11,O35=0,P35="Да"),1,0),"") | S35: =IF(NOT(ISNUMBER(R35)),"",IF(R35=1,IF(ISNUMBER(S34),S34+1,1),0)) | T35: =IF(AND(Q35="Да",EOMONTH(A35,0)<Допускания!$D$7,COUNT(B35:C35)=2,COUNT(E35:G35)=3,COUNT(L35:M35)=2,ISNUMBER(O35),L35>=M35,ISNUMBER(I35),ISNUMBER(N35)),IF(AND(D35>=50000,E35>=30000,I35>=Допускания!$D$10,N35>=Допускания!$D$11,O35=0,P35="Да"),1,0),"") | U35: =IF(NOT(ISNUMBER(T35)),"",IF(T35=1,IF(ISNUMBER(U34),U34+1,1),0))
A36: =EDATE(DATE(YEAR(Допускания!$D$6),MONTH(Допускания!$D$6),1),28) -> 47119 | D36: =IF(COUNT(B36:C36)<2,"",SUM(B36:C36)) | H36: =IF(OR(NOT(ISNUMBER(D36)),COUNT(F36:G36)<2),"",D36-SUM(F36:G36)) | I36: =IF(OR(NOT(ISNUMBER(H36)),D36=0),"",H36/D36) | N36: =IF(COUNT(L36:M36)<2,"",IF(L36=0,IF(M36=0,1,""),M36/L36)) | P36: Не | Q36: Не | R36: =IF(AND(Q36="Да",EOMONTH(A36,0)<Допускания!$D$7,COUNT(B36:C36)=2,COUNT(E36:G36)=3,COUNT(L36:M36)=2,ISNUMBER(O36),L36>=M36,ISNUMBER(I36),ISNUMBER(N36)),IF(AND(D36>=30000,E36>=15000,I36>=Допускания!$D$10,N36>=Допускания!$D$11,O36=0,P36="Да"),1,0),"") | S36: =IF(NOT(ISNUMBER(R36)),"",IF(R36=1,IF(ISNUMBER(S35),S35+1,1),0)) | T36: =IF(AND(Q36="Да",EOMONTH(A36,0)<Допускания!$D$7,COUNT(B36:C36)=2,COUNT(E36:G36)=3,COUNT(L36:M36)=2,ISNUMBER(O36),L36>=M36,ISNUMBER(I36),ISNUMBER(N36)),IF(AND(D36>=50000,E36>=30000,I36>=Допускания!$D$10,N36>=Допускания!$D$11,O36=0,P36="Да"),1,0),"") | U36: =IF(NOT(ISNUMBER(T36)),"",IF(T36=1,IF(ISNUMBER(U35),U35+1,1),0))
A37: =EDATE(DATE(YEAR(Допускания!$D$6),MONTH(Допускания!$D$6),1),29) -> 47150 | D37: =IF(COUNT(B37:C37)<2,"",SUM(B37:C37)) | H37: =IF(OR(NOT(ISNUMBER(D37)),COUNT(F37:G37)<2),"",D37-SUM(F37:G37)) | I37: =IF(OR(NOT(ISNUMBER(H37)),D37=0),"",H37/D37) | N37: =IF(COUNT(L37:M37)<2,"",IF(L37=0,IF(M37=0,1,""),M37/L37)) | P37: Не | Q37: Не | R37: =IF(AND(Q37="Да",EOMONTH(A37,0)<Допускания!$D$7,COUNT(B37:C37)=2,COUNT(E37:G37)=3,COUNT(L37:M37)=2,ISNUMBER(O37),L37>=M37,ISNUMBER(I37),ISNUMBER(N37)),IF(AND(D37>=30000,E37>=15000,I37>=Допускания!$D$10,N37>=Допускания!$D$11,O37=0,P37="Да"),1,0),"") | S37: =IF(NOT(ISNUMBER(R37)),"",IF(R37=1,IF(ISNUMBER(S36),S36+1,1),0)) | T37: =IF(AND(Q37="Да",EOMONTH(A37,0)<Допускания!$D$7,COUNT(B37:C37)=2,COUNT(E37:G37)=3,COUNT(L37:M37)=2,ISNUMBER(O37),L37>=M37,ISNUMBER(I37),ISNUMBER(N37)),IF(AND(D37>=50000,E37>=30000,I37>=Допускания!$D$10,N37>=Допускания!$D$11,O37=0,P37="Да"),1,0),"") | U37: =IF(NOT(ISNUMBER(T37)),"",IF(T37=1,IF(ISNUMBER(U36),U36+1,1),0))
A38: =EDATE(DATE(YEAR(Допускания!$D$6),MONTH(Допускания!$D$6),1),30) -> 47178 | D38: =IF(COUNT(B38:C38)<2,"",SUM(B38:C38)) | H38: =IF(OR(NOT(ISNUMBER(D38)),COUNT(F38:G38)<2),"",D38-SUM(F38:G38)) | I38: =IF(OR(NOT(ISNUMBER(H38)),D38=0),"",H38/D38) | N38: =IF(COUNT(L38:M38)<2,"",IF(L38=0,IF(M38=0,1,""),M38/L38)) | P38: Не | Q38: Не | R38: =IF(AND(Q38="Да",EOMONTH(A38,0)<Допускания!$D$7,COUNT(B38:C38)=2,COUNT(E38:G38)=3,COUNT(L38:M38)=2,ISNUMBER(O38),L38>=M38,ISNUMBER(I38),ISNUMBER(N38)),IF(AND(D38>=30000,E38>=15000,I38>=Допускания!$D$10,N38>=Допускания!$D$11,O38=0,P38="Да"),1,0),"") | S38: =IF(NOT(ISNUMBER(R38)),"",IF(R38=1,IF(ISNUMBER(S37),S37+1,1),0)) | T38: =IF(AND(Q38="Да",EOMONTH(A38,0)<Допускания!$D$7,COUNT(B38:C38)=2,COUNT(E38:G38)=3,COUNT(L38:M38)=2,ISNUMBER(O38),L38>=M38,ISNUMBER(I38),ISNUMBER(N38)),IF(AND(D38>=50000,E38>=30000,I38>=Допускания!$D$10,N38>=Допускания!$D$11,O38=0,P38="Да"),1,0),"") | U38: =IF(NOT(ISNUMBER(T38)),"",IF(T38=1,IF(ISNUMBER(U37),U37+1,1),0))
A39: =EDATE(DATE(YEAR(Допускания!$D$6),MONTH(Допускания!$D$6),1),31) -> 47209 | D39: =IF(COUNT(B39:C39)<2,"",SUM(B39:C39)) | H39: =IF(OR(NOT(ISNUMBER(D39)),COUNT(F39:G39)<2),"",D39-SUM(F39:G39)) | I39: =IF(OR(NOT(ISNUMBER(H39)),D39=0),"",H39/D39) | N39: =IF(COUNT(L39:M39)<2,"",IF(L39=0,IF(M39=0,1,""),M39/L39)) | P39: Не | Q39: Не | R39: =IF(AND(Q39="Да",EOMONTH(A39,0)<Допускания!$D$7,COUNT(B39:C39)=2,COUNT(E39:G39)=3,COUNT(L39:M39)=2,ISNUMBER(O39),L39>=M39,ISNUMBER(I39),ISNUMBER(N39)),IF(AND(D39>=30000,E39>=15000,I39>=Допускания!$D$10,N39>=Допускания!$D$11,O39=0,P39="Да"),1,0),"") | S39: =IF(NOT(ISNUMBER(R39)),"",IF(R39=1,IF(ISNUMBER(S38),S38+1,1),0)) | T39: =IF(AND(Q39="Да",EOMONTH(A39,0)<Допускания!$D$7,COUNT(B39:C39)=2,COUNT(E39:G39)=3,COUNT(L39:M39)=2,ISNUMBER(O39),L39>=M39,ISNUMBER(I39),ISNUMBER(N39)),IF(AND(D39>=50000,E39>=30000,I39>=Допускания!$D$10,N39>=Допускания!$D$11,O39=0,P39="Да"),1,0),"") | U39: =IF(NOT(ISNUMBER(T39)),"",IF(T39=1,IF(ISNUMBER(U38),U38+1,1),0))
A40: =EDATE(DATE(YEAR(Допускания!$D$6),MONTH(Допускания!$D$6),1),32) -> 47239 | D40: =IF(COUNT(B40:C40)<2,"",SUM(B40:C40)) | H40: =IF(OR(NOT(ISNUMBER(D40)),COUNT(F40:G40)<2),"",D40-SUM(F40:G40)) | I40: =IF(OR(NOT(ISNUMBER(H40)),D40=0),"",H40/D40) | N40: =IF(COUNT(L40:M40)<2,"",IF(L40=0,IF(M40=0,1,""),M40/L40)) | P40: Не | Q40: Не | R40: =IF(AND(Q40="Да",EOMONTH(A40,0)<Допускания!$D$7,COUNT(B40:C40)=2,COUNT(E40:G40)=3,COUNT(L40:M40)=2,ISNUMBER(O40),L40>=M40,ISNUMBER(I40),ISNUMBER(N40)),IF(AND(D40>=30000,E40>=15000,I40>=Допускания!$D$10,N40>=Допускания!$D$11,O40=0,P40="Да"),1,0),"") | S40: =IF(NOT(ISNUMBER(R40)),"",IF(R40=1,IF(ISNUMBER(S39),S39+1,1),0)) | T40: =IF(AND(Q40="Да",EOMONTH(A40,0)<Допускания!$D$7,COUNT(B40:C40)=2,COUNT(E40:G40)=3,COUNT(L40:M40)=2,ISNUMBER(O40),L40>=M40,ISNUMBER(I40),ISNUMBER(N40)),IF(AND(D40>=50000,E40>=30000,I40>=Допускания!$D$10,N40>=Допускания!$D$11,O40=0,P40="Да"),1,0),"") | U40: =IF(NOT(ISNUMBER(T40)),"",IF(T40=1,IF(ISNUMBER(U39),U39+1,1),0))
A41: =EDATE(DATE(YEAR(Допускания!$D$6),MONTH(Допускания!$D$6),1),33) -> 47270 | D41: =IF(COUNT(B41:C41)<2,"",SUM(B41:C41)) | H41: =IF(OR(NOT(ISNUMBER(D41)),COUNT(F41:G41)<2),"",D41-SUM(F41:G41)) | I41: =IF(OR(NOT(ISNUMBER(H41)),D41=0),"",H41/D41) | N41: =IF(COUNT(L41:M41)<2,"",IF(L41=0,IF(M41=0,1,""),M41/L41)) | P41: Не | Q41: Не | R41: =IF(AND(Q41="Да",EOMONTH(A41,0)<Допускания!$D$7,COUNT(B41:C41)=2,COUNT(E41:G41)=3,COUNT(L41:M41)=2,ISNUMBER(O41),L41>=M41,ISNUMBER(I41),ISNUMBER(N41)),IF(AND(D41>=30000,E41>=15000,I41>=Допускания!$D$10,N41>=Допускания!$D$11,O41=0,P41="Да"),1,0),"") | S41: =IF(NOT(ISNUMBER(R41)),"",IF(R41=1,IF(ISNUMBER(S40),S40+1,1),0)) | T41: =IF(AND(Q41="Да",EOMONTH(A41,0)<Допускания!$D$7,COUNT(B41:C41)=2,COUNT(E41:G41)=3,COUNT(L41:M41)=2,ISNUMBER(O41),L41>=M41,ISNUMBER(I41),ISNUMBER(N41)),IF(AND(D41>=50000,E41>=30000,I41>=Допускания!$D$10,N41>=Допускания!$D$11,O41=0,P41="Да"),1,0),"") | U41: =IF(NOT(ISNUMBER(T41)),"",IF(T41=1,IF(ISNUMBER(U40),U40+1,1),0))
A42: =EDATE(DATE(YEAR(Допускания!$D$6),MONTH(Допускания!$D$6),1),34) -> 47300 | D42: =IF(COUNT(B42:C42)<2,"",SUM(B42:C42)) | H42: =IF(OR(NOT(ISNUMBER(D42)),COUNT(F42:G42)<2),"",D42-SUM(F42:G42)) | I42: =IF(OR(NOT(ISNUMBER(H42)),D42=0),"",H42/D42) | N42: =IF(COUNT(L42:M42)<2,"",IF(L42=0,IF(M42=0,1,""),M42/L42)) | P42: Не | Q42: Не | R42: =IF(AND(Q42="Да",EOMONTH(A42,0)<Допускания!$D$7,COUNT(B42:C42)=2,COUNT(E42:G42)=3,COUNT(L42:M42)=2,ISNUMBER(O42),L42>=M42,ISNUMBER(I42),ISNUMBER(N42)),IF(AND(D42>=30000,E42>=15000,I42>=Допускания!$D$10,N42>=Допускания!$D$11,O42=0,P42="Да"),1,0),"") | S42: =IF(NOT(ISNUMBER(R42)),"",IF(R42=1,IF(ISNUMBER(S41),S41+1,1),0)) | T42: =IF(AND(Q42="Да",EOMONTH(A42,0)<Допускания!$D$7,COUNT(B42:C42)=2,COUNT(E42:G42)=3,COUNT(L42:M42)=2,ISNUMBER(O42),L42>=M42,ISNUMBER(I42),ISNUMBER(N42)),IF(AND(D42>=50000,E42>=30000,I42>=Допускания!$D$10,N42>=Допускания!$D$11,O42=0,P42="Да"),1,0),"") | U42: =IF(NOT(ISNUMBER(T42)),"",IF(T42=1,IF(ISNUMBER(U41),U41+1,1),0))
A44: При 0 доставки и 0 закъснения quality тестът е изпълнен. MRR и margin условията остават задължителни.

Sheet Модел
C2: Месечни финансови сценарии
C4: ASSUMPTION · прогнозен месец при натрупана клиентска база
C5: Избран модел | D5: =Допускания!F5 -> PLANNED Growth
C7: Показател | D7: 5000 | E7: 10000 | F7: 20000 | G7: 30000 | H7: 50000
C9: Обем
C10: Нови сайтове | D10: =Допускания!D57 -> 4 | E10: =Допускания!E57 -> 5 | F10: =Допускания!F57 -> 5 | G10: =Допускания!G57 -> 4 | H10: =Допускания!H57 -> 0
C11: Нови системи | D11: =Допускания!D60 -> 1 | E11: =Допускания!E60 -> 2 | F11: =Допускания!F60 -> 3 | G11: =Допускания!G60 -> 3 | H11: =Допускания!H60 -> 5
C12: Средна цена система | D12: =Допускания!D63 -> 2500 | E12: =Допускания!E63 -> 2500 | F12: =Допускания!F63 -> 3250 | G12: =Допускания!G63 -> 4400 | H12: =Допускания!H63 -> 4000
C13: Care сайтове | D13: =Допускания!D69 -> 10 | E13: =Допускания!E69 -> 10 | F13: =Допускания!F69 -> 10 | G13: =Допускания!G69 -> 20 | H13: =Допускания!H69 -> 25
C14: Care системи | D14: =Допускания!D72 -> 6 | E14: =Допускания!E72 -> 7 | F14: =Допускания!F72 -> 12 | G14: =Допускания!G72 -> 14 | H14: =Допускания!H72 -> 20
C15: Growth Basic | D15: =Допускания!D75 -> 0 | E15: =Допускания!E75 -> 8 | F15: =Допускания!F75 -> 12 | G15: =Допускания!G75 -> 30 | H15: =Допускания!H75 -> 48
C16: Growth Plus | D16: =Допускания!D78 -> 0 | E16: =Допускания!E78 -> 0 | F16: =Допускания!F78 -> 10 | G16: =Допускания!G78 -> 15 | H16: =Допускания!H78 -> 40
C17: Нови Growth за месеца | D17: =Допускания!D81 -> 0 | E17: =Допускания!E81 -> 2 | F17: =Допускания!F81 -> 4 | G17: =Допускания!G81 -> 6 | H17: =Допускания!H81 -> 8
C18: Клиенти с Care и Growth | D18: =Допускания!D84 -> 0 | E18: =Допускания!E84 -> 4 | F18: =Допускания!F84 -> 11 | G18: =Допускания!G84 -> 17 | H18: =Допускания!H84 -> 22
C20: Приход
C21: Приход от нови сайтове | D21: =D10*Допускания!$D$15 -> 1800 | E21: =E10*Допускания!$D$15 -> 2250 | F21: =F10*Допускания!$D$15 -> 2250 | G21: =G10*Допускания!$D$15 -> 1800 | H21: =H10*Допускания!$D$15 -> 0
C22: Приход от нови системи | D22: =D11*D12 -> 2500 | E22: =E11*E12 -> 5000 | F22: =F11*F12 -> 9750 | G22: =G11*G12 -> 13200 | H22: =H11*H12 -> 20000
C23: Еднократен приход | D23: =SUM(D21:D22) -> 4300 | E23: =SUM(E21:E22) -> 7250 | F23: =SUM(F21:F22) -> 12000 | G23: =SUM(G21:G22) -> 15000 | H23: =SUM(H21:H22) -> 20000 | J23: Признат проектен приход при изпълнен scope. Bookings и авансите се следят отделно.
C24: Care сайтове MRR | D24: =D13*Допускания!$D$16 -> 400 | E24: =E13*Допускания!$D$16 -> 400 | F24: =F13*Допускания!$D$16 -> 400 | G24: =G13*Допускания!$D$16 -> 800 | H24: =H13*Допускания!$D$16 -> 1000
C25: Care системи MRR | D25: =D14*Допускания!$D$17 -> 300 | E25: =E14*Допускания!$D$17 -> 350 | F25: =F14*Допускания!$D$17 -> 600 | G25: =G14*Допускания!$D$17 -> 700 | H25: =H14*Допускания!$D$17 -> 1000
C26: Growth Basic MRR | D26: =D15*Допускания!$D$18 -> 0 | E26: =E15*Допускания!$D$18 -> 2000 | F26: =F15*Допускания!$D$18 -> 3000 | G26: =G15*Допускания!$D$18 -> 7500 | H26: =H15*Допускания!$D$18 -> 12000
C27: Growth Plus MRR | D27: =D16*Допускания!$D$19 -> 0 | E27: =E16*Допускания!$D$19 -> 0 | F27: =F16*Допускания!$D$19 -> 4000 | G27: =G16*Допускания!$D$19 -> 6000 | H27: =H16*Допускания!$D$19 -> 16000
C28: Общ MRR | D28: =SUM(D24:D27) -> 700 | E28: =SUM(E24:E27) -> 2750 | F28: =SUM(F24:F27) -> 8000 | G28: =SUM(G24:G27) -> 15000 | H28: =SUM(H24:H27) -> 30000 | J28: Пълен run-rate месец. Growth новите клиенти са включени в активната база.
C29: Общ месечен приход | D29: =D23+D28 -> 5000 | E29: =E23+E28 -> 10000 | F29: =F23+F28 -> 20000 | G29: =G23+G28 -> 30000 | H29: =H23+H28 -> 50000
C30: Отклонение от целта | D30: =D29-D7 -> 0 | E30: =E29-E7 -> 0 | F30: =F29-F7 -> 0 | G30: =G29-G7 -> 0 | H30: =H29-H7 -> 0
C31: Уникални recurring клиенти | D31: =SUM(D13:D16)-D18 -> 16 | E31: =SUM(E13:E16)-E18 -> 21 | F31: =SUM(F13:F16)-F18 -> 33 | G31: =SUM(G13:G16)-G18 -> 62 | H31: =SUM(H13:H16)-H18 -> 111
C32: Нови уникални клиентски победи | D32: =D10+D11+D17*(1-Допускания!$D$47) -> 5 | E32: =E10+E11+E17*(1-Допускания!$D$47) -> 8 | F32: =F10+F11+F17*(1-Допускания!$D$47) -> 10 | G32: =G10+G11+G17*(1-Допускания!$D$47) -> 10 | H32: =H10+H11+H17*(1-Допускания!$D$47) -> 9
C34: Капацитет и пряк разход
C35: Development часове | D35: =D10*Допускания!$D$20+D11*Допускания!D66 -> 72 | E35: =E10*Допускания!$D$20+E11*Допускания!E66 -> 120 | F35: =F10*Допускания!$D$20+F11*Допускания!F66 -> 196 | G35: =G10*Допускания!$D$20+G11*Допускания!G66 -> 224 | H35: =H10*Допускания!$D$20+H11*Допускания!H66 -> 320
C36: Care часове | D36: =D13*Допускания!$D$21+D14*Допускания!$D$22 -> 7.2 | E36: =E13*Допускания!$D$21+E14*Допускания!$D$22 -> 7.9 | F36: =F13*Допускания!$D$21+F14*Допускания!$D$22 -> 11.4 | G36: =G13*Допускания!$D$21+G14*Допускания!$D$22 -> 15.8 | H36: =H13*Допускания!$D$21+H14*Допускания!$D$22 -> 21.5
C37: Growth часове текущи | D37: =D15*Допускания!$D$23+D16*Допускания!$D$24 -> 0 | E37: =E15*Допускания!$D$23+E16*Допускания!$D$24 -> 16 | F37: =F15*Допускания!$D$23+F16*Допускания!$D$24 -> 54 | G37: =G15*Допускания!$D$23+G16*Допускания!$D$24 -> 105 | H37: =H15*Допускания!$D$23+H16*Допускания!$D$24 -> 216
C38: Growth onboarding часове | D38: =D17*Допускания!$D$25 -> 0 | E38: =E17*Допускания!$D$25 -> 6 | F38: =F17*Допускания!$D$25 -> 12 | G38: =G17*Допускания!$D$25 -> 18 | H38: =H17*Допускания!$D$25 -> 24
C39: Общо productive часа | D39: =SUM(D35:D38) -> 79.2 | E39: =SUM(E35:E38) -> 149.9 | F39: =SUM(F35:F38) -> 273.4 | G39: =SUM(G35:G38) -> 362.8 | H39: =SUM(H35:H38) -> 581.5 | J39: 100 productive часа = 1 FTE. Sales часовете са отделно.
C40: Delivery capacity FTE | D40: =D39/Допускания!$D$46 -> 0.792 | E40: =E39/Допускания!$D$46 -> 1.499 | F40: =F39/Допускания!$D$46 -> 2.734 | G40: =G39/Допускания!$D$46 -> 3.628 | H40: =H39/Допускания!$D$46 -> 5.815
C41: Development труд | D41: =D35*Допускания!$D$26 -> 1800 | E41: =E35*Допускания!$D$26 -> 3000 | F41: =F35*Допускания!$D$26 -> 4900 | G41: =G35*Допускания!$D$26 -> 5600 | H41: =H35*Допускания!$D$26 -> 8000
C42: Care труд | D42: =D36*Допускания!$D$27 -> 144 | E42: =E36*Допускания!$D$27 -> 158 | F42: =F36*Допускания!$D$27 -> 228 | G42: =G36*Допускания!$D$27 -> 316 | H42: =H36*Допускания!$D$27 -> 430
C43: Growth труд с onboarding | D43: =(D37+D38)*Допускания!$D$28 -> 0 | E43: =(E37+E38)*Допускания!$D$28 -> 660 | F43: =(F37+F38)*Допускания!$D$28 -> 1980 | G43: =(G37+G38)*Допускания!$D$28 -> 3690 | H43: =(H37+H38)*Допускания!$D$28 -> 7200
C44: Общо contractors | D44: =SUM(D41:D43) -> 1944 | E44: =SUM(E41:E43) -> 3818 | F44: =SUM(F41:F43) -> 7108 | G44: =SUM(G41:G43) -> 9606 | H44: =SUM(H41:H43) -> 15630
C45: Пряка инфраструктура и tools | D45: =D13*Допускания!$D$29+D14*Допускания!$D$30+D10*Допускания!$D$31+D11*Допускания!$D$32+D15*Допускания!$D$33+D16*Допускания!$D$34 -> 147 | E45: =E13*Допускания!$D$29+E14*Допускания!$D$30+E10*Допускания!$D$31+E11*Допускания!$D$32+E15*Допускания!$D$33+E16*Допускания!$D$34 -> 259 | F45: =F13*Допускания!$D$29+F14*Допускания!$D$30+F10*Допускания!$D$31+F11*Допускания!$D$32+F15*Допускания!$D$33+F16*Допускания!$D$34 -> 574 | G45: =G13*Допускания!$D$29+G14*Допускания!$D$30+G10*Допускания!$D$31+G11*Допускания!$D$32+G15*Допускания!$D$33+G16*Допускания!$D$34 -> 913 | H45: =H13*Допускания!$D$29+H14*Допускания!$D$30+H10*Допускания!$D$31+H11*Допускания!$D$32+H15*Допускания!$D$33+H16*Допускания!$D$34 -> 1695
C46: Общо преки разходи | D46: =D44+D45 -> 2091 | E46: =E44+E45 -> 4077 | F46: =F44+F45 -> 7682 | G46: =G44+G45 -> 10519 | H46: =H44+H45 -> 17325
C47: Брутна печалба | D47: =D29-D46 -> 2909 | E47: =E29-E46 -> 5923 | F47: =F29-F46 -> 12318 | G47: =G29-G46 -> 19481 | H47: =H29-H46 -> 32675
C48: Брутен марж | D48: =IF(D29=0,"n.a.",D47/D29) -> 0.5818 | E48: =IF(E29=0,"n.a.",E47/E29) -> 0.5923 | F48: =IF(F29=0,"n.a.",F47/F29) -> 0.6159 | G48: =IF(G29=0,"n.a.",G47/G29) -> 0.64936667 | H48: =IF(H29=0,"n.a.",H47/H29) -> 0.6535
C50: Оперативни разходи
C51: Payroll с founder pay | D51: =Допускания!D87 -> 1500 | E51: =Допускания!E87 -> 2800 | F51: =Допускания!F87 -> 4000 | G51: =Допускания!G87 -> 5000 | H51: =Допускания!H87 -> 8500 | J51: Включва основателя и sales/ops/CS. Не добавяй същия труд втори път.
C52: Общ софтуер | D52: =Допускания!D90 -> 250 | E52: =Допускания!E90 -> 350 | F52: =Допускания!F90 -> 500 | G52: =Допускания!G90 -> 600 | H52: =Допускания!H90 -> 900
C53: Реклама BDS | D53: =Допускания!D93 -> 300 | E53: =Допускания!E93 -> 500 | F53: =Допускания!F93 -> 750 | G53: =Допускания!G93 -> 900 | H53: =Допускания!H93 -> 1500
C54: Администрация | D54: =Допускания!D96 -> 200 | E54: =Допускания!E96 -> 300 | F54: =Допускания!F96 -> 400 | G54: =Допускания!G96 -> 500 | H54: =Допускания!H96 -> 700
C55: Обучение и подобрения | D55: =Допускания!D99 -> 100 | E55: =Допускания!E99 -> 200 | F55: =Допускания!F99 -> 400 | G55: =Допускания!G99 -> 600 | H55: =Допускания!H99 -> 1000
C56: Общо оперативни разходи | D56: =SUM(D51:D55) -> 2350 | E56: =SUM(E51:E55) -> 4150 | F56: =SUM(F51:F55) -> 6050 | G56: =SUM(G51:G55) -> 7600 | H56: =SUM(H51:H55) -> 12600
C57: Оперативна печалба | D57: =D47-D56 -> 559 | E57: =E47-E56 -> 1773 | F57: =F47-F56 -> 6268 | G57: =G47-G56 -> 11881 | H57: =H47-H56 -> 20075
C58: Оперативен марж | D58: =IF(D29=0,"n.a.",D57/D29) -> 0.1118 | E58: =IF(E29=0,"n.a.",E57/E29) -> 0.1773 | F58: =IF(F29=0,"n.a.",F57/F29) -> 0.3134 | G58: =IF(G29=0,"n.a.",G57/G29) -> 0.39603333 | H58: =IF(H29=0,"n.a.",H57/H29) -> 0.4015
C60: Sales обем за един месец
C61: Нови клиентски победи | D61: =D32 -> 5 | E61: =E32 -> 8 | F61: =F32 -> 10 | G61: =G32 -> 10 | H61: =H32 -> 9 | J61: Консервативен outbound еквивалент; не предполага допълнителни безплатни paid wins.
C62: Изпратени предложения | D62: =ROUNDUP(D61/Допускания!$D$35,0) -> 20 | E62: =ROUNDUP(E61/Допускания!$D$35,0) -> 32 | F62: =ROUNDUP(F61/Допускания!$D$35,0) -> 40 | G62: =ROUNDUP(G61/Допускания!$D$35,0) -> 40 | H62: =ROUNDUP(H61/Допускания!$D$35,0) -> 36
C63: Проведени срещи | D63: =ROUNDUP(D62/Допускания!$D$36,0) -> 27 | E63: =ROUNDUP(E62/Допускания!$D$36,0) -> 43 | F63: =ROUNDUP(F62/Допускания!$D$36,0) -> 54 | G63: =ROUNDUP(G62/Допускания!$D$36,0) -> 54 | H63: =ROUNDUP(H62/Допускания!$D$36,0) -> 48
C64: Квалифицирани лийдове SQL | D64: =ROUNDUP(D63/Допускания!$D$37,0) -> 34 | E64: =ROUNDUP(E63/Допускания!$D$37,0) -> 54 | F64: =ROUNDUP(F63/Допускания!$D$37,0) -> 68 | G64: =ROUNDUP(G63/Допускания!$D$37,0) -> 68 | H64: =ROUNDUP(H63/Допускания!$D$37,0) -> 60
C65: Реални контакти | D65: =ROUNDUP(D64/Допускания!$D$38,0) -> 136 | E65: =ROUNDUP(E64/Допускания!$D$38,0) -> 216 | F65: =ROUNDUP(F64/Допускания!$D$38,0) -> 272 | G65: =ROUNDUP(G64/Допускания!$D$38,0) -> 272 | H65: =ROUNDUP(H64/Допускания!$D$38,0) -> 240
C66: Verified prospects | D66: =ROUNDUP(D65/Допускания!$D$39,0) -> 340 | E66: =ROUNDUP(E65/Допускания!$D$39,0) -> 540 | F66: =ROUNDUP(F65/Допускания!$D$39,0) -> 680 | G66: =ROUNDUP(G65/Допускания!$D$39,0) -> 680 | H66: =ROUNDUP(H65/Допускания!$D$39,0) -> 600
C67: Опити за разговор | D67: =D66*Допускания!$D$41 -> 680 | E67: =E66*Допускания!$D$41 -> 1080 | F67: =F66*Допускания!$D$41 -> 1360 | G67: =G66*Допускания!$D$41 -> 1360 | H67: =H66*Допускания!$D$41 -> 1200
C68: Raw prospects за research | D68: =ROUNDUP(D66/Допускания!$D$40,0) -> 567 | E68: =ROUNDUP(E66/Допускания!$D$40,0) -> 900 | F68: =ROUNDUP(F66/Допускания!$D$40,0) -> 1134 | G68: =ROUNDUP(G66/Допускания!$D$40,0) -> 1134 | H68: =ROUNDUP(H66/Допускания!$D$40,0) -> 1000
C69: Sales часове | D69: =D66*Допускания!$D$42+D67*Допускания!$D$43+D63*Допускания!$D$44+D62*Допускания!$D$45 -> 86.25 | E69: =E66*Допускания!$D$42+E67*Допускания!$D$43+E63*Допускания!$D$44+E62*Допускания!$D$45 -> 137.25 | F69: =F66*Допускания!$D$42+F67*Допускания!$D$43+F63*Допускания!$D$44+F62*Допускания!$D$45 -> 172.5 | G69: =G66*Допускания!$D$42+G67*Допускания!$D$43+G63*Допускания!$D$44+G62*Допускания!$D$45 -> 172.5 | H69: =H66*Допускания!$D$42+H67*Допускания!$D$43+H63*Допускания!$D$44+H62*Допускания!$D$45 -> 153
C70: Sales capacity FTE | D70: =D69/Допускания!$D$46 -> 0.8625 | E70: =E69/Допускания!$D$46 -> 1.3725 | F70: =F69/Допускания!$D$46 -> 1.725 | G70: =G69/Допускания!$D$46 -> 1.725 | H70: =H69/Допускания!$D$46 -> 1.53
C72: Чувствителност и натрупване
C73: Печалба при 50% повече труд | D73: =D57-D44*0.5 -> -413 | E73: =E57-E44*0.5 -> -136 | F73: =F57-F44*0.5 -> 2714 | G73: =G57-G44*0.5 -> 7078 | H73: =H57-H44*0.5 -> 12260
C74: Марж при 50% повече труд | D74: =IF(D29=0,"n.a.",D73/D29) -> -0.0826 | E74: =IF(E29=0,"n.a.",E73/E29) -> -0.0136 | F74: =IF(F29=0,"n.a.",F73/F29) -> 0.1357 | G74: =IF(G29=0,"n.a.",G73/G29) -> 0.23593333 | H74: =IF(H29=0,"n.a.",H73/H29) -> 0.2452
C75: Печалба при двойни dev часове | D75: =D57-D41 -> -1241 | E75: =E57-E41 -> -1227 | F75: =F57-F41 -> 1368 | G75: =G57-G41 -> 6281 | H75: =H57-H41 -> 12075
C76: Целева Growth клиентска база | D76: =D15+D16 -> 0 | E76: =E15+E16 -> 8 | F76: =F15+F16 -> 22 | G76: =G15+G16 -> 45 | H76: =H15+H16 -> 88
C77: Месеци за Growth база от нула | D77: =IF(D76=0,0,IF(D17=0,"n.a.",IF(Допускания!$D$48=0,ROUNDUP(D76/D17,0),IF(D76*Допускания!$D$48>=D17,"n.a.",ROUNDUP(LN(1-D76*Допускания!$D$48/D17)/LN(1-Допускания!$D$48),0))))) -> 0 | E77: =IF(E76=0,0,IF(E17=0,"n.a.",IF(Допускания!$D$48=0,ROUNDUP(E76/E17,0),IF(E76*Допускания!$D$48>=E17,"n.a.",ROUNDUP(LN(1-E76*Допускания!$D$48/E17)/LN(1-Допускания!$D$48),0))))) -> 5 | F77: =IF(F76=0,0,IF(F17=0,"n.a.",IF(Допускания!$D$48=0,ROUNDUP(F76/F17,0),IF(F76*Допускания!$D$48>=F17,"n.a.",ROUNDUP(LN(1-F76*Допускания!$D$48/F17)/LN(1-Допускания!$D$48),0))))) -> 6 | G77: =IF(G76=0,0,IF(G17=0,"n.a.",IF(Допускания!$D$48=0,ROUNDUP(G76/G17,0),IF(G76*Допускания!$D$48>=G17,"n.a.",ROUNDUP(LN(1-G76*Допускания!$D$48/G17)/LN(1-Допускания!$D$48),0))))) -> 9 | H77: =IF(H76=0,0,IF(H17=0,"n.a.",IF(Допускания!$D$48=0,ROUNDUP(H76/H17,0),IF(H76*Допускания!$D$48>=H17,"n.a.",ROUNDUP(LN(1-H76*Допускания!$D$48/H17)/LN(1-Допускания!$D$48),0))))) -> 13 | J77: Постоянен new Growth темп от първия месец; не включва ramp-up.
C78: 12 месечна Growth retention | D78: =(1-Допускания!$D$48)^12 -> 0.78471672 | E78: =(1-Допускания!$D$48)^12 -> 0.78471672 | F78: =(1-Допускания!$D$48)^12 -> 0.78471672 | G78: =(1-Допускания!$D$48)^12 -> 0.78471672 | H78: =(1-Допускания!$D$48)^12 -> 0.78471672

Sheet Допускания
C2: Допускания и управление
C5: Избран модел | D5: 2 | F5: =IF(D5=1,"Каталог","PLANNED Growth") -> PLANNED Growth | J5: 1 = официален каталог; 2 = планиран Growth модел
C6: Начало на плана | D6: 46286 | J6: Промени преди въвеждане на actuals; после запази фиксирана.
C7: Дата за преглед | D7: =TODAY() -> 46282 | J7: TODAY се обновява при отваряне. Може да зададеш отчетна дата.
C8: Цел месечен приход | D8: 30000 | J8: Целта е признат приход без ДДС и клиентски рекламни бюджети.
C9: Цел MRR | D9: 15000 | J9: За цел 50 000 евро промени на 30 000 евро.
C10: Минимален оперативен марж | D10: 0.25 | J10: След възнаграждение на основателя; преди корпоративен данък.
C11: Минимум доставки навреме | D11: 0.9 | J11: От приключените за месеца проекти.
C12: Поредни месеци за устойчивост | D12: 3 | J12: Критерий за потвърдена устойчивост.
C14: Общ параметър | D14: Стойност | J14: Статус и източник
C15: BUSINESS сайт | D15: 450 | J15: CURRENT STATE · S03
C16: Care сайт на месец | D16: 40 | J16: =HYPERLINK("https://github.com/PreslavBlazhev/Bulgaria-Digital-Services/blob/4e364d88adb45a25519b03710624bd96f7425450/website/PRICES%20AND%20PACKETS/%D0%A6%D0%B5%D0%BD%D0%B8%20%D0%B7%D0%B0%20%D1%81%D0%B0%D0%B9%D1%82%D0%BE%D0%B2%D0%B5%20%D0%B8%20%D1%82%D1%8F%D1%85%D0%BD%D0%B0%D1%82%D0%B0%20%D0%BF%D0%BE%D0%B4%D0%B4%D1%80%D1%8A%D0%B6%D0%BA%D0%B0.txt","S03 Официални цени сайтове") -> S03 Официални цени сайтове
C17: Care система на месец | D17: 50 | J17: =HYPERLINK("https://github.com/PreslavBlazhev/Bulgaria-Digital-Services/blob/4e364d88adb45a25519b03710624bd96f7425450/website/PRICES%20AND%20PACKETS/%D0%A6%D0%B5%D0%BD%D0%B8%20%D0%B7%D0%B0%20%D0%A1%D0%B8%D1%81%D1%82%D0%B5%D0%BC%D0%B8%20%D0%B8%20%D1%81%D0%BF%D0%B8%D1%81%D1%8A%D0%BA%20%D1%81%20%D1%84%D1%83%D0%BD%D0%BA%D1%86%D0%B8%D0%B8.txt","S04 Официални цени системи") -> S04 Официални цени системи
C18: Growth Basic на месец | D18: 250 | J18: PLANNED · цена за валидиране с 3 платени пилота
C19: Growth Plus на месец | D19: 400 | J19: PLANNED · цена за валидиране с 3 платени пилота
C20: Часове BUSINESS сайт | D20: 8 | J20: ASSUMPTION · с reusable components и ограничен scope
C21: Часове Care сайт | D21: 0.3 | J21: ASSUMPTION · средно за месец
C22: Часове Care система | D22: 0.7 | J22: ASSUMPTION · средно за месец
C23: Часове Growth Basic | D23: 2 | J23: ASSUMPTION · месечно без onboarding
C24: Часове Growth Plus | D24: 3 | J24: ASSUMPTION · месечно без onboarding
C25: Onboarding часа за нов Growth | D25: 3 | J25: ASSUMPTION · еднократно
C26: Delivery евро на час | D26: 25 | J26: ASSUMPTION · пълен пряк разход
C27: Support евро на час | D27: 20 | J27: ASSUMPTION · пълен пряк разход
C28: Growth евро на час | D28: 30 | J28: ASSUMPTION · пълен пряк разход
C29: Инфраструктура Care сайт | D29: 4 | J29: ASSUMPTION · евро на клиент месечно
... C50: Седмици в месец | D50: 4.3333333 | J50: ASSUMPTION · за среден седмичен sales target
C52: Всички моделни обеми и разходи по-долу са ASSUMPTION.
C53: Цените се третират като нетни. Данъчният статус се потвърждава с T01.
C55: Цел за месеца | D55: 5000 | E55: 10000 | F55: 20000 | G55: 30000 | H55: 50000
C57: Нови сайтове активен | D57: =IF(CHOOSE($D$5,ISNUMBER(D58),ISNUMBER(D59)),CHOOSE($D$5,D58,D59),"Липсва вход") -> 4 | E57: =IF(CHOOSE($D$5,ISNUMBER(E58),ISNUMBER(E59)),CHOOSE($D$5,E58,E59),"Липсва вход") -> 5 | F57: =IF(CHOOSE($D$5,ISNUMBER(F58),ISNUMBER(F59)),CHOOSE($D$5,F58,F59),"Липсва вход") -> 5 | G57: =IF(CHOOSE($D$5,ISNUMBER(G58),ISNUMBER(G59)),CHOOSE($D$5,G58,G59),"Липсва вход") -> 4 | H57: =IF(CHOOSE($D$5,ISNUMBER(H58),ISNUMBER(H59)),CHOOSE($D$5,H58,H59),"Липсва вход") -> 0
C58: 1 Каталог | D58: 4 | E58: 5 | F58: 10 | G58: 10 | H58: 10 | J58: Payroll е sales, operations, CS и founder pay. Delivery вече е в contractors.
C59: 2 Growth | D59: 4 | E59: 5 | F59: 5 | G59: 4 | H59: 0
C60: Нови системи активен | D60: =IF(CHOOSE($D$5,ISNUMBER(D61),ISNUMBER(D62)),CHOOSE($D$5,D61,D62),"Липсва вход") -> 1 | E60: =IF(CHOOSE($D$5,ISNUMBER(E61),ISNUMBER(E62)),CHOOSE($D$5,E61,E62),"Липсва вход") -> 2 | F60: =IF(CHOOSE($D$5,ISNUMBER(F61),ISNUMBER(F62)),CHOOSE($D$5,F61,F62),"Липсва вход") -> 3 | G60: =IF(CHOOSE($D$5,ISNUMBER(G61),ISNUMBER(G62)),CHOOSE($D$5,G61,G62),"Липсва вход") -> 3 | H60: =IF(CHOOSE($D$5,ISNUMBER(H61),ISNUMBER(H62)),CHOOSE($D$5,H61,H62),"Липсва вход") -> 5 | J60: Care и Growth са натрупана база; не се придобиват за един месец.
C61: 1 Каталог | D61: 1 | E61: 2 | F61: 4 | G61: 7 | H61: 9
C62: 2 Growth | D62: 1 | E62: 2 | F62: 3 | G62: 3 | H62: 5 | J62: При overlap се брои един уникален клиент. Няма двойно броене на хостинг.
C63: Средна цена система активен | D63: =IF(CHOOSE($D$5,ISNUMBER(D64),ISNUMBER(D65)),CHOOSE($D$5,D64,D65),"Липсва вход") -> 2500 | E63: =IF(CHOOSE($D$5,ISNUMBER(E64),ISNUMBER(E65)),CHOOSE($D$5,E64,E65),"Липсва вход") -> 2500 | F63: =IF(CHOOSE($D$5,ISNUMBER(F64),ISNUMBER(F65)),CHOOSE($D$5,F64,F65),"Липсва вход") -> 3250 | G63: =IF(CHOOSE($D$5,ISNUMBER(G64),ISNUMBER(G65)),CHOOSE($D$5,G64,G65),"Липсва вход") -> 4400 | H63: =IF(CHOOSE($D$5,ISNUMBER(H64),ISNUMBER(H65)),CHOOSE($D$5,H64,H65),"Липсва вход") -> 4000
C64: 1 Каталог | D64: 2500 | E64: 2500 | F64: 2500 | G64: 2500 | H64: 3500
C65: 2 Growth | D65: 2500 | E65: 2500 | F65: 3250 | G65: 4400 | H65: 4000
C66: Часове на система активен | D66: =IF(CHOOSE($D$5,ISNUMBER(D67),ISNUMBER(D68)),CHOOSE($D$5,D67,D68),"Липсва вход") -> 40 | E66: =IF(CHOOSE($D$5,ISNUMBER(E67),ISNUMBER(E68)),CHOOSE($D$5,E67,E68),"Липсва вход") -> 40 | F66: =IF(CHOOSE($D$5,ISNUMBER(F67),ISNUMBER(F68)),CHOOSE($D$5,F67,F68),"Липсва вход") -> 52 | G66: =IF(CHOOSE($D$5,ISNUMBER(G67),ISNUMBER(G68)),CHOOSE($D$5,G67,G68),"Липсва вход") -> 64 | H66: =IF(CHOOSE($D$5,ISNUMBER(H67),ISNUMBER(H68)),CHOOSE($D$5,H67,H68),"Липсва вход") -> 64
C67: 1 Каталог | D67: 40 | E67: 40 | F67: 40 | G67: 40 | H67: 56
C68: 2 Growth | D68: 40 | E68: 40 | F68: 52 | G68: 64 | H68: 64
C69: Активни Care сайтове активен | D69: =IF(CHOOSE($D$5,ISNUMBER(D70),ISNUMBER(D71)),CHOOSE($D$5,D70,D71),"Липсва вход") -> 10 | E69: =IF(CHOOSE($D$5,ISNUMBER(E70),ISNUMBER(E71)),CHOOSE($D$5,E70,E71),"Липсва вход") -> 10 | F69: =IF(CHOOSE($D$5,ISNUMBER(F70),ISNUMBER(F71)),CHOOSE($D$5,F70,F71),"Липсва вход") -> 10 | G69: =IF(CHOOSE($D$5,ISNUMBER(G70),ISNUMBER(G71)),CHOOSE($D$5,G70,G71),"Липсва вход") -> 20 | H69: =IF(CHOOSE($D$5,ISNUMBER(H70),ISNUMBER(H71)),CHOOSE($D$5,H70,H71),"Липсва вход") -> 25
C70: 1 Каталог | D70: 10 | E70: 25 | F70: 50 | G70: 100 | H70: 100
C71: 2 Growth | D71: 10 | E71: 10 | F71: 10 | G71: 20 | H71: 25
C72: Активни Care системи активен | D72: =IF(CHOOSE($D$5,ISNUMBER(D73),ISNUMBER(D74)),CHOOSE($D$5,D73,D74),"Липсва вход") -> 6 | E72: =IF(CHOOSE($D$5,ISNUMBER(E73),ISNUMBER(E74)),CHOOSE($D$5,E73,E74),"Липсва вход") -> 7 | F72: =IF(CHOOSE($D$5,ISNUMBER(F73),ISNUMBER(F74)),CHOOSE($D$5,F73,F74),"Липсва вход") -> 12 | G72: =IF(CHOOSE($D$5,ISNUMBER(G73),ISNUMBER(G74)),CHOOSE($D$5,G73,G74),"Липсва вход") -> 14 | H72: =IF(CHOOSE($D$5,ISNUMBER(H73),ISNUMBER(H74)),CHOOSE($D$5,H73,H74),"Липсва вход") -> 20
C73: 1 Каталог | D73: 6 | E73: 35 | F73: 70 | G73: 80 | H73: 200
C74: 2 Growth | D74: 6 | E74: 7 | F74: 12 | G74: 14 | H74: 20
C75: Активни Growth Basic активен | D75: =IF(CHOOSE($D$5,ISNUMBER(D76),ISNUMBER(D77)),CHOOSE($D$5,D76,D77),"Липсва вход") -> 0 | E75: =IF(CHOOSE($D$5,ISNUMBER(E76),ISNUMBER(E77)),CHOOSE($D$5,E76,E77),"Липсва вход") -> 8 | F75: =IF(CHOOSE($D$5,ISNUMBER(F76),ISNUMBER(F77)),CHOOSE($D$5,F76,F77),"Липсва вход") -> 12 | G75: =IF(CHOOSE($D$5,ISNUMBER(G76),ISNUMBER(G77)),CHOOSE($D$5,G76,G77),"Липсва вход") -> 30 | H75: =IF(CHOOSE($D$5,ISNUMBER(H76),ISNUMBER(H77)),CHOOSE($D$5,H76,H77),"Липсва вход") -> 48
C76: 1 Каталог | D76: 0 | E76: 0 | F76: 0 | G76: 0 | H76: 0
C77: 2 Growth | D77: 0 | E77: 8 | F77: 12 | G77: 30 | H77: 48
C78: Активни Growth Plus активен | D78: =IF(CHOOSE($D$5,ISNUMBER(D79),ISNUMBER(D80)),CHOOSE($D$5,D79,D80),"Липсва вход") -> 0 | E78: =IF(CHOOSE($D$5,ISNUMBER(E79),ISNUMBER(E80)),CHOOSE($D$5,E79,E80),"Липсва вход") -> 0 | F78: =IF(CHOOSE($D$5,ISNUMBER(F79),ISNUMBER(F80)),CHOOSE($D$5,F79,F80),"Липсва вход") -> 10 | G78: =IF(CHOOSE($D$5,ISNUMBER(G79),ISNUMBER(G80)),CHOOSE($D$5,G79,G80),"Липсва вход") -> 15 | H78: =IF(CHOOSE($D$5,ISNUMBER(H79),ISNUMBER(H80)),CHOOSE($D$5,H79,H80),"Липсва вход") -> 40
C79: 1 Каталог | D79: 0 | E79: 0 | F79: 0 | G79: 0 | H79: 0
C80: 2 Growth | D80: 0 | E80: 0 | F80: 10 | G80: 15 | H80: 40
C81: Нови Growth за месеца активен | D81: =IF(CHOOSE($D$5,ISNUMBER(D82),ISNUMBER(D83)),CHOOSE($D$5,D82,D83),"Липсва вход") -> 0 | E81: =IF(CHOOSE($D$5,ISNUMBER(E82),ISNUMBER(E83)),CHOOSE($D$5,E82,E83),"Липсва вход") -> 2 | F81: =IF(CHOOSE($D$5,ISNUMBER(F82),ISNUMBER(F83)),CHOOSE($D$5,F82,F83),"Липсва вход") -> 4 | G81: =IF(CHOOSE($D$5,ISNUMBER(G82),ISNUMBER(G83)),CHOOSE($D$5,G82,G83),"Липсва вход") -> 6 | H81: =IF(CHOOSE($D$5,ISNUMBER(H82),ISNUMBER(H83)),CHOOSE($D$5,H82,H83),"Липсва вход") -> 8
C82: 1 Каталог | D82: 0 | E82: 0 | F82: 0 | G82: 0 | H82: 0
C83: 2 Growth | D83: 0 | E83: 2 | F83: 4 | G83: 6 | H83: 8
C84: Клиенти с Care и Growth активен | D84: =IF(CHOOSE($D$5,ISNUMBER(D85),ISNUMBER(D86)),CHOOSE($D$5,D85,D86),"Липсва вход") -> 0 | E84: =IF(CHOOSE($D$5,ISNUMBER(E85),ISNUMBER(E86)),CHOOSE($D$5,E85,E86),"Липсва вход") -> 4 | F84: =IF(CHOOSE($D$5,ISNUMBER(F85),ISNUMBER(F86)),CHOOSE($D$5,F85,F86),"Липсва вход") -> 11 | G84: =IF(CHOOSE($D$5,ISNUMBER(G85),ISNUMBER(G86)),CHOOSE($D$5,G85,G86),"Липсва вход") -> 17 | H84: =IF(CHOOSE($D$5,ISNUMBER(H85),ISNUMBER(H86)),CHOOSE($D$5,H85,H86),"Липсва вход") -> 22
C85: 1 Каталог | D85: 0 | E85: 0 | F85: 0 | G85: 0 | H85: 0
C86: 2 Growth | D86: 0 | E86: 4 | F86: 11 | G86: 17 | H86: 22
C87: Payroll с founder pay активен | D87: =IF(CHOOSE($D$5,ISNUMBER(D88),ISNUMBER(D89)),CHOOSE($D$5,D88,D89),"Липсва вход") -> 1500 | E87: =IF(CHOOSE($D$5,ISNUMBER(E88),ISNUMBER(E89)),CHOOSE($D$5,E88,E89),"Липсва вход") -> 2800 | F87: =IF(CHOOSE($D$5,ISNUMBER(F88),ISNUMBER(F89)),CHOOSE($D$5,F88,F89),"Липсва вход") -> 4000 | G87: =IF(CHOOSE($D$5,ISNUMBER(G88),ISNUMBER(G89)),CHOOSE($D$5,G88,G89),"Липсва вход") -> 5000 | H87: =IF(CHOOSE($D$5,ISNUMBER(H88),ISNUMBER(H89)),CHOOSE($D$5,H88,H89),"Липсва вход") -> 8500
C88: 1 Каталог | D88: 1500 | E88: 2800 | F88: 4400 | G88: 6400 | H88: 9000
C89: 2 Growth | D89: 1500 | E89: 2800 | F89: 4000 | G89: 5000 | H89: 8500
C90: Общ софтуер активен | D90: =IF(CHOOSE($D$5,ISNUMBER(D91),ISNUMBER(D92)),CHOOSE($D$5,D91,D92),"Липсва вход") -> 250 | E90: =IF(CHOOSE($D$5,ISNUMBER(E91),ISNUMBER(E92)),CHOOSE($D$5,E91,E92),"Липсва вход") -> 350 | F90: =IF(CHOOSE($D$5,ISNUMBER(F91),ISNUMBER(F92)),CHOOSE($D$5,F91,F92),"Липсва вход") -> 500 | G90: =IF(CHOOSE($D$5,ISNUMBER(G91),ISNUMBER(G92)),CHOOSE($D$5,G91,G92),"Липсва вход") -> 600 | H90: =IF(CHOOSE($D$5,ISNUMBER(H91),ISNUMBER(H92)),CHOOSE($D$5,H91,H92),"Липсва вход") -> 900
C91: 1 Каталог | D91: 250 | E91: 350 | F91: 500 | G91: 700 | H91: 1100
C92: 2 Growth | D92: 250 | E92: 350 | F92: 500 | G92: 600 | H92: 900
C93: Реклама за BDS активен | D93: =IF(CHOOSE($D$5,ISNUMBER(D94),ISNUMBER(D95)),CHOOSE($D$5,D94,D95),"Липсва вход") -> 300 | E93: =IF(CHOOSE($D$5,ISNUMBER(E94),ISNUMBER(E95)),CHOOSE($D$5,E94,E95),"Липсва вход") -> 500 | F93: =IF(CHOOSE($D$5,ISNUMBER(F94),ISNUMBER(F95)),CHOOSE($D$5,F94,F95),"Липсва вход") -> 750 | G93: =IF(CHOOSE($D$5,ISNUMBER(G94),ISNUMBER(G95)),CHOOSE($D$5,G94,G95),"Липсва вход") -> 900 | H93: =IF(CHOOSE($D$5,ISNUMBER(H94),ISNUMBER(H95)),CHOOSE($D$5,H94,H95),"Липсва вход") -> 1500
C94: 1 Каталог | D94: 300 | E94: 500 | F94: 750 | G94: 1000 | H94: 1500
C95: 2 Growth | D95: 300 | E95: 500 | F95: 750 | G95: 900 | H95: 1500
C96: Администрация активен | D96: =IF(CHOOSE($D$5,ISNUMBER(D97),ISNUMBER(D98)),CHOOSE($D$5,D97,D98),"Липсва вход") -> 200 | E96: =IF(CHOOSE($D$5,ISNUMBER(E97),ISNUMBER(E98)),CHOOSE($D$5,E97,E98),"Липсва вход") -> 300 | F96: =IF(CHOOSE($D$5,ISNUMBER(F97),ISNUMBER(F98)),CHOOSE($D$5,F97,F98),"Липсва вход") -> 400 | G96: =IF(CHOOSE($D$5,ISNUMBER(G97),ISNUMBER(G98)),CHOOSE($D$5,G97,G98),"Липсва вход") -> 500 | H96: =IF(CHOOSE($D$5,ISNUMBER(H97),ISNUMBER(H98)),CHOOSE($D$5,H97,H98),"Липсва вход") -> 700
C97: 1 Каталог | D97: 200 | E97: 300 | F97: 400 | G97: 500 | H97: 700
C98: 2 Growth | D98: 200 | E98: 300 | F98: 400 | G98: 500 | H98: 700
C99: Обучение и подобрения активен | D99: =IF(CHOOSE($D$5,ISNUMBER(D100),ISNUMBER(D101)),CHOOSE($D$5,D100,D101),"Липсва вход") -> 100 | E99: =IF(CHOOSE($D$5,ISNUMBER(E100),ISNUMBER(E101)),CHOOSE($D$5,E100,E101),"Липсва вход") -> 200 | F99: =IF(CHOOSE($D$5,ISNUMBER(F100),ISNUMBER(F101)),CHOOSE($D$5,F100,F101),"Липсва вход") -> 400 | G99: =IF(CHOOSE($D$5,ISNUMBER(G100),ISNUMBER(G101)),CHOOSE($D$5,G100,G101),"Липсва вход") -> 600 | H99: =IF(CHOOSE($D$5,ISNUMBER(H100),ISNUMBER(H101)),CHOOSE($D$5,H100,H101),"Липсва вход") -> 1000
C100: 1 Каталог | D100: 100 | E100: 200 | F100: 400 | G100: 600 | H100: 1000
C101: 2 Growth | D101: 100 | E101: 200 | F101: 400 | G101: 600 | H101: 1000

Sheet Лийдове
A2: Приоритет за контактуване
A4: По желание за export от CRM. Обещани follow-ups, inbound и оферти излизат пред cold prospects. Неизвестен критерий = 0.
A6: Lead ID | B6: Бизнес | C6: Сайт | D6: Контакт | E6: Източник | F6: Проверено на | G6: Тип действие | H6: Дата за действие | I6: Подходящ | J6: Do not contact | K6: Дубликат | L6: Проблем 20 | M6: Стойност 20 | N6: Готовност 15 | O6: Решаващ 15 | P6: Fit 15 | Q6: Интерес 10 | R6: Данни 5 | S6: Score 100 | T6: Приоритет | U6: Ред за контакт | V6: Защо или какво липсва | W6: Word
S7: =IF(B7="","",SUM(L7:R7)) | T7: =IF(B7="","",IF(OR(J7="Да",K7="Да",I7<>"Да",D7="",E7="",F7=""),0,IF(AND(G7="Нов",S7<35),0,IF(AND(G7="Follow-up",ISNUMBER(H7),H7<=Допускания!$D$7),400,IF(G7="Inbound",300,IF(G7="Оферта",200,0)))+S7))) | U7: =IF(OR(B7="",T7=0),"",COUNTIFS($T$7:$T$56,">"&T7)+COUNTIFS($T$7:T7,T7)) | V7: =IF(B7="","",IF(OR(J7="Да",K7="Да"),"Изключен",IF(T7=0,"Провери fit, контакт и evidence",IF(T7>=400,"Обещан follow-up",IF(T7>=300,"Входящ интерес",IF(T7>=200,"Активна оферта",IF(S7>=75,"P1 силна нужда и fit",IF(S7>=55,"P2 нормален приоритет","P3 допълни research")))))))) | W7: =HYPERLINK("BDS_Plan.docx#S07","Scoring в Word") -> Scoring в Word
S8: =IF(B8="","",SUM(L8:R8)) | T8: =IF(B8="","",IF(OR(J8="Да",K8="Да",I8<>"Да",D8="",E8="",F8=""),0,IF(AND(G8="Нов",S8<35),0,IF(AND(G8="Follow-up",ISNUMBER(H8),H8<=Допускания!$D$7),400,IF(G8="Inbound",300,IF(G8="Оферта",200,0)))+S8))) | U8: =IF(OR(B8="",T8=0),"",COUNTIFS($T$7:$T$56,">"&T8)+COUNTIFS($T$7:T8,T8)) | V8: =IF(B8="","",IF(OR(J8="Да",K8="Да"),"Изключен",IF(T8=0,"Провери fit, контакт и evidence",IF(T8>=400,"Обещан follow-up",IF(T8>=300,"Входящ интерес",IF(T8>=200,"Активна оферта",IF(S8>=75,"P1 силна нужда и fit",IF(S8>=55,"P2 нормален приоритет","P3 допълни research")))))))) | W8: =HYPERLINK("BDS_Plan.docx#S07","Scoring в Word") -> Scoring в Word
S9: =IF(B9="","",SUM(L9:R9)) | T9: =IF(B9="","",IF(OR(J9="Да",K9="Да",I9<>"Да",D9="",E9="",F9=""),0,IF(AND(G9="Нов",S9<35),0,IF(AND(G9="Follow-up",ISNUMBER(H9),H9<=Допускания!$D$7),400,IF(G9="Inbound",300,IF(G9="Оферта",200,0)))+S9))) | U9: =IF(OR(B9="",T9=0),"",COUNTIFS($T$7:$T$56,">"&T9)+COUNTIFS($T$7:T9,T9)) | V9: =IF(B9="","",IF(OR(J9="Да",K9="Да"),"Изключен",IF(T9=0,"Провери fit, контакт и evidence",IF(T9>=400,"Обещан follow-up",IF(T9>=300,"Входящ интерес",IF(T9>=200,"Активна оферта",IF(S9>=75,"P1 силна нужда и fit",IF(S9>=55,"P2 нормален приоритет","P3 допълни research")))))))) | W9: =HYPERLINK("BDS_Plan.docx#S07","Scoring в Word") -> Scoring в Word
S10: =IF(B10="","",SUM(L10:R10)) | T10: =IF(B10="","",IF(OR(J10="Да",K10="Да",I10<>"Да",D10="",E10="",F10=""),0,IF(AND(G10="Нов",S10<35),0,IF(AND(G10="Follow-up",ISNUMBER(H10),H10<=Допускания!$D$7),400,IF(G10="Inbound",300,IF(G10="Оферта",200,0)))+S10))) | U10: =IF(OR(B10="",T10=0),"",COUNTIFS($T$7:$T$56,">"&T10)+COUNTIFS($T$7:T10,T10)) | V10: =IF(B10="","",IF(OR(J10="Да",K10="Да"),"Изключен",IF(T10=0,"Провери fit, контакт и evidence",IF(T10>=400,"Обещан follow-up",IF(T10>=300,"Входящ интерес",IF(T10>=200,"Активна оферта",IF(S10>=75,"P1 силна нужда и fit",IF(S10>=55,"P2 нормален приоритет","P3 допълни research")))))))) | W10: =HYPERLINK("BDS_Plan.docx#S07","Scoring в Word") -> Scoring в Word
S11: =IF(B11="","",SUM(L11:R11)) | T11: =IF(B11="","",IF(OR(J11="Да",K11="Да",I11<>"Да",D11="",E11="",F11=""),0,IF(AND(G11="Нов",S11<35),0,IF(AND(G11="Follow-up",ISNUMBER(H11),H11<=Допускания!$D$7),400,IF(G11="Inbound",300,IF(G11="Оферта",200,0)))+S11))) | U11: =IF(OR(B11="",T11=0),"",COUNTIFS($T$7:$T$56,">"&T11)+COUNTIFS($T$7:T11,T11)) | V11: =IF(B11="","",IF(OR(J11="Да",K11="Да"),"Изключен",IF(T11=0,"Провери fit, контакт и evidence",IF(T11>=400,"Обещан follow-up",IF(T11>=300,"Входящ интерес",IF(T11>=200,"Активна оферта",IF(S11>=75,"P1 силна нужда и fit",IF(S11>=55,"P2 нормален приоритет","P3 допълни research")))))))) | W11: =HYPERLINK("BDS_Plan.docx#S07","Scoring в Word") -> Scoring в Word
S12: =IF(B12="","",SUM(L12:R12)) | T12: =IF(B12="","",IF(OR(J12="Да",K12="Да",I12<>"Да",D12="",E12="",F12=""),0,IF(AND(G12="Нов",S12<35),0,IF(AND(G12="Follow-up",ISNUMBER(H12),H12<=Допускания!$D$7),400,IF(G12="Inbound",300,IF(G12="Оферта",200,0)))+S12))) | U12: =IF(OR(B12="",T12=0),"",COUNTIFS($T$7:$T$56,">"&T12)+COUNTIFS($T$7:T12,T12)) | V12: =IF(B12="","",IF(OR(J12="Да",K12="Да"),"Изключен",IF(T12=0,"Провери fit, контакт и evidence",IF(T12>=400,"Обещан follow-up",IF(T12>=300,"Входящ интерес",IF(T12>=200,"Активна оферта",IF(S12>=75,"P1 силна нужда и fit",IF(S12>=55,"P2 нормален приоритет","P3 допълни research")))))))) | W12: =HYPERLINK("BDS_Plan.docx#S07","Scoring в Word") -> Scoring в Word
S13: =IF(B13="","",SUM(L13:R13)) | T13: =IF(B13="","",IF(OR(J13="Да",K13="Да",I13<>"Да",D13="",E13="",F13=""),0,IF(AND(G13="Нов",S13<35),0,IF(AND(G13="Follow-up",ISNUMBER(H13),H13<=Допускания!$D$7),400,IF(G13="Inbound",300,IF(G13="Оферта",200,0)))+S13))) | U13: =IF(OR(B13="",T13=0),"",COUNTIFS($T$7:$T$56,">"&T13)+COUNTIFS($T$7:T13,T13)) | V13: =IF(B13="","",IF(OR(J13="Да",K13="Да"),"Изключен",IF(T13=0,"Провери fit, контакт и evidence",IF(T13>=400,"Обещан follow-up",IF(T13>=300,"Входящ интерес",IF(T13>=200,"Активна оферта",IF(S13>=75,"P1 силна нужда и fit",IF(S13>=55,"P2 нормален приоритет","P3 допълни research")))))))) | W13: =HYPERLINK("BDS_Plan.docx#S07","Scoring в Word") -> Scoring в Word
S14: =IF(B14="","",SUM(L14:R14)) | T14: =IF(B14="","",IF(OR(J14="Да",K14="Да",I14<>"Да",D14="",E14="",F14=""),0,IF(AND(G14="Нов",S14<35),0,IF(AND(G14="Follow-up",ISNUMBER(H14),H14<=Допускания!$D$7),400,IF(G14="Inbound",300,IF(G14="Оферта",200,0)))+S14))) | U14: =IF(OR(B14="",T14=0),"",COUNTIFS($T$7:$T$56,">"&T14)+COUNTIFS($T$7:T14,T14)) | V14: =IF(B14="","",IF(OR(J14="Да",K14="Да"),"Изключен",IF(T14=0,"Провери fit, контакт и evidence",IF(T14>=400,"Обещан follow-up",IF(T14>=300,"Входящ интерес",IF(T14>=200,"Активна оферта",IF(S14>=75,"P1 силна нужда и fit",IF(S14>=55,"P2 нормален приоритет","P3 допълни research")))))))) | W14: =HYPERLINK("BDS_Plan.docx#S07","Scoring в Word") -> Scoring в Word
S15: =IF(B15="","",SUM(L15:R15)) | T15: =IF(B15="","",IF(OR(J15="Да",K15="Да",I15<>"Да",D15="",E15="",F15=""),0,IF(AND(G15="Нов",S15<35),0,IF(AND(G15="Follow-up",ISNUMBER(H15),H15<=Допускания!$D$7),400,IF(G15="Inbound",300,IF(G15="Оферта",200,0)))+S15))) | U15: =IF(OR(B15="",T15=0),"",COUNTIFS($T$7:$T$56,">"&T15)+COUNTIFS($T$7:T15,T15)) | V15: =IF(B15="","",IF(OR(J15="Да",K15="Да"),"Изключен",IF(T15=0,"Провери fit, контакт и evidence",IF(T15>=400,"Обещан follow-up",IF(T15>=300,"Входящ интерес",IF(T15>=200,"Активна оферта",IF(S15>=75,"P1 силна нужда и fit",IF(S15>=55,"P2 нормален приоритет","P3 допълни research")))))))) | W15: =HYPERLINK("BDS_Plan.docx#S07","Scoring в Word") -> Scoring в Word
S16: =IF(B16="","",SUM(L16:R16)) | T16: =IF(B16="","",IF(OR(J16="Да",K16="Да",I16<>"Да",D16="",E16="",F16=""),0,IF(AND(G16="Нов",S16<35),0,IF(AND(G16="Follow-up",ISNUMBER(H16),H16<=Допускания!$D$7),400,IF(G16="Inbound",300,IF(G16="Оферта",200,0)))+S16))) | U16: =IF(OR(B16="",T16=0),"",COUNTIFS($T$7:$T$56,">"&T16)+COUNTIFS($T$7:T16,T16)) | V16: =IF(B16="","",IF(OR(J16="Да",K16="Да"),"Изключен",IF(T16=0,"Провери fit, контакт и evidence",IF(T16>=400,"Обещан follow-up",IF(T16>=300,"Входящ интерес",IF(T16>=200,"Активна оферта",IF(S16>=75,"P1 силна нужда и fit",IF(S16>=55,"P2 нормален приоритет","P3 допълни research")))))))) | W16: =HYPERLINK("BDS_Plan.docx#S07","Scoring в Word") -> Scoring в Word
S17: =IF(B17="","",SUM(L17:R17)) | T17: =IF(B17="","",IF(OR(J17="Да",K17="Да",I17<>"Да",D17="",E17="",F17=""),0,IF(AND(G17="Нов",S17<35),0,IF(AND(G17="Follow-up",ISNUMBER(H17),H17<=Допускания!$D$7),400,IF(G17="Inbound",300,IF(G17="Оферта",200,0)))+S17))) | U17: =IF(OR(B17="",T17=0),"",COUNTIFS($T$7:$T$56,">"&T17)+COUNTIFS($T$7:T17,T17)) | V17: =IF(B17="","",IF(OR(J17="Да",K17="Да"),"Изключен",IF(T17=0,"Провери fit, контакт и evidence",IF(T17>=400,"Обещан follow-up",IF(T17>=300,"Входящ интерес",IF(T17>=200,"Активна оферта",IF(S17>=75,"P1 силна нужда и fit",IF(S17>=55,"P2 нормален приоритет","P3 допълни research")))))))) | W17: =HYPERLINK("BDS_Plan.docx#S07","Scoring в Word") -> Scoring в Word
S18: =IF(B18="","",SUM(L18:R18)) | T18: =IF(B18="","",IF(OR(J18="Да",K18="Да",I18<>"Да",D18="",E18="",F18=""),0,IF(AND(G18="Нов",S18<35),0,IF(AND(G18="Follow-up",ISNUMBER(H18),H18<=Допускания!$D$7),400,IF(G18="Inbound",300,IF(G18="Оферта",200,0)))+S18))) | U18: =IF(OR(B18="",T18=0),"",COUNTIFS($T$7:$T$56,">"&T18)+COUNTIFS($T$7:T18,T18)) | V18: =IF(B18="","",IF(OR(J18="Да",K18="Да"),"Изключен",IF(T18=0,"Провери fit, контакт и evidence",IF(T18>=400,"Обещан follow-up",IF(T18>=300,"Входящ интерес",IF(T18>=200,"Активна оферта",IF(S18>=75,"P1 силна нужда и fit",IF(S18>=55,"P2 нормален приоритет","P3 допълни research")))))))) | W18: =HYPERLINK("BDS_Plan.docx#S07","Scoring в Word") -> Scoring в Word
... S56: =IF(B56="","",SUM(L56:R56)) | T56: =IF(B56="","",IF(OR(J56="Да",K56="Да",I56<>"Да",D56="",E56="",F56=""),0,IF(AND(G56="Нов",S56<35),0,IF(AND(G56="Follow-up",ISNUMBER(H56),H56<=Допускания!$D$7),400,IF(G56="Inbound",300,IF(G56="Оферта",200,0)))+S56))) | U56: =IF(OR(B56="",T56=0),"",COUNTIFS($T$7:$T$56,">"&T56)+COUNTIFS($T$7:T56,T56)) | V56: =IF(B56="","",IF(OR(J56="Да",K56="Да"),"Изключен",IF(T56=0,"Провери fit, контакт и evidence",IF(T56>=400,"Обещан follow-up",IF(T56>=300,"Входящ интерес",IF(T56>=200,"Активна оферта",IF(S56>=75,"P1 силна нужда и fit",IF(S56>=55,"P2 нормален приоритет","P3 допълни research")))))))) | W56: =HYPERLINK("BDS_Plan.docx#S07","Scoring в Word") -> Scoring в Word
